Workbook

Sheet Budget
A1: Family Budget Planner - | D1: ='Section-Category'!D1 -> 2026
A2: Starting Balance:
A3: 1776341.3
B4: AG | C4: AF | D4: AG | E4: AF | F4: AH | G4: AF | H4: AF | I4: AF | J4: AF | K4: AG | L4: AF | M4: AG
A5: Goal: Saving For My Daughter
A6: Summary | B6: Jan | C6: Feb | D6: Mar | E6: Apr | F6: May | G6: Jun | H6: Jul | I6: Aug | J6: Sep | K6: Oct | L6: Nov | M6: Dec | N6: Total | O6: Avg
A7: BUDGET REMINDER
A8: Balance I Can Used (Bank) | O8: =SUM(C8:N8) -> 0
A9: Balance I have Left (Bank) | B9: =IF(OR(B$8="#",TRIM(B$18)="0"),"0",B8-B17) -> 0 | C9: =IF(OR(C$8="#",TRIM(C$18)="0"),"0",C8-C17) -> 0 | D9: =IF(OR(D$8="#",TRIM(D$18)="0"),"0",D8-D17) -> 0 | E9: =IF(OR(E$8="#",TRIM(E$18)="0"),"0",E8-E17) -> 0 | F9: =F8-F17 -> 0 | G9: =IF(OR(G$8="#",TRIM(G$18)="0"),"0",G8-G17) -> 0 | H9: =IF(OR(H$8="#",TRIM(H$18)="0"),"0",H8-H17) -> 0 | I9: =IF(OR(I$8="#",TRIM(I$18)="0"),"0",I8-I17) -> 0 | J9: =IF(OR(J$8="#",TRIM(J$18)="0"),"0",J8-J17) -> 0 | K9: =IF(OR(K$8="#",TRIM(K$18)="0"),"0",K8-K17) -> 0 | L9: =IF(OR(L$8="#",TRIM(L$18)="0"),"0",L8-L17) -> 0 | M9: =IF(OR(M$8="#",TRIM(M$18)="0"),"0",M8-M17) -> 0 | N9: =IF(OR(N$8="#",TRIM(N$18)="0"),"-",N8-N17) -> - | O9: =SUM(C9:N9) -> 0
A10: PETTY CASH
A11: Petty Cash | N11: =SUM(B11:M11) -> 0 | O11: =SUM(C11:N11) -> 0
A12: Petty Cash Used | B12: =IF(TRIM(B$54)="0","0",B54) -> 0 | C12: =IF(TRIM(C$54)="0","0",C54) -> 0 | D12: =IF(TRIM(D$54)="0","0",D54) -> 0 | E12: =IF(TRIM(E$54)="0","0",E54) -> 0 | F12: =IF(TRIM(F$54)="0","0",F54) -> 0 | G12: =IF(TRIM(G$54)="0","0",G54) -> 0 | H12: =IF(TRIM(H$54)="0","0",H54) -> 0 | I12: =IF(TRIM(I$54)="0","0",I54) -> 0 | ... M12: =IF(TRIM(M$54)="0","0",M54) -> 0 | N12: =SUM(B12:M12) -> 0 | O12: =SUM(C12:N12) -> 0
A14: Current Balance (Petty Cash) | B14: =IF(TRIM(B$11)="0","",B11-B12) -> 0 | C14: =IF(TRIM(C$11)="0","",C11-C12) -> 0 | D14: =IF(TRIM(D$11)="0","",D11-D12) -> 0 | E14: =IF(TRIM(E$11)="0","",E11-E12) -> 0 | F14: =IF(TRIM(F$11)="0","",F11-F12) -> 0 | G14: =IF(TRIM(G$11)="0","",G11-G12) -> 0 | H14: =IF(TRIM(H$11)="0","",H11-H12) -> 0 | I14: =IF(TRIM(I$11)="0","",I11-I12) -> 0 | ... N14: =IF(TRIM(N$11)="0","",N11-N12) | O14: =O11-O12 -> 0
A15: BANK
A16: Total Income | B16: =B43 -> 0 | C16: =C43 -> 0 | D16: =D43 -> 0 | E16: =E43 -> 0 | F16: =F43 -> 0 | G16: =G43 -> 0 | H16: =H43 -> 0 | I16: =I43 -> 0 | ... M16: =M43 -> 0 | N16: =SUM(B16:M16) -> 0 | O16: =N16/COLUMNS(B16:M16) -> 0
A17: Total Expenses | B17: =B63+B80+B94+B106+B116+B125+B134+B142+B150+B158+B173+B181+B191+B201+B210 -> 0 | C17: =C63+C80+C94+C106+C116+C125+C134+C142+C150+C158+C173+C181+C191+C201+C210 -> 0 | D17: =D63+D80+D94+D106+D116+D125+D134+D142+D150+D158+D173+D181+D191+D201+D210 -> 0 | E17: =E63+E80+E94+E106+E116+E125+E134+E142+E150+E158+E173+E181+E191+E201+E210 -> 0 | F17: =F63+F80+F94+F106+F116+F125+F134+F142+F150+F158+F173+F181+F191+F201+F210 -> 0 | G17: =G63+G80+G94+G106+G116+G125+G134+G142+G150+G158+G173+G181+G191+G201+G210 -> 0 | H17: =H63+H80+H94+H106+H116+H125+H134+H142+H150+H158+H173+H181+H191+H201+H210 -> 0 | I17: =I63+I80+I94+I106+I116+I125+I134+I142+I150+I158+I173+I181+I191+I201+I210 -> 0 | ... M17: =M63+M80+M94+M106+M116+M125+M134+M142+M150+M158+M173+M181+M191+M201+M210 -> 0 | N17: =SUM(B17:M17) -> 0 | O17: =N17/COLUMNS(B17:M17) -> 0
A18: NET (Income - Expenses) | B18: =B16-B17 -> 0 | C18: =C16-C17 -> 0 | D18: =D16-D17 -> 0 | E18: =E16-E17 -> 0 | F18: =F16-F17 -> 0 | G18: =G16-G17 -> 0 | H18: =H16-H17 -> 0 | I18: =I16-I17 -> 0 | ... M18: =M16-M17 -> 0 | N18: =SUM(B18:M18) -> 0 | O18: =N18/COLUMNS(B18:M18) -> 0
A20: Current Balance (In Bank) | B20: =A3+B18 -> 1776341.3 | C20: =B21+C18 -> 1776341.3 | D20: =C21+D18 -> 1776341.3 | E20: =D21+E18 -> 1776341.3 | F20: =IF(F$11=0,"-",E20+F18) -> - | G20: =IF(G$11=0,"-",F20+G18) -> - | H20: =IF(H$11=0,"-",G20+H18) -> - | I20: =IF(I$11=0,"-",H20+I18) -> - | J20: =IF(J$11=0,"-",I20+J18) -> - | K20: =IF(K$11=0,"-",J20+K18) -> - | L20: =IF(L$11=0,"-",K20+L18) -> - | M20: =IF(M$11=0,"-",L20+M18) -> -
A21: Saving Total (Cash + Bank) | B21: =B20+B14 -> 1776341.3 | C21: =C20+C14 -> 1776341.3 | D21: =D20+D14 -> 1776341.3 | E21: =E20+E14 -> 1776341.3 | F21: =F20+F14 -> #VALUE! | G21: =IF(G$11=0,"-",G14+G20) -> - | H21: =IF(H$11=0,"-",H14+H20) -> - | I21: =IF(I$11=0,"-",I14+I20) -> - | J21: =IF(J$11=0,"-",J14+J20) -> - | K21: =IF(K$11=0,"-",K14+K20) -> - | L21: =IF(L$11=0,"-",L14+L20) -> - | M21: =IF(M$11=0,"-",M14+M20) -> -
A35: ='Section-Category'!A1 -> INCOME | B35: =B$6 -> Jan | C35: =C$6 -> Feb | D35: =D$6 -> Mar | E35: =E$6 -> Apr | F35: =F$6 -> May | G35: =G$6 -> Jun | H35: =H$6 -> Jul | I35: =I$6 -> Aug | ... M35: =M$6 -> Dec | N35: Total | O35: Avg
A36: ='Section-Category'!A2 -> Wages & Tips | B36: {=IF(OR(TRIM(INDIRECT("'"&B$6&"'!"&B$4&ROW()-31))="0",INDIRECT("'"&B$6&"'!"&B$4&ROW()-31)="",NOT(ISNUMBER(INDIRECT("'"&B$6&"'!"&B$4&ROW()-31)))),"-",INDIRECT("'"&B$6&"'!"&B$4&ROW()-31))} -> - | C36: {=IF(OR(TRIM(INDIRECT("'"&C$6&"'!"&C$4&ROW()-31))="0",INDIRECT("'"&C$6&"'!"&C$4&ROW()-31)="",NOT(ISNUMBER(INDIRECT("'"&C$6&"'!"&C$4&ROW()-31)))),"-",INDIRECT("'"&C$6&"'!"&C$4&ROW()-31))} -> - | D36: {=IF(OR(TRIM(INDIRECT("'"&D$6&"'!"&D$4&ROW()-31))="0",INDIRECT("'"&D$6&"'!"&D$4&ROW()-31)="",NOT(ISNUMBER(INDIRECT("'"&D$6&"'!"&D$4&ROW()-31)))),"-",INDIRECT("'"&D$6&"'!"&D$4&ROW()-31))} -> - | E36: {=IF(OR(TRIM(INDIRECT("'"&E$6&"'!"&E$4&ROW()-31))="0",INDIRECT("'"&E$6&"'!"&E$4&ROW()-31)="",NOT(ISNUMBER(INDIRECT("'"&E$6&"'!"&E$4&ROW()-31)))),"-",INDIRECT("'"&E$6&"'!"&E$4&ROW()-31))} -> - | F36: {=IF(OR(TRIM(INDIRECT("'"&F$6&"'!"&F$4&ROW()-31))="0",INDIRECT("'"&F$6&"'!"&F$4&ROW()-31)="",NOT(ISNUMBER(INDIRECT("'"&F$6&"'!"&F$4&ROW()-31)))),"-",INDIRECT("'"&F$6&"'!"&F$4&ROW()-31))} -> - | G36: {=IF(OR(TRIM(INDIRECT("'"&G$6&"'!"&G$4&ROW()-31))="0",INDIRECT("'"&G$6&"'!"&G$4&ROW()-31)="",NOT(ISNUMBER(INDIRECT("'"&G$6&"'!"&G$4&ROW()-31)))),"-",INDIRECT("'"&G$6&"'!"&G$4&ROW()-31))} -> - | H36: {=IF(OR(TRIM(INDIRECT("'"&H$6&"'!"&H$4&ROW()-31))="0",INDIRECT("'"&H$6&"'!"&H$4&ROW()-31)="",NOT(ISNUMBER(INDIRECT("'"&H$6&"'!"&H$4&ROW()-31)))),"-",INDIRECT("'"&H$6&"'!"&H$4&ROW()-31))} -> - | I36: {=IF(OR(TRIM(INDIRECT("'"&I$6&"'!"&I$4&ROW()-31))="0",INDIRECT("'"&I$6&"'!"&I$4&ROW()-31)="",NOT(ISNUMBER(INDIRECT("'"&I$6&"'!"&I$4&ROW()-31)))),"-",INDIRECT("'"&I$6&"'!"&I$4&ROW()-31))} -> - | ... M36: {=IF(OR(TRIM(INDIRECT("'"&M$6&"'!"&M$4&ROW()-31))="0",INDIRECT("'"&M$6&"'!"&M$4&ROW()-31)="",NOT(ISNUMBER(INDIRECT("'"&M$6&"'!"&M$4&ROW()-31)))),"-",INDIRECT("'"&M$6&"'!"&M$4&ROW()-31))} -> - | N36: =SUM(B36:M36) -> 0 | O36: =N36/COLUMNS(B36:M36) -> 0
A37: ='Section-Category'!A3 -> Interest Income | B37: {=IF(OR(TRIM(INDIRECT("'"&B$6&"'!"&B$4&ROW()-31))="0",INDIRECT("'"&B$6&"'!"&B$4&ROW()-31)="",NOT(ISNUMBER(INDIRECT("'"&B$6&"'!"&B$4&ROW()-31)))),"-",INDIRECT("'"&B$6&"'!"&B$4&ROW()-31))} -> - | C37: {=IF(OR(TRIM(INDIRECT("'"&C$6&"'!"&C$4&ROW()-31))="0",INDIRECT("'"&C$6&"'!"&C$4&ROW()-31)="",NOT(ISNUMBER(INDIRECT("'"&C$6&"'!"&C$4&ROW()-31)))),"-",INDIRECT("'"&C$6&"'!"&C$4&ROW()-31))} -> - | D37: {=IF(OR(TRIM(INDIRECT("'"&D$6&"'!"&D$4&ROW()-31))="0",INDIRECT("'"&D$6&"'!"&D$4&ROW()-31)="",NOT(ISNUMBER(INDIRECT("'"&D$6&"'!"&D$4&ROW()-31)))),"-",INDIRECT("'"&D$6&"'!"&D$4&ROW()-31))} -> - | E37: {=IF(OR(TRIM(INDIRECT("'"&E$6&"'!"&E$4&ROW()-31))="0",INDIRECT("'"&E$6&"'!"&E$4&ROW()-31)="",NOT(ISNUMBER(INDIRECT("'"&E$6&"'!"&E$4&ROW()-31)))),"-",INDIRECT("'"&E$6&"'!"&E$4&ROW()-31))} -> - | F37: {=IF(OR(TRIM(INDIRECT("'"&F$6&"'!"&F$4&ROW()-31))="0",INDIRECT("'"&F$6&"'!"&F$4&ROW()-31)="",NOT(ISNUMBER(INDIRECT("'"&F$6&"'!"&F$4&ROW()-31)))),"-",INDIRECT("'"&F$6&"'!"&F$4&ROW()-31))} -> - | G37: {=IF(OR(TRIM(INDIRECT("'"&G$6&"'!"&G$4&ROW()-31))="0",INDIRECT("'"&G$6&"'!"&G$4&ROW()-31)="",NOT(ISNUMBER(INDIRECT("'"&G$6&"'!"&G$4&ROW()-31)))),"-",INDIRECT("'"&G$6&"'!"&G$4&ROW()-31))} -> - | H37: {=IF(OR(TRIM(INDIRECT("'"&H$6&"'!"&H$4&ROW()-31))="0",INDIRECT("'"&H$6&"'!"&H$4&ROW()-31)="",NOT(ISNUMBER(INDIRECT("'"&H$6&"'!"&H$4&ROW()-31)))),"-",INDIRECT("'"&H$6&"'!"&H$4&ROW()-31))} -> - | I37: {=IF(OR(TRIM(INDIRECT("'"&I$6&"'!"&I$4&ROW()-31))="0",INDIRECT("'"&I$6&"'!"&I$4&ROW()-31)="",NOT(ISNUMBER(INDIRECT("'"&I$6&"'!"&I$4&ROW()-31)))),"-",INDIRECT("'"&I$6&"'!"&I$4&ROW()-31))} -> - | ... M37: {=IF(OR(TRIM(INDIRECT("'"&M$6&"'!"&M$4&ROW()-31))="0",INDIRECT("'"&M$6&"'!"&M$4&ROW()-31)="",NOT(ISNUMBER(INDIRECT("'"&M$6&"'!"&M$4&ROW()-31)))),"-",INDIRECT("'"&M$6&"'!"&M$4&ROW()-31))} -> - | N37: =SUM(B37:M37) -> 0 | O37: =N37/COLUMNS(B37:M37) -> 0
A38: ='Section-Category'!A4 -> Dividends | B38: {=IF(OR(TRIM(INDIRECT("'"&B$6&"'!"&B$4&ROW()-31))="0",INDIRECT("'"&B$6&"'!"&B$4&ROW()-31)="",NOT(ISNUMBER(INDIRECT("'"&B$6&"'!"&B$4&ROW()-31)))),"-",INDIRECT("'"&B$6&"'!"&B$4&ROW()-31))} -> - | C38: {=IF(OR(TRIM(INDIRECT("'"&C$6&"'!"&C$4&ROW()-31))="0",INDIRECT("'"&C$6&"'!"&C$4&ROW()-31)="",NOT(ISNUMBER(INDIRECT("'"&C$6&"'!"&C$4&ROW()-31)))),"-",INDIRECT("'"&C$6&"'!"&C$4&ROW()-31))} -> - | D38: {=IF(OR(TRIM(INDIRECT("'"&D$6&"'!"&D$4&ROW()-31))="0",INDIRECT("'"&D$6&"'!"&D$4&ROW()-31)="",NOT(ISNUMBER(INDIRECT("'"&D$6&"'!"&D$4&ROW()-31)))),"-",INDIRECT("'"&D$6&"'!"&D$4&ROW()-31))} -> - | E38: {=IF(OR(TRIM(INDIRECT("'"&E$6&"'!"&E$4&ROW()-31))="0",INDIRECT("'"&E$6&"'!"&E$4&ROW()-31)="",NOT(ISNUMBER(INDIRECT("'"&E$6&"'!"&E$4&ROW()-31)))),"-",INDIRECT("'"&E$6&"'!"&E$4&ROW()-31))} -> - | F38: {=IF(OR(TRIM(INDIRECT("'"&F$6&"'!"&F$4&ROW()-31))="0",INDIRECT("'"&F$6&"'!"&F$4&ROW()-31)="",NOT(ISNUMBER(INDIRECT("'"&F$6&"'!"&F$4&ROW()-31)))),"-",INDIRECT("'"&F$6&"'!"&F$4&ROW()-31))} -> - | G38: {=IF(OR(TRIM(INDIRECT("'"&G$6&"'!"&G$4&ROW()-31))="0",INDIRECT("'"&G$6&"'!"&G$4&ROW()-31)="",NOT(ISNUMBER(INDIRECT("'"&G$6&"'!"&G$4&ROW()-31)))),"-",INDIRECT("'"&G$6&"'!"&G$4&ROW()-31))} -> - | H38: {=IF(OR(TRIM(INDIRECT("'"&H$6&"'!"&H$4&ROW()-31))="0",INDIRECT("'"&H$6&"'!"&H$4&ROW()-31)="",NOT(ISNUMBER(INDIRECT("'"&H$6&"'!"&H$4&ROW()-31)))),"-",INDIRECT("'"&H$6&"'!"&H$4&ROW()-31))} -> - | I38: {=IF(OR(TRIM(INDIRECT("'"&I$6&"'!"&I$4&ROW()-31))="0",INDIRECT("'"&I$6&"'!"&I$4&ROW()-31)="",NOT(ISNUMBER(INDIRECT("'"&I$6&"'!"&I$4&ROW()-31)))),"-",INDIRECT("'"&I$6&"'!"&I$4&ROW()-31))} -> - | ... M38: {=IF(OR(TRIM(INDIRECT("'"&M$6&"'!"&M$4&ROW()-31))="0",INDIRECT("'"&M$6&"'!"&M$4&ROW()-31)="",NOT(ISNUMBER(INDIRECT("'"&M$6&"'!"&M$4&ROW()-31)))),"-",INDIRECT("'"&M$6&"'!"&M$4&ROW()-31))} -> - | N38: =SUM(B38:M38) -> 0 | O38: =N38/COLUMNS(B38:M38) -> 0
A39: ='Section-Category'!A5 -> Gifts Received | B39: {=IF(OR(TRIM(INDIRECT("'"&B$6&"'!"&B$4&ROW()-31))="0",INDIRECT("'"&B$6&"'!"&B$4&ROW()-31)="",NOT(ISNUMBER(INDIRECT("'"&B$6&"'!"&B$4&ROW()-31)))),"-",INDIRECT("'"&B$6&"'!"&B$4&ROW()-31))} -> - | C39: {=IF(OR(TRIM(INDIRECT("'"&C$6&"'!"&C$4&ROW()-31))="0",INDIRECT("'"&C$6&"'!"&C$4&ROW()-31)="",NOT(ISNUMBER(INDIRECT("'"&C$6&"'!"&C$4&ROW()-31)))),"-",INDIRECT("'"&C$6&"'!"&C$4&ROW()-31))} -> - | D39: {=IF(OR(TRIM(INDIRECT("'"&D$6&"'!"&D$4&ROW()-31))="0",INDIRECT("'"&D$6&"'!"&D$4&ROW()-31)="",NOT(ISNUMBER(INDIRECT("'"&D$6&"'!"&D$4&ROW()-31)))),"-",INDIRECT("'"&D$6&"'!"&D$4&ROW()-31))} -> - | E39: {=IF(OR(TRIM(INDIRECT("'"&E$6&"'!"&E$4&ROW()-31))="0",INDIRECT("'"&E$6&"'!"&E$4&ROW()-31)="",NOT(ISNUMBER(INDIRECT("'"&E$6&"'!"&E$4&ROW()-31)))),"-",INDIRECT("'"&E$6&"'!"&E$4&ROW()-31))} -> - | F39: {=IF(OR(TRIM(INDIRECT("'"&F$6&"'!"&F$4&ROW()-31))="0",INDIRECT("'"&F$6&"'!"&F$4&ROW()-31)="",NOT(ISNUMBER(INDIRECT("'"&F$6&"'!"&F$4&ROW()-31)))),"-",INDIRECT("'"&F$6&"'!"&F$4&ROW()-31))} -> - | G39: {=IF(OR(TRIM(INDIRECT("'"&G$6&"'!"&G$4&ROW()-31))="0",INDIRECT("'"&G$6&"'!"&G$4&ROW()-31)="",NOT(ISNUMBER(INDIRECT("'"&G$6&"'!"&G$4&ROW()-31)))),"-",INDIRECT("'"&G$6&"'!"&G$4&ROW()-31))} -> - | H39: {=IF(OR(TRIM(INDIRECT("'"&H$6&"'!"&H$4&ROW()-31))="0",INDIRECT("'"&H$6&"'!"&H$4&ROW()-31)="",NOT(ISNUMBER(INDIRECT("'"&H$6&"'!"&H$4&ROW()-31)))),"-",INDIRECT("'"&H$6&"'!"&H$4&ROW()-31))} -> - | I39: {=IF(OR(TRIM(INDIRECT("'"&I$6&"'!"&I$4&ROW()-31))="0",INDIRECT("'"&I$6&"'!"&I$4&ROW()-31)="",NOT(ISNUMBER(INDIRECT("'"&I$6&"'!"&I$4&ROW()-31)))),"-",INDIRECT("'"&I$6&"'!"&I$4&ROW()-31))} -> - | ... M39: {=IF(OR(TRIM(INDIRECT("'"&M$6&"'!"&M$4&ROW()-31))="0",INDIRECT("'"&M$6&"'!"&M$4&ROW()-31)="",NOT(ISNUMBER(INDIRECT("'"&M$6&"'!"&M$4&ROW()-31)))),"-",INDIRECT("'"&M$6&"'!"&M$4&ROW()-31))} -> - | N39: =SUM(B39:M39) -> 0 | O39: =N39/COLUMNS(B39:M39) -> 0
A40: ='Section-Category'!A6 -> Refunds/Reimbursements | B40: {=IF(OR(TRIM(INDIRECT("'"&B$6&"'!"&B$4&ROW()-31))="0",INDIRECT("'"&B$6&"'!"&B$4&ROW()-31)="",NOT(ISNUMBER(INDIRECT("'"&B$6&"'!"&B$4&ROW()-31)))),"-",INDIRECT("'"&B$6&"'!"&B$4&ROW()-31))} -> - | C40: {=IF(OR(TRIM(INDIRECT("'"&C$6&"'!"&C$4&ROW()-31))="0",INDIRECT("'"&C$6&"'!"&C$4&ROW()-31)="",NOT(ISNUMBER(INDIRECT("'"&C$6&"'!"&C$4&ROW()-31)))),"-",INDIRECT("'"&C$6&"'!"&C$4&ROW()-31))} -> - | D40: {=IF(OR(TRIM(INDIRECT("'"&D$6&"'!"&D$4&ROW()-31))="0",INDIRECT("'"&D$6&"'!"&D$4&ROW()-31)="",NOT(ISNUMBER(INDIRECT("'"&D$6&"'!"&D$4&ROW()-31)))),"-",INDIRECT("'"&D$6&"'!"&D$4&ROW()-31))} -> - | E40: {=IF(OR(TRIM(INDIRECT("'"&E$6&"'!"&E$4&ROW()-31))="0",INDIRECT("'"&E$6&"'!"&E$4&ROW()-31)="",NOT(ISNUMBER(INDIRECT("'"&E$6&"'!"&E$4&ROW()-31)))),"-",INDIRECT("'"&E$6&"'!"&E$4&ROW()-31))} -> - | F40: {=IF(OR(TRIM(INDIRECT("'"&F$6&"'!"&F$4&ROW()-31))="0",INDIRECT("'"&F$6&"'!"&F$4&ROW()-31)="",NOT(ISNUMBER(INDIRECT("'"&F$6&"'!"&F$4&ROW()-31)))),"-",INDIRECT("'"&F$6&"'!"&F$4&ROW()-31))} -> - | G40: {=IF(OR(TRIM(INDIRECT("'"&G$6&"'!"&G$4&ROW()-31))="0",INDIRECT("'"&G$6&"'!"&G$4&ROW()-31)="",NOT(ISNUMBER(INDIRECT("'"&G$6&"'!"&G$4&ROW()-31)))),"-",INDIRECT("'"&G$6&"'!"&G$4&ROW()-31))} -> - | H40: {=IF(OR(TRIM(INDIRECT("'"&H$6&"'!"&H$4&ROW()-31))="0",INDIRECT("'"&H$6&"'!"&H$4&ROW()-31)="",NOT(ISNUMBER(INDIRECT("'"&H$6&"'!"&H$4&ROW()-31)))),"-",INDIRECT("'"&H$6&"'!"&H$4&ROW()-31))} -> - | I40: {=IF(OR(TRIM(INDIRECT("'"&I$6&"'!"&I$4&ROW()-31))="0",INDIRECT("'"&I$6&"'!"&I$4&ROW()-31)="",NOT(ISNUMBER(INDIRECT("'"&I$6&"'!"&I$4&ROW()-31)))),"-",INDIRECT("'"&I$6&"'!"&I$4&ROW()-31))} -> - | ... M40: {=IF(OR(TRIM(INDIRECT("'"&M$6&"'!"&M$4&ROW()-31))="0",INDIRECT("'"&M$6&"'!"&M$4&ROW()-31)="",NOT(ISNUMBER(INDIRECT("'"&M$6&"'!"&M$4&ROW()-31)))),"-",INDIRECT("'"&M$6&"'!"&M$4&ROW()-31))} -> - | N40: =SUM(B40:M40) -> 0 | O40: =N40/COLUMNS(B40:M40) -> 0
A41: ='Section-Category'!A7 -> Other | B41: {=IF(OR(TRIM(INDIRECT("'"&B$6&"'!"&B$4&ROW()-31))="0",INDIRECT("'"&B$6&"'!"&B$4&ROW()-31)="",NOT(ISNUMBER(INDIRECT("'"&B$6&"'!"&B$4&ROW()-31)))),"-",INDIRECT("'"&B$6&"'!"&B$4&ROW()-31))} -> - | C41: {=IF(OR(TRIM(INDIRECT("'"&C$6&"'!"&C$4&ROW()-31))="0",INDIRECT("'"&C$6&"'!"&C$4&ROW()-31)="",NOT(ISNUMBER(INDIRECT("'"&C$6&"'!"&C$4&ROW()-31)))),"-",INDIRECT("'"&C$6&"'!"&C$4&ROW()-31))} -> - | D41: {=IF(OR(TRIM(INDIRECT("'"&D$6&"'!"&D$4&ROW()-31))="0",INDIRECT("'"&D$6&"'!"&D$4&ROW()-31)="",NOT(ISNUMBER(INDIRECT("'"&D$6&"'!"&D$4&ROW()-31)))),"-",INDIRECT("'"&D$6&"'!"&D$4&ROW()-31))} -> - | E41: {=IF(OR(TRIM(INDIRECT("'"&E$6&"'!"&E$4&ROW()-31))="0",INDIRECT("'"&E$6&"'!"&E$4&ROW()-31)="",NOT(ISNUMBER(INDIRECT("'"&E$6&"'!"&E$4&ROW()-31)))),"-",INDIRECT("'"&E$6&"'!"&E$4&ROW()-31))} -> - | F41: {=IF(OR(TRIM(INDIRECT("'"&F$6&"'!"&F$4&ROW()-31))="0",INDIRECT("'"&F$6&"'!"&F$4&ROW()-31)="",NOT(ISNUMBER(INDIRECT("'"&F$6&"'!"&F$4&ROW()-31)))),"-",INDIRECT("'"&F$6&"'!"&F$4&ROW()-31))} -> - | G41: {=IF(OR(TRIM(INDIRECT("'"&G$6&"'!"&G$4&ROW()-31))="0",INDIRECT("'"&G$6&"'!"&G$4&ROW()-31)="",NOT(ISNUMBER(INDIRECT("'"&G$6&"'!"&G$4&ROW()-31)))),"-",INDIRECT("'"&G$6&"'!"&G$4&ROW()-31))} -> - | H41: {=IF(OR(TRIM(INDIRECT("'"&H$6&"'!"&H$4&ROW()-31))="0",INDIRECT("'"&H$6&"'!"&H$4&ROW()-31)="",NOT(ISNUMBER(INDIRECT("'"&H$6&"'!"&H$4&ROW()-31)))),"-",INDIRECT("'"&H$6&"'!"&H$4&ROW()-31))} -> - | I41: {=IF(OR(TRIM(INDIRECT("'"&I$6&"'!"&I$4&ROW()-31))="0",INDIRECT("'"&I$6&"'!"&I$4&ROW()-31)="",NOT(ISNUMBER(INDIRECT("'"&I$6&"'!"&I$4&ROW()-31)))),"-",INDIRECT("'"&I$6&"'!"&I$4&ROW()-31))} -> - | ... M41: {=IF(OR(TRIM(INDIRECT("'"&M$6&"'!"&M$4&ROW()-31))="0",INDIRECT("'"&M$6&"'!"&M$4&ROW()-31)="",NOT(ISNUMBER(INDIRECT("'"&M$6&"'!"&M$4&ROW()-31)))),"-",INDIRECT("'"&M$6&"'!"&M$4&ROW()-31))} -> - | N41: =SUM(B41:M41) -> 0 | O41: =N41/COLUMNS(B41:M41) -> 0
A42: ='Section-Category'!A8 -> Transfer From Savings | B42: {=IF(OR(TRIM(INDIRECT("'"&B$6&"'!"&B$4&ROW()-31))="0",INDIRECT("'"&B$6&"'!"&B$4&ROW()-31)="",NOT(ISNUMBER(INDIRECT("'"&B$6&"'!"&B$4&ROW()-31)))),"-",INDIRECT("'"&B$6&"'!"&B$4&ROW()-31))} -> - | C42: {=IF(OR(TRIM(INDIRECT("'"&C$6&"'!"&C$4&ROW()-31))="0",INDIRECT("'"&C$6&"'!"&C$4&ROW()-31)="",NOT(ISNUMBER(INDIRECT("'"&C$6&"'!"&C$4&ROW()-31)))),"-",INDIRECT("'"&C$6&"'!"&C$4&ROW()-31))} -> - | D42: {=IF(OR(TRIM(INDIRECT("'"&D$6&"'!"&D$4&ROW()-31))="0",INDIRECT("'"&D$6&"'!"&D$4&ROW()-31)="",NOT(ISNUMBER(INDIRECT("'"&D$6&"'!"&D$4&ROW()-31)))),"-",INDIRECT("'"&D$6&"'!"&D$4&ROW()-31))} -> - | E42: {=IF(OR(TRIM(INDIRECT("'"&E$6&"'!"&E$4&ROW()-31))="0",INDIRECT("'"&E$6&"'!"&E$4&ROW()-31)="",NOT(ISNUMBER(INDIRECT("'"&E$6&"'!"&E$4&ROW()-31)))),"-",INDIRECT("'"&E$6&"'!"&E$4&ROW()-31))} -> - | F42: {=IF(OR(TRIM(INDIRECT("'"&F$6&"'!"&F$4&ROW()-31))="0",INDIRECT("'"&F$6&"'!"&F$4&ROW()-31)="",NOT(ISNUMBER(INDIRECT("'"&F$6&"'!"&F$4&ROW()-31)))),"-",INDIRECT("'"&F$6&"'!"&F$4&ROW()-31))} -> - | G42: {=IF(OR(TRIM(INDIRECT("'"&G$6&"'!"&G$4&ROW()-31))="0",INDIRECT("'"&G$6&"'!"&G$4&ROW()-31)="",NOT(ISNUMBER(INDIRECT("'"&G$6&"'!"&G$4&ROW()-31)))),"-",INDIRECT("'"&G$6&"'!"&G$4&ROW()-31))} -> - | H42: {=IF(OR(TRIM(INDIRECT("'"&H$6&"'!"&H$4&ROW()-31))="0",INDIRECT("'"&H$6&"'!"&H$4&ROW()-31)="",NOT(ISNUMBER(INDIRECT("'"&H$6&"'!"&H$4&ROW()-31)))),"-",INDIRECT("'"&H$6&"'!"&H$4&ROW()-31))} -> - | I42: {=IF(OR(TRIM(INDIRECT("'"&I$6&"'!"&I$4&ROW()-31))="0",INDIRECT("'"&I$6&"'!"&I$4&ROW()-31)="",NOT(ISNUMBER(INDIRECT("'"&I$6&"'!"&I$4&ROW()-31)))),"-",INDIRECT("'"&I$6&"'!"&I$4&ROW()-31))} -> - | ... M42: {=IF(OR(TRIM(INDIRECT("'"&M$6&"'!"&M$4&ROW()-31))="0",INDIRECT("'"&M$6&"'!"&M$4&ROW()-31)="",NOT(ISNUMBER(INDIRECT("'"&M$6&"'!"&M$4&ROW()-31)))),"-",INDIRECT("'"&M$6&"'!"&M$4&ROW()-31))} -> - | N42: =SUM(B42:M42) -> 0 | O42: =N42/COLUMNS(B42:M42) -> 0
A43: Total INCOME | B43: =SUM(B36:B42) -> 0 | C43: =SUM(C36:C42) -> 0 | D43: =SUM(D36:D42) -> 0 | E43: =SUM(E36:E42) -> 0 | F43: =SUM(F36:F42) -> 0 | G43: =SUM(G36:G42) -> 0 | H43: =SUM(H36:H42) -> 0 | I43: =SUM(I36:I42) -> 0 | ... O43: =SUM(O36:O42) -> 0
A45: ='Section-Category'!A82 -> Petty Cash Used | B45: =B$6 -> Jan | C45: =C$6 -> Feb | D45: =D$6 -> Mar | E45: =E$6 -> Apr | F45: =F$6 -> May | G45: =G$6 -> Jun | H45: =H$6 -> Jul | I45: =I$6 -> Aug | ... M45: =M$6 -> Dec
A46: ='Section-Category'!A83 -> Pocket Money Wife | B46: {=IF(OR(TRIM(INDIRECT("'"&B$6&"'!"&B$4&ROW()-31))="0",INDIRECT("'"&B$6&"'!"&B$4&ROW()-31)="",NOT(ISNUMBER(INDIRECT("'"&B$6&"'!"&B$4&ROW()-31)))),"-",INDIRECT("'"&B$6&"'!"&B$4&ROW()-31))} -> - | C46: {=IF(OR(TRIM(INDIRECT("'"&C$6&"'!"&C$4&ROW()-31))="0",INDIRECT("'"&C$6&"'!"&C$4&ROW()-31)="",NOT(ISNUMBER(INDIRECT("'"&C$6&"'!"&C$4&ROW()-31)))),"-",INDIRECT("'"&C$6&"'!"&C$4&ROW()-31))} -> - | D46: {=IF(OR(TRIM(INDIRECT("'"&D$6&"'!"&D$4&ROW()-31))="0",INDIRECT("'"&D$6&"'!"&D$4&ROW()-31)="",NOT(ISNUMBER(INDIRECT("'"&D$6&"'!"&D$4&ROW()-31)))),"-",INDIRECT("'"&D$6&"'!"&D$4&ROW()-31))} -> - | E46: {=IF(OR(TRIM(INDIRECT("'"&E$6&"'!"&E$4&ROW()-31))="0",INDIRECT("'"&E$6&"'!"&E$4&ROW()-31)="",NOT(ISNUMBER(INDIRECT("'"&E$6&"'!"&E$4&ROW()-31)))),"-",INDIRECT("'"&E$6&"'!"&E$4&ROW()-31))} -> - | F46: {=IF(OR(TRIM(INDIRECT("'"&F$6&"'!"&F$4&ROW()-31))="0",INDIRECT("'"&F$6&"'!"&F$4&ROW()-31)="",NOT(ISNUMBER(INDIRECT("'"&F$6&"'!"&F$4&ROW()-31)))),"-",INDIRECT("'"&F$6&"'!"&F$4&ROW()-31))} -> - | G46: {=IF(OR(TRIM(INDIRECT("'"&G$6&"'!"&G$4&ROW()-31))="0",INDIRECT("'"&G$6&"'!"&G$4&ROW()-31)="",NOT(ISNUMBER(INDIRECT("'"&G$6&"'!"&G$4&ROW()-31)))),"-",INDIRECT("'"&G$6&"'!"&G$4&ROW()-31))} -> - | H46: {=IF(OR(TRIM(INDIRECT("'"&H$6&"'!"&H$4&ROW()-31))="0",INDIRECT("'"&H$6&"'!"&H$4&ROW()-31)="",NOT(ISNUMBER(INDIRECT("'"&H$6&"'!"&H$4&ROW()-31)))),"-",INDIRECT("'"&H$6&"'!"&H$4&ROW()-31))} -> - | I46: {=IF(OR(TRIM(INDIRECT("'"&I$6&"'!"&I$4&ROW()-31))="0",INDIRECT("'"&I$6&"'!"&I$4&ROW()-31)="",NOT(ISNUMBER(INDIRECT("'"&I$6&"'!"&I$4&ROW()-31)))),"-",INDIRECT("'"&I$6&"'!"&I$4&ROW()-31))} -> - | ... M46: {=IF(OR(TRIM(INDIRECT("'"&M$6&"'!"&M$4&ROW()-31))="0",INDIRECT("'"&M$6&"'!"&M$4&ROW()-31)="",NOT(ISNUMBER(INDIRECT("'"&M$6&"'!"&M$4&ROW()-31)))),"-",INDIRECT("'"&M$6&"'!"&M$4&ROW()-31))} -> - | N46: 0 | O46: 0
A47: ='Section-Category'!A84 -> Car Repair / Workshop | B47: {=IF(OR(TRIM(INDIRECT("'"&B$6&"'!"&B$4&ROW()-31))="0",INDIRECT("'"&B$6&"'!"&B$4&ROW()-31)="",NOT(ISNUMBER(INDIRECT("'"&B$6&"'!"&B$4&ROW()-31)))),"-",INDIRECT("'"&B$6&"'!"&B$4&ROW()-31))} -> - | C47: {=IF(OR(TRIM(INDIRECT("'"&C$6&"'!"&C$4&ROW()-31))="0",INDIRECT("'"&C$6&"'!"&C$4&ROW()-31)="",NOT(ISNUMBER(INDIRECT("'"&C$6&"'!"&C$4&ROW()-31)))),"-",INDIRECT("'"&C$6&"'!"&C$4&ROW()-31))} -> - | D47: {=IF(OR(TRIM(INDIRECT("'"&D$6&"'!"&D$4&ROW()-31))="0",INDIRECT("'"&D$6&"'!"&D$4&ROW()-31)="",NOT(ISNUMBER(INDIRECT("'"&D$6&"'!"&D$4&ROW()-31)))),"-",INDIRECT("'"&D$6&"'!"&D$4&ROW()-31))} -> - | E47: {=IF(OR(TRIM(INDIRECT("'"&E$6&"'!"&E$4&ROW()-31))="0",INDIRECT("'"&E$6&"'!"&E$4&ROW()-31)="",NOT(ISNUMBER(INDIRECT("'"&E$6&"'!"&E$4&ROW()-31)))),"-",INDIRECT("'"&E$6&"'!"&E$4&ROW()-31))} -> - | F47: {=IF(OR(TRIM(INDIRECT("'"&F$6&"'!"&F$4&ROW()-31))="0",INDIRECT("'"&F$6&"'!"&F$4&ROW()-31)="",NOT(ISNUMBER(INDIRECT("'"&F$6&"'!"&F$4&ROW()-31)))),"-",INDIRECT("'"&F$6&"'!"&F$4&ROW()-31))} -> - | G47: {=IF(OR(TRIM(INDIRECT("'"&G$6&"'!"&G$4&ROW()-31))="0",INDIRECT("'"&G$6&"'!"&G$4&ROW()-31)="",NOT(ISNUMBER(INDIRECT("'"&G$6&"'!"&G$4&ROW()-31)))),"-",INDIRECT("'"&G$6&"'!"&G$4&ROW()-31))} -> - | H47: {=IF(OR(TRIM(INDIRECT("'"&H$6&"'!"&H$4&ROW()-31))="0",INDIRECT("'"&H$6&"'!"&H$4&ROW()-31)="",NOT(ISNUMBER(INDIRECT("'"&H$6&"'!"&H$4&ROW()-31)))),"-",INDIRECT("'"&H$6&"'!"&H$4&ROW()-31))} -> - | I47: {=IF(OR(TRIM(INDIRECT("'"&I$6&"'!"&I$4&ROW()-31))="0",INDIRECT("'"&I$6&"'!"&I$4&ROW()-31)="",NOT(ISNUMBER(INDIRECT("'"&I$6&"'!"&I$4&ROW()-31)))),"-",INDIRECT("'"&I$6&"'!"&I$4&ROW()-31))} -> - | ... M47: {=IF(OR(TRIM(INDIRECT("'"&M$6&"'!"&M$4&ROW()-31))="0",INDIRECT("'"&M$6&"'!"&M$4&ROW()-31)="",NOT(ISNUMBER(INDIRECT("'"&M$6&"'!"&M$4&ROW()-31)))),"-",INDIRECT("'"&M$6&"'!"&M$4&ROW()-31))} -> - | N47: 0 | O47: 0
A48: ='Section-Category'!A85 -> Food | B48: {=IF(OR(TRIM(INDIRECT("'"&B$6&"'!"&B$4&ROW()-31))="0",INDIRECT("'"&B$6&"'!"&B$4&ROW()-31)="",NOT(ISNUMBER(INDIRECT("'"&B$6&"'!"&B$4&ROW()-31)))),"-",INDIRECT("'"&B$6&"'!"&B$4&ROW()-31))} -> - | C48: {=IF(OR(TRIM(INDIRECT("'"&C$6&"'!"&C$4&ROW()-31))="0",INDIRECT("'"&C$6&"'!"&C$4&ROW()-31)="",NOT(ISNUMBER(INDIRECT("'"&C$6&"'!"&C$4&ROW()-31)))),"-",INDIRECT("'"&C$6&"'!"&C$4&ROW()-31))} -> - | D48: {=IF(OR(TRIM(INDIRECT("'"&D$6&"'!"&D$4&ROW()-31))="0",INDIRECT("'"&D$6&"'!"&D$4&ROW()-31)="",NOT(ISNUMBER(INDIRECT("'"&D$6&"'!"&D$4&ROW()-31)))),"-",INDIRECT("'"&D$6&"'!"&D$4&ROW()-31))} -> - | E48: {=IF(OR(TRIM(INDIRECT("'"&E$6&"'!"&E$4&ROW()-31))="0",INDIRECT("'"&E$6&"'!"&E$4&ROW()-31)="",NOT(ISNUMBER(INDIRECT("'"&E$6&"'!"&E$4&ROW()-31)))),"-",INDIRECT("'"&E$6&"'!"&E$4&ROW()-31))} -> - | F48: {=IF(OR(TRIM(INDIRECT("'"&F$6&"'!"&F$4&ROW()-31))="0",INDIRECT("'"&F$6&"'!"&F$4&ROW()-31)="",NOT(ISNUMBER(INDIRECT("'"&F$6&"'!"&F$4&ROW()-31)))),"-",INDIRECT("'"&F$6&"'!"&F$4&ROW()-31))} -> - | G48: {=IF(OR(TRIM(INDIRECT("'"&G$6&"'!"&G$4&ROW()-31))="0",INDIRECT("'"&G$6&"'!"&G$4&ROW()-31)="",NOT(ISNUMBER(INDIRECT("'"&G$6&"'!"&G$4&ROW()-31)))),"-",INDIRECT("'"&G$6&"'!"&G$4&ROW()-31))} -> - | H48: {=IF(OR(TRIM(INDIRECT("'"&H$6&"'!"&H$4&ROW()-31))="0",INDIRECT("'"&H$6&"'!"&H$4&ROW()-31)="",NOT(ISNUMBER(INDIRECT("'"&H$6&"'!"&H$4&ROW()-31)))),"-",INDIRECT("'"&H$6&"'!"&H$4&ROW()-31))} -> - | I48: {=IF(OR(TRIM(INDIRECT("'"&I$6&"'!"&I$4&ROW()-31))="0",INDIRECT("'"&I$6&"'!"&I$4&ROW()-31)="",NOT(ISNUMBER(INDIRECT("'"&I$6&"'!"&I$4&ROW()-31)))),"-",INDIRECT("'"&I$6&"'!"&I$4&ROW()-31))} -> - | ... M48: {=IF(OR(TRIM(INDIRECT("'"&M$6&"'!"&M$4&ROW()-31))="0",INDIRECT("'"&M$6&"'!"&M$4&ROW()-31)="",NOT(ISNUMBER(INDIRECT("'"&M$6&"'!"&M$4&ROW()-31)))),"-",INDIRECT("'"&M$6&"'!"&M$4&ROW()-31))} -> - | N48: 0 | O48: 0
A49: ='Section-Category'!A86 -> Donation | B49: {=IF(OR(TRIM(INDIRECT("'"&B$6&"'!"&B$4&ROW()-31))="0",INDIRECT("'"&B$6&"'!"&B$4&ROW()-31)="",NOT(ISNUMBER(INDIRECT("'"&B$6&"'!"&B$4&ROW()-31)))),"-",INDIRECT("'"&B$6&"'!"&B$4&ROW()-31))} -> - | C49: {=IF(OR(TRIM(INDIRECT("'"&C$6&"'!"&C$4&ROW()-31))="0",INDIRECT("'"&C$6&"'!"&C$4&ROW()-31)="",NOT(ISNUMBER(INDIRECT("'"&C$6&"'!"&C$4&ROW()-31)))),"-",INDIRECT("'"&C$6&"'!"&C$4&ROW()-31))} -> - | D49: {=IF(OR(TRIM(INDIRECT("'"&D$6&"'!"&D$4&ROW()-31))="0",INDIRECT("'"&D$6&"'!"&D$4&ROW()-31)="",NOT(ISNUMBER(INDIRECT("'"&D$6&"'!"&D$4&ROW()-31)))),"-",INDIRECT("'"&D$6&"'!"&D$4&ROW()-31))} -> - | E49: {=IF(OR(TRIM(INDIRECT("'"&E$6&"'!"&E$4&ROW()-31))="0",INDIRECT("'"&E$6&"'!"&E$4&ROW()-31)="",NOT(ISNUMBER(INDIRECT("'"&E$6&"'!"&E$4&ROW()-31)))),"-",INDIRECT("'"&E$6&"'!"&E$4&ROW()-31))} -> - | F49: {=IF(OR(TRIM(INDIRECT("'"&F$6&"'!"&F$4&ROW()-31))="0",INDIRECT("'"&F$6&"'!"&F$4&ROW()-31)="",NOT(ISNUMBER(INDIRECT("'"&F$6&"'!"&F$4&ROW()-31)))),"-",INDIRECT("'"&F$6&"'!"&F$4&ROW()-31))} -> - | G49: {=IF(OR(TRIM(INDIRECT("'"&G$6&"'!"&G$4&ROW()-31))="0",INDIRECT("'"&G$6&"'!"&G$4&ROW()-31)="",NOT(ISNUMBER(INDIRECT("'"&G$6&"'!"&G$4&ROW()-31)))),"-",INDIRECT("'"&G$6&"'!"&G$4&ROW()-31))} -> - | H49: {=IF(OR(TRIM(INDIRECT("'"&H$6&"'!"&H$4&ROW()-31))="0",INDIRECT("'"&H$6&"'!"&H$4&ROW()-31)="",NOT(ISNUMBER(INDIRECT("'"&H$6&"'!"&H$4&ROW()-31)))),"-",INDIRECT("'"&H$6&"'!"&H$4&ROW()-31))} -> - | I49: {=IF(OR(TRIM(INDIRECT("'"&I$6&"'!"&I$4&ROW()-31))="0",INDIRECT("'"&I$6&"'!"&I$4&ROW()-31)="",NOT(ISNUMBER(INDIRECT("'"&I$6&"'!"&I$4&ROW()-31)))),"-",INDIRECT("'"&I$6&"'!"&I$4&ROW()-31))} -> - | ... M49: {=IF(OR(TRIM(INDIRECT("'"&M$6&"'!"&M$4&ROW()-31))="0",INDIRECT("'"&M$6&"'!"&M$4&ROW()-31)="",NOT(ISNUMBER(INDIRECT("'"&M$6&"'!"&M$4&ROW()-31)))),"-",INDIRECT("'"&M$6&"'!"&M$4&ROW()-31))} -> - | N49: 0 | O49: 0
A50: ='Section-Category'!A87 -> Medical | B50: {=IF(OR(TRIM(INDIRECT("'"&B$6&"'!"&B$4&ROW()-31))="0",INDIRECT("'"&B$6&"'!"&B$4&ROW()-31)="",NOT(ISNUMBER(INDIRECT("'"&B$6&"'!"&B$4&ROW()-31)))),"-",INDIRECT("'"&B$6&"'!"&B$4&ROW()-31))} -> - | C50: {=IF(OR(TRIM(INDIRECT("'"&C$6&"'!"&C$4&ROW()-31))="0",INDIRECT("'"&C$6&"'!"&C$4&ROW()-31)="",NOT(ISNUMBER(INDIRECT("'"&C$6&"'!"&C$4&ROW()-31)))),"-",INDIRECT("'"&C$6&"'!"&C$4&ROW()-31))} -> - | D50: {=IF(OR(TRIM(INDIRECT("'"&D$6&"'!"&D$4&ROW()-31))="0",INDIRECT("'"&D$6&"'!"&D$4&ROW()-31)="",NOT(ISNUMBER(INDIRECT("'"&D$6&"'!"&D$4&ROW()-31)))),"-",INDIRECT("'"&D$6&"'!"&D$4&ROW()-31))} -> - | E50: {=IF(OR(TRIM(INDIRECT("'"&E$6&"'!"&E$4&ROW()-31))="0",INDIRECT("'"&E$6&"'!"&E$4&ROW()-31)="",NOT(ISNUMBER(INDIRECT("'"&E$6&"'!"&E$4&ROW()-31)))),"-",INDIRECT("'"&E$6&"'!"&E$4&ROW()-31))} -> - | F50: {=IF(OR(TRIM(INDIRECT("'"&F$6&"'!"&F$4&ROW()-31))="0",INDIRECT("'"&F$6&"'!"&F$4&ROW()-31)="",NOT(ISNUMBER(INDIRECT("'"&F$6&"'!"&F$4&ROW()-31)))),"-",INDIRECT("'"&F$6&"'!"&F$4&ROW()-31))} -> - | G50: {=IF(OR(TRIM(INDIRECT("'"&G$6&"'!"&G$4&ROW()-31))="0",INDIRECT("'"&G$6&"'!"&G$4&ROW()-31)="",NOT(ISNUMBER(INDIRECT("'"&G$6&"'!"&G$4&ROW()-31)))),"-",INDIRECT("'"&G$6&"'!"&G$4&ROW()-31))} -> - | H50: {=IF(OR(TRIM(INDIRECT("'"&H$6&"'!"&H$4&ROW()-31))="0",INDIRECT("'"&H$6&"'!"&H$4&ROW()-31)="",NOT(ISNUMBER(INDIRECT("'"&H$6&"'!"&H$4&ROW()-31)))),"-",INDIRECT("'"&H$6&"'!"&H$4&ROW()-31))} -> - | I50: {=IF(OR(TRIM(INDIRECT("'"&I$6&"'!"&I$4&ROW()-31))="0",INDIRECT("'"&I$6&"'!"&I$4&ROW()-31)="",NOT(ISNUMBER(INDIRECT("'"&I$6&"'!"&I$4&ROW()-31)))),"-",INDIRECT("'"&I$6&"'!"&I$4&ROW()-31))} -> - | ... M50: {=IF(OR(TRIM(INDIRECT("'"&M$6&"'!"&M$4&ROW()-31))="0",INDIRECT("'"&M$6&"'!"&M$4&ROW()-31)="",NOT(ISNUMBER(INDIRECT("'"&M$6&"'!"&M$4&ROW()-31)))),"-",INDIRECT("'"&M$6&"'!"&M$4&ROW()-31))} -> - | N50: 0 | O50: 0
A51: ='Section-Category'!A88 -> Donation | B51: {=IF(OR(TRIM(INDIRECT("'"&B$6&"'!"&B$4&ROW()-31))="0",INDIRECT("'"&B$6&"'!"&B$4&ROW()-31)="",NOT(ISNUMBER(INDIRECT("'"&B$6&"'!"&B$4&ROW()-31)))),"-",INDIRECT("'"&B$6&"'!"&B$4&ROW()-31))} -> - | C51: {=IF(OR(TRIM(INDIRECT("'"&C$6&"'!"&C$4&ROW()-31))="0",INDIRECT("'"&C$6&"'!"&C$4&ROW()-31)="",NOT(ISNUMBER(INDIRECT("'"&C$6&"'!"&C$4&ROW()-31)))),"-",INDIRECT("'"&C$6&"'!"&C$4&ROW()-31))} -> - | D51: {=IF(OR(TRIM(INDIRECT("'"&D$6&"'!"&D$4&ROW()-31))="0",INDIRECT("'"&D$6&"'!"&D$4&ROW()-31)="",NOT(ISNUMBER(INDIRECT("'"&D$6&"'!"&D$4&ROW()-31)))),"-",INDIRECT("'"&D$6&"'!"&D$4&ROW()-31))} -> - | E51: {=IF(OR(TRIM(INDIRECT("'"&E$6&"'!"&E$4&ROW()-31))="0",INDIRECT("'"&E$6&"'!"&E$4&ROW()-31)="",NOT(ISNUMBER(INDIRECT("'"&E$6&"'!"&E$4&ROW()-31)))),"-",INDIRECT("'"&E$6&"'!"&E$4&ROW()-31))} -> - | F51: {=IF(OR(TRIM(INDIRECT("'"&F$6&"'!"&F$4&ROW()-31))="0",INDIRECT("'"&F$6&"'!"&F$4&ROW()-31)="",NOT(ISNUMBER(INDIRECT("'"&F$6&"'!"&F$4&ROW()-31)))),"-",INDIRECT("'"&F$6&"'!"&F$4&ROW()-31))} -> - | G51: {=IF(OR(TRIM(INDIRECT("'"&G$6&"'!"&G$4&ROW()-31))="0",INDIRECT("'"&G$6&"'!"&G$4&ROW()-31)="",NOT(ISNUMBER(INDIRECT("'"&G$6&"'!"&G$4&ROW()-31)))),"-",INDIRECT("'"&G$6&"'!"&G$4&ROW()-31))} -> - | H51: {=IF(OR(TRIM(INDIRECT("'"&H$6&"'!"&H$4&ROW()-31))="0",INDIRECT("'"&H$6&"'!"&H$4&ROW()-31)="",NOT(ISNUMBER(INDIRECT("'"&H$6&"'!"&H$4&ROW()-31)))),"-",INDIRECT("'"&H$6&"'!"&H$4&ROW()-31))} -> - | I51: {=IF(OR(TRIM(INDIRECT("'"&I$6&"'!"&I$4&ROW()-31))="0",INDIRECT("'"&I$6&"'!"&I$4&ROW()-31)="",NOT(ISNUMBER(INDIRECT("'"&I$6&"'!"&I$4&ROW()-31)))),"-",INDIRECT("'"&I$6&"'!"&I$4&ROW()-31))} -> - | ... M51: {=IF(OR(TRIM(INDIRECT("'"&M$6&"'!"&M$4&ROW()-31))="0",INDIRECT("'"&M$6&"'!"&M$4&ROW()-31)="",NOT(ISNUMBER(INDIRECT("'"&M$6&"'!"&M$4&ROW()-31)))),"-",INDIRECT("'"&M$6&"'!"&M$4&ROW()-31))} -> - | N51: 0 | O51: 0
A52: ='Section-Category'!A89 -> Pocket Money Husband | B52: {=IF(OR(TRIM(INDIRECT("'"&B$6&"'!"&B$4&ROW()-31))="0",INDIRECT("'"&B$6&"'!"&B$4&ROW()-31)="",NOT(ISNUMBER(INDIRECT("'"&B$6&"'!"&B$4&ROW()-31)))),"-",INDIRECT("'"&B$6&"'!"&B$4&ROW()-31))} -> - | C52: {=IF(OR(TRIM(INDIRECT("'"&C$6&"'!"&C$4&ROW()-31))="0",INDIRECT("'"&C$6&"'!"&C$4&ROW()-31)="",NOT(ISNUMBER(INDIRECT("'"&C$6&"'!"&C$4&ROW()-31)))),"-",INDIRECT("'"&C$6&"'!"&C$4&ROW()-31))} -> - | D52: {=IF(OR(TRIM(INDIRECT("'"&D$6&"'!"&D$4&ROW()-31))="0",INDIRECT("'"&D$6&"'!"&D$4&ROW()-31)="",NOT(ISNUMBER(INDIRECT("'"&D$6&"'!"&D$4&ROW()-31)))),"-",INDIRECT("'"&D$6&"'!"&D$4&ROW()-31))} -> - | E52: {=IF(OR(TRIM(INDIRECT("'"&E$6&"'!"&E$4&ROW()-31))="0",INDIRECT("'"&E$6&"'!"&E$4&ROW()-31)="",NOT(ISNUMBER(INDIRECT("'"&E$6&"'!"&E$4&ROW()-31)))),"-",INDIRECT("'"&E$6&"'!"&E$4&ROW()-31))} -> - | F52: {=IF(OR(TRIM(INDIRECT("'"&F$6&"'!"&F$4&ROW()-31))="0",INDIRECT("'"&F$6&"'!"&F$4&ROW()-31)="",NOT(ISNUMBER(INDIRECT("'"&F$6&"'!"&F$4&ROW()-31)))),"-",INDIRECT("'"&F$6&"'!"&F$4&ROW()-31))} -> - | G52: {=IF(OR(TRIM(INDIRECT("'"&G$6&"'!"&G$4&ROW()-31))="0",INDIRECT("'"&G$6&"'!"&G$4&ROW()-31)="",NOT(ISNUMBER(INDIRECT("'"&G$6&"'!"&G$4&ROW()-31)))),"-",INDIRECT("'"&G$6&"'!"&G$4&ROW()-31))} -> - | H52: {=IF(OR(TRIM(INDIRECT("'"&H$6&"'!"&H$4&ROW()-31))="0",INDIRECT("'"&H$6&"'!"&H$4&ROW()-31)="",NOT(ISNUMBER(INDIRECT("'"&H$6&"'!"&H$4&ROW()-31)))),"-",INDIRECT("'"&H$6&"'!"&H$4&ROW()-31))} -> - | I52: {=IF(OR(TRIM(INDIRECT("'"&I$6&"'!"&I$4&ROW()-31))="0",INDIRECT("'"&I$6&"'!"&I$4&ROW()-31)="",NOT(ISNUMBER(INDIRECT("'"&I$6&"'!"&I$4&ROW()-31)))),"-",INDIRECT("'"&I$6&"'!"&I$4&ROW()-31))} -> - | ... M52: {=IF(OR(TRIM(INDIRECT("'"&M$6&"'!"&M$4&ROW()-31))="0",INDIRECT("'"&M$6&"'!"&M$4&ROW()-31)="",NOT(ISNUMBER(INDIRECT("'"&M$6&"'!"&M$4&ROW()-31)))),"-",INDIRECT("'"&M$6&"'!"&M$4&ROW()-31))} -> - | N52: 0 | O52: 0
A53: ='Section-Category'!A90 -> Other | B53: {=IF(OR(TRIM(INDIRECT("'"&B$6&"'!"&B$4&ROW()-31))="0",INDIRECT("'"&B$6&"'!"&B$4&ROW()-31)="",NOT(ISNUMBER(INDIRECT("'"&B$6&"'!"&B$4&ROW()-31)))),"-",INDIRECT("'"&B$6&"'!"&B$4&ROW()-31))} -> - | C53: {=IF(OR(TRIM(INDIRECT("'"&C$6&"'!"&C$4&ROW()-31))="0",INDIRECT("'"&C$6&"'!"&C$4&ROW()-31)="",NOT(ISNUMBER(INDIRECT("'"&C$6&"'!"&C$4&ROW()-31)))),"-",INDIRECT("'"&C$6&"'!"&C$4&ROW()-31))} -> - | D53: {=IF(OR(TRIM(INDIRECT("'"&D$6&"'!"&D$4&ROW()-31))="0",INDIRECT("'"&D$6&"'!"&D$4&ROW()-31)="",NOT(ISNUMBER(INDIRECT("'"&D$6&"'!"&D$4&ROW()-31)))),"-",INDIRECT("'"&D$6&"'!"&D$4&ROW()-31))} -> - | E53: {=IF(OR(TRIM(INDIRECT("'"&E$6&"'!"&E$4&ROW()-31))="0",INDIRECT("'"&E$6&"'!"&E$4&ROW()-31)="",NOT(ISNUMBER(INDIRECT("'"&E$6&"'!"&E$4&ROW()-31)))),"-",INDIRECT("'"&E$6&"'!"&E$4&ROW()-31))} -> - | F53: {=IF(OR(TRIM(INDIRECT("'"&F$6&"'!"&F$4&ROW()-31))="0",INDIRECT("'"&F$6&"'!"&F$4&ROW()-31)="",NOT(ISNUMBER(INDIRECT("'"&F$6&"'!"&F$4&ROW()-31)))),"-",INDIRECT("'"&F$6&"'!"&F$4&ROW()-31))} -> - | G53: {=IF(OR(TRIM(INDIRECT("'"&G$6&"'!"&G$4&ROW()-31))="0",INDIRECT("'"&G$6&"'!"&G$4&ROW()-31)="",NOT(ISNUMBER(INDIRECT("'"&G$6&"'!"&G$4&ROW()-31)))),"-",INDIRECT("'"&G$6&"'!"&G$4&ROW()-31))} -> - | H53: {=IF(OR(TRIM(INDIRECT("'"&H$6&"'!"&H$4&ROW()-31))="0",INDIRECT("'"&H$6&"'!"&H$4&ROW()-31)="",NOT(ISNUMBER(INDIRECT("'"&H$6&"'!"&H$4&ROW()-31)))),"-",INDIRECT("'"&H$6&"'!"&H$4&ROW()-31))} -> - | I53: {=IF(OR(TRIM(INDIRECT("'"&I$6&"'!"&I$4&ROW()-31))="0",INDIRECT("'"&I$6&"'!"&I$4&ROW()-31)="",NOT(ISNUMBER(INDIRECT("'"&I$6&"'!"&I$4&ROW()-31)))),"-",INDIRECT("'"&I$6&"'!"&I$4&ROW()-31))} -> - | ... M53: {=IF(OR(TRIM(INDIRECT("'"&M$6&"'!"&M$4&ROW()-31))="0",INDIRECT("'"&M$6&"'!"&M$4&ROW()-31)="",NOT(ISNUMBER(INDIRECT("'"&M$6&"'!"&M$4&ROW()-31)))),"-",INDIRECT("'"&M$6&"'!"&M$4&ROW()-31))} -> - | N53: 0 | O53: 0
A54: ='Section-Category'!A91 -> Total Petty Cash Used | B54: =SUM(B46:B53) -> 0 | C54: =SUM(C46:C53) -> 0 | D54: =SUM(D46:D53) -> 0 | E54: =SUM(E46:E53) -> 0 | F54: =SUM(F46:F53) -> 0 | G54: =SUM(G46:G53) -> 0 | H54: =SUM(H46:H53) -> 0 | I54: =SUM(I46:I53) -> 0 | ... O54: =SUM(O46:O53) -> 0
A55: ='Section-Category'!A92 -> % of Total Petty Cash | B55: =IF(B$11=0," - ",B54/B$11) -> - | C55: =IF(C$11=0," - ",C54/C$11) -> - | D55: =IF(D$11=0," - ",D54/D$11) -> - | E55: =IF(E$11=0," - ",E54/E$11) -> - | F55: =IF(F$11=0," - ",F54/F$11) -> - | G55: =IF(G$11=0," - ",G54/G$11) -> - | H55: =IF(H$11=0," - ",H54/H$11) -> - | I55: =IF(I$11=0," - ",I54/I$11) -> - | ... O55: =IF(O$11=0," - ",O54/O$11) -> -
A57: ='Section-Category'!A11 -> SAVINGS EXPENSE | B57: =B$6 -> Jan | C57: =C$6 -> Feb | D57: =D$6 -> Mar | E57: =E$6 -> Apr | F57: =F$6 -> May | G57: =G$6 -> Jun | H57: =H$6 -> Jul | I57: =I$6 -> Aug | ... M57: =M$6 -> Dec | N57: Total | O57: Avg
A58: ='Section-Category'!A12 -> Emergency Fund | B58: {=IF(OR(TRIM(INDIRECT("'"&B$6&"'!"&B$4&ROW()-32))="0",INDIRECT("'"&B$6&"'!"&B$4&ROW()-32)="",NOT(ISNUMBER(INDIRECT("'"&B$6&"'!"&B$4&ROW()-32)))),"-",INDIRECT("'"&B$6&"'!"&B$4&ROW()-32))} -> - | C58: {=IF(OR(TRIM(INDIRECT("'"&C$6&"'!"&C$4&ROW()-32))="0",INDIRECT("'"&C$6&"'!"&C$4&ROW()-32)="",NOT(ISNUMBER(INDIRECT("'"&C$6&"'!"&C$4&ROW()-32)))),"-",INDIRECT("'"&C$6&"'!"&C$4&ROW()-32))} -> - | D58: {=IF(OR(TRIM(INDIRECT("'"&D$6&"'!"&D$4&ROW()-32))="0",INDIRECT("'"&D$6&"'!"&D$4&ROW()-32)="",NOT(ISNUMBER(INDIRECT("'"&D$6&"'!"&D$4&ROW()-32)))),"-",INDIRECT("'"&D$6&"'!"&D$4&ROW()-32))} -> - | E58: {=IF(OR(TRIM(INDIRECT("'"&E$6&"'!"&E$4&ROW()-32))="0",INDIRECT("'"&E$6&"'!"&E$4&ROW()-32)="",NOT(ISNUMBER(INDIRECT("'"&E$6&"'!"&E$4&ROW()-32)))),"-",INDIRECT("'"&E$6&"'!"&E$4&ROW()-32))} -> - | F58: {=IF(OR(TRIM(INDIRECT("'"&F$6&"'!"&F$4&ROW()-32))="0",INDIRECT("'"&F$6&"'!"&F$4&ROW()-32)="",NOT(ISNUMBER(INDIRECT("'"&F$6&"'!"&F$4&ROW()-32)))),"-",INDIRECT("'"&F$6&"'!"&F$4&ROW()-32))} -> - | G58: {=IF(OR(TRIM(INDIRECT("'"&G$6&"'!"&G$4&ROW()-32))="0",INDIRECT("'"&G$6&"'!"&G$4&ROW()-32)="",NOT(ISNUMBER(INDIRECT("'"&G$6&"'!"&G$4&ROW()-32)))),"-",INDIRECT("'"&G$6&"'!"&G$4&ROW()-32))} -> - | H58: {=IF(OR(TRIM(INDIRECT("'"&H$6&"'!"&H$4&ROW()-32))="0",INDIRECT("'"&H$6&"'!"&H$4&ROW()-32)="",NOT(ISNUMBER(INDIRECT("'"&H$6&"'!"&H$4&ROW()-32)))),"-",INDIRECT("'"&H$6&"'!"&H$4&ROW()-32))} -> - | I58: {=IF(OR(TRIM(INDIRECT("'"&I$6&"'!"&I$4&ROW()-32))="0",INDIRECT("'"&I$6&"'!"&I$4&ROW()-32)="",NOT(ISNUMBER(INDIRECT("'"&I$6&"'!"&I$4&ROW()-32)))),"-",INDIRECT("'"&I$6&"'!"&I$4&ROW()-32))} -> - | ... M58: {=IF(OR(TRIM(INDIRECT("'"&M$6&"'!"&M$4&ROW()-32))="0",INDIRECT("'"&M$6&"'!"&M$4&ROW()-32)="",NOT(ISNUMBER(INDIRECT("'"&M$6&"'!"&M$4&ROW()-32)))),"-",INDIRECT("'"&M$6&"'!"&M$4&ROW()-32))} -> - | N58: =SUM(B58:M58) -> 0 | O58: =N58/COLUMNS(B58:M58) -> 0
A59: ='Section-Category'!A13 -> Investments | B59: {=IF(OR(TRIM(INDIRECT("'"&B$6&"'!"&B$4&ROW()-32))="0",INDIRECT("'"&B$6&"'!"&B$4&ROW()-32)="",NOT(ISNUMBER(INDIRECT("'"&B$6&"'!"&B$4&ROW()-32)))),"-",INDIRECT("'"&B$6&"'!"&B$4&ROW()-32))} -> - | C59: {=IF(OR(TRIM(INDIRECT("'"&C$6&"'!"&C$4&ROW()-32))="0",INDIRECT("'"&C$6&"'!"&C$4&ROW()-32)="",NOT(ISNUMBER(INDIRECT("'"&C$6&"'!"&C$4&ROW()-32)))),"-",INDIRECT("'"&C$6&"'!"&C$4&ROW()-32))} -> - | D59: {=IF(OR(TRIM(INDIRECT("'"&D$6&"'!"&D$4&ROW()-32))="0",INDIRECT("'"&D$6&"'!"&D$4&ROW()-32)="",NOT(ISNUMBER(INDIRECT("'"&D$6&"'!"&D$4&ROW()-32)))),"-",INDIRECT("'"&D$6&"'!"&D$4&ROW()-32))} -> - | E59: {=IF(OR(TRIM(INDIRECT("'"&E$6&"'!"&E$4&ROW()-32))="0",INDIRECT("'"&E$6&"'!"&E$4&ROW()-32)="",NOT(ISNUMBER(INDIRECT("'"&E$6&"'!"&E$4&ROW()-32)))),"-",INDIRECT("'"&E$6&"'!"&E$4&ROW()-32))} -> - | F59: {=IF(OR(TRIM(INDIRECT("'"&F$6&"'!"&F$4&ROW()-32))="0",INDIRECT("'"&F$6&"'!"&F$4&ROW()-32)="",NOT(ISNUMBER(INDIRECT("'"&F$6&"'!"&F$4&ROW()-32)))),"-",INDIRECT("'"&F$6&"'!"&F$4&ROW()-32))} -> - | G59: {=IF(OR(TRIM(INDIRECT("'"&G$6&"'!"&G$4&ROW()-32))="0",INDIRECT("'"&G$6&"'!"&G$4&ROW()-32)="",NOT(ISNUMBER(INDIRECT("'"&G$6&"'!"&G$4&ROW()-32)))),"-",INDIRECT("'"&G$6&"'!"&G$4&ROW()-32))} -> - | H59: {=IF(OR(TRIM(INDIRECT("'"&H$6&"'!"&H$4&ROW()-32))="0",INDIRECT("'"&H$6&"'!"&H$4&ROW()-32)="",NOT(ISNUMBER(INDIRECT("'"&H$6&"'!"&H$4&ROW()-32)))),"-",INDIRECT("'"&H$6&"'!"&H$4&ROW()-32))} -> - | I59: {=IF(OR(TRIM(INDIRECT("'"&I$6&"'!"&I$4&ROW()-32))="0",INDIRECT("'"&I$6&"'!"&I$4&ROW()-32)="",NOT(ISNUMBER(INDIRECT("'"&I$6&"'!"&I$4&ROW()-32)))),"-",INDIRECT("'"&I$6&"'!"&I$4&ROW()-32))} -> - | ... M59: {=IF(OR(TRIM(INDIRECT("'"&M$6&"'!"&M$4&ROW()-32))="0",INDIRECT("'"&M$6&"'!"&M$4&ROW()-32)="",NOT(ISNUMBER(INDIRECT("'"&M$6&"'!"&M$4&ROW()-32)))),"-",INDIRECT("'"&M$6&"'!"&M$4&ROW()-32))} -> - | N59: =SUM(B59:M59) -> 0 | O59: =N59/COLUMNS(B59:M59) -> 0
A60: ='Section-Category'!A14 -> Pocket Money Wife | B60: {=IF(OR(TRIM(INDIRECT("'"&B$6&"'!"&B$4&ROW()-32))="0",INDIRECT("'"&B$6&"'!"&B$4&ROW()-32)="",NOT(ISNUMBER(INDIRECT("'"&B$6&"'!"&B$4&ROW()-32)))),"-",INDIRECT("'"&B$6&"'!"&B$4&ROW()-32))} -> - | C60: {=IF(OR(TRIM(INDIRECT("'"&C$6&"'!"&C$4&ROW()-32))="0",INDIRECT("'"&C$6&"'!"&C$4&ROW()-32)="",NOT(ISNUMBER(INDIRECT("'"&C$6&"'!"&C$4&ROW()-32)))),"-",INDIRECT("'"&C$6&"'!"&C$4&ROW()-32))} -> - | D60: {=IF(OR(TRIM(INDIRECT("'"&D$6&"'!"&D$4&ROW()-32))="0",INDIRECT("'"&D$6&"'!"&D$4&ROW()-32)="",NOT(ISNUMBER(INDIRECT("'"&D$6&"'!"&D$4&ROW()-32)))),"-",INDIRECT("'"&D$6&"'!"&D$4&ROW()-32))} -> - | E60: {=IF(OR(TRIM(INDIRECT("'"&E$6&"'!"&E$4&ROW()-32))="0",INDIRECT("'"&E$6&"'!"&E$4&ROW()-32)="",NOT(ISNUMBER(INDIRECT("'"&E$6&"'!"&E$4&ROW()-32)))),"-",INDIRECT("'"&E$6&"'!"&E$4&ROW()-32))} -> - | F60: {=IF(OR(TRIM(INDIRECT("'"&F$6&"'!"&F$4&ROW()-32))="0",INDIRECT("'"&F$6&"'!"&F$4&ROW()-32)="",NOT(ISNUMBER(INDIRECT("'"&F$6&"'!"&F$4&ROW()-32)))),"-",INDIRECT("'"&F$6&"'!"&F$4&ROW()-32))} -> - | G60: {=IF(OR(TRIM(INDIRECT("'"&G$6&"'!"&G$4&ROW()-32))="0",INDIRECT("'"&G$6&"'!"&G$4&ROW()-32)="",NOT(ISNUMBER(INDIRECT("'"&G$6&"'!"&G$4&ROW()-32)))),"-",INDIRECT("'"&G$6&"'!"&G$4&ROW()-32))} -> - | H60: {=IF(OR(TRIM(INDIRECT("'"&H$6&"'!"&H$4&ROW()-32))="0",INDIRECT("'"&H$6&"'!"&H$4&ROW()-32)="",NOT(ISNUMBER(INDIRECT("'"&H$6&"'!"&H$4&ROW()-32)))),"-",INDIRECT("'"&H$6&"'!"&H$4&ROW()-32))} -> - | I60: {=IF(OR(TRIM(INDIRECT("'"&I$6&"'!"&I$4&ROW()-32))="0",INDIRECT("'"&I$6&"'!"&I$4&ROW()-32)="",NOT(ISNUMBER(INDIRECT("'"&I$6&"'!"&I$4&ROW()-32)))),"-",INDIRECT("'"&I$6&"'!"&I$4&ROW()-32))} -> - | ... M60: {=IF(OR(TRIM(INDIRECT("'"&M$6&"'!"&M$4&ROW()-32))="0",INDIRECT("'"&M$6&"'!"&M$4&ROW()-32)="",NOT(ISNUMBER(INDIRECT("'"&M$6&"'!"&M$4&ROW()-32)))),"-",INDIRECT("'"&M$6&"'!"&M$4&ROW()-32))} -> - | N60: =SUM(B60:M60) -> 0 | O60: =N60/COLUMNS(B60:M60) -> 0
A61: ='Section-Category'!A15 -> <Name-Of-Entry> | B61: {=IF(OR(TRIM(INDIRECT("'"&B$6&"'!"&B$4&ROW()-32))="0",INDIRECT("'"&B$6&"'!"&B$4&ROW()-32)="",NOT(ISNUMBER(INDIRECT("'"&B$6&"'!"&B$4&ROW()-32)))),"-",INDIRECT("'"&B$6&"'!"&B$4&ROW()-32))} -> - | C61: {=IF(OR(TRIM(INDIRECT("'"&C$6&"'!"&C$4&ROW()-32))="0",INDIRECT("'"&C$6&"'!"&C$4&ROW()-32)="",NOT(ISNUMBER(INDIRECT("'"&C$6&"'!"&C$4&ROW()-32)))),"-",INDIRECT("'"&C$6&"'!"&C$4&ROW()-32))} -> - | D61: {=IF(OR(TRIM(INDIRECT("'"&D$6&"'!"&D$4&ROW()-32))="0",INDIRECT("'"&D$6&"'!"&D$4&ROW()-32)="",NOT(ISNUMBER(INDIRECT("'"&D$6&"'!"&D$4&ROW()-32)))),"-",INDIRECT("'"&D$6&"'!"&D$4&ROW()-32))} -> - | E61: {=IF(OR(TRIM(INDIRECT("'"&E$6&"'!"&E$4&ROW()-32))="0",INDIRECT("'"&E$6&"'!"&E$4&ROW()-32)="",NOT(ISNUMBER(INDIRECT("'"&E$6&"'!"&E$4&ROW()-32)))),"-",INDIRECT("'"&E$6&"'!"&E$4&ROW()-32))} -> - | F61: {=IF(OR(TRIM(INDIRECT("'"&F$6&"'!"&F$4&ROW()-32))="0",INDIRECT("'"&F$6&"'!"&F$4&ROW()-32)="",NOT(ISNUMBER(INDIRECT("'"&F$6&"'!"&F$4&ROW()-32)))),"-",INDIRECT("'"&F$6&"'!"&F$4&ROW()-32))} -> - | G61: {=IF(OR(TRIM(INDIRECT("'"&G$6&"'!"&G$4&ROW()-32))="0",INDIRECT("'"&G$6&"'!"&G$4&ROW()-32)="",NOT(ISNUMBER(INDIRECT("'"&G$6&"'!"&G$4&ROW()-32)))),"-",INDIRECT("'"&G$6&"'!"&G$4&ROW()-32))} -> - | H61: {=IF(OR(TRIM(INDIRECT("'"&H$6&"'!"&H$4&ROW()-32))="0",INDIRECT("'"&H$6&"'!"&H$4&ROW()-32)="",NOT(ISNUMBER(INDIRECT("'"&H$6&"'!"&H$4&ROW()-32)))),"-",INDIRECT("'"&H$6&"'!"&H$4&ROW()-32))} -> - | I61: {=IF(OR(TRIM(INDIRECT("'"&I$6&"'!"&I$4&ROW()-32))="0",INDIRECT("'"&I$6&"'!"&I$4&ROW()-32)="",NOT(ISNUMBER(INDIRECT("'"&I$6&"'!"&I$4&ROW()-32)))),"-",INDIRECT("'"&I$6&"'!"&I$4&ROW()-32))} -> - | ... M61: {=IF(OR(TRIM(INDIRECT("'"&M$6&"'!"&M$4&ROW()-32))="0",INDIRECT("'"&M$6&"'!"&M$4&ROW()-32)="",NOT(ISNUMBER(INDIRECT("'"&M$6&"'!"&M$4&ROW()-32)))),"-",INDIRECT("'"&M$6&"'!"&M$4&ROW()-32))} -> - | N61: =SUM(B61:M61) -> 0 | O61: =N61/COLUMNS(B61:M61) -> 0
A62: ='Section-Category'!A16 -> <Name-Of-Entry> | B62: {=IF(OR(TRIM(INDIRECT("'"&B$6&"'!"&B$4&ROW()-32))="0",INDIRECT("'"&B$6&"'!"&B$4&ROW()-32)="",NOT(ISNUMBER(INDIRECT("'"&B$6&"'!"&B$4&ROW()-32)))),"-",INDIRECT("'"&B$6&"'!"&B$4&ROW()-32))} -> - | C62: {=IF(OR(TRIM(INDIRECT("'"&C$6&"'!"&C$4&ROW()-32))="0",INDIRECT("'"&C$6&"'!"&C$4&ROW()-32)="",NOT(ISNUMBER(INDIRECT("'"&C$6&"'!"&C$4&ROW()-32)))),"-",INDIRECT("'"&C$6&"'!"&C$4&ROW()-32))} -> - | D62: {=IF(OR(TRIM(INDIRECT("'"&D$6&"'!"&D$4&ROW()-32))="0",INDIRECT("'"&D$6&"'!"&D$4&ROW()-32)="",NOT(ISNUMBER(INDIRECT("'"&D$6&"'!"&D$4&ROW()-32)))),"-",INDIRECT("'"&D$6&"'!"&D$4&ROW()-32))} -> - | E62: {=IF(OR(TRIM(INDIRECT("'"&E$6&"'!"&E$4&ROW()-32))="0",INDIRECT("'"&E$6&"'!"&E$4&ROW()-32)="",NOT(ISNUMBER(INDIRECT("'"&E$6&"'!"&E$4&ROW()-32)))),"-",INDIRECT("'"&E$6&"'!"&E$4&ROW()-32))} -> - | F62: {=IF(OR(TRIM(INDIRECT("'"&F$6&"'!"&F$4&ROW()-32))="0",INDIRECT("'"&F$6&"'!"&F$4&ROW()-32)="",NOT(ISNUMBER(INDIRECT("'"&F$6&"'!"&F$4&ROW()-32)))),"-",INDIRECT("'"&F$6&"'!"&F$4&ROW()-32))} -> - | G62: {=IF(OR(TRIM(INDIRECT("'"&G$6&"'!"&G$4&ROW()-32))="0",INDIRECT("'"&G$6&"'!"&G$4&ROW()-32)="",NOT(ISNUMBER(INDIRECT("'"&G$6&"'!"&G$4&ROW()-32)))),"-",INDIRECT("'"&G$6&"'!"&G$4&ROW()-32))} -> - | H62: {=IF(OR(TRIM(INDIRECT("'"&H$6&"'!"&H$4&ROW()-32))="0",INDIRECT("'"&H$6&"'!"&H$4&ROW()-32)="",NOT(ISNUMBER(INDIRECT("'"&H$6&"'!"&H$4&ROW()-32)))),"-",INDIRECT("'"&H$6&"'!"&H$4&ROW()-32))} -> - | I62: {=IF(OR(TRIM(INDIRECT("'"&I$6&"'!"&I$4&ROW()-32))="0",INDIRECT("'"&I$6&"'!"&I$4&ROW()-32)="",NOT(ISNUMBER(INDIRECT("'"&I$6&"'!"&I$4&ROW()-32)))),"-",INDIRECT("'"&I$6&"'!"&I$4&ROW()-32))} -> - | ... M62: {=IF(OR(TRIM(INDIRECT("'"&M$6&"'!"&M$4&ROW()-32))="0",INDIRECT("'"&M$6&"'!"&M$4&ROW()-32)="",NOT(ISNUMBER(INDIRECT("'"&M$6&"'!"&M$4&ROW()-32)))),"-",INDIRECT("'"&M$6&"'!"&M$4&ROW()-32))} -> - | N62: =SUM(B62:M62) -> 0 | O62: =N62/COLUMNS(B62:M62) -> 0
A63: ='Section-Category'!A17 -> Total SAVINGS EXPENSE | B63: =SUM(B58:B62) -> 0 | C63: =SUM(C58:C62) -> 0 | D63: =SUM(D58:D62) -> 0 | E63: =SUM(E58:E62) -> 0 | F63: =SUM(F58:F62) -> 0 | G63: =SUM(G58:G62) -> 0 | H63: =SUM(H58:H62) -> 0 | I63: =SUM(I58:I62) -> 0 | ... O63: =SUM(O58:O62) -> 0
A64: ='Section-Category'!A18 -> % of Total Expenses | B64: =IF(B$17=0," - ",B63/B$17) -> - | C64: =IF(C$17=0," - ",C63/C$17) -> - | D64: =IF(D$17=0," - ",D63/D$17) -> - | E64: =IF(E$17=0," - ",E63/E$17) -> - | F64: =IF(F$17=0," - ",F63/F$17) -> - | G64: =IF(G$17=0," - ",G63/G$17) -> - | H64: =IF(H$17=0," - ",H63/H$17) -> - | I64: =IF(I$17=0," - ",I63/I$17) -> - | ... O64: =IF(O$17=0," - ",O63/O$17) -> -
A66: ='Section-Category'!A20 -> HOME EXPENSES | B66: =B$6 -> Jan | C66: =C$6 -> Feb | D66: =D$6 -> Mar | E66: =E$6 -> Apr | F66: =F$6 -> May | G66: =G$6 -> Jun | H66: =H$6 -> Jul | I66: =I$6 -> Aug | ... M66: =M$6 -> Dec | N66: Total | O66: Avg
A67: ='Section-Category'!A21 -> Mortgage/Rent | B67: {=IF(OR(TRIM(INDIRECT("'"&B$6&"'!"&B$4&ROW()-33))="0",INDIRECT("'"&B$6&"'!"&B$4&ROW()-33)="",NOT(ISNUMBER(INDIRECT("'"&B$6&"'!"&B$4&ROW()-33)))),"-",INDIRECT("'"&B$6&"'!"&B$4&ROW()-33))} -> - | C67: {=IF(OR(TRIM(INDIRECT("'"&C$6&"'!"&C$4&ROW()-33))="0",INDIRECT("'"&C$6&"'!"&C$4&ROW()-33)="",NOT(ISNUMBER(INDIRECT("'"&C$6&"'!"&C$4&ROW()-33)))),"-",INDIRECT("'"&C$6&"'!"&C$4&ROW()-33))} -> - | D67: {=IF(OR(TRIM(INDIRECT("'"&D$6&"'!"&D$4&ROW()-33))="0",INDIRECT("'"&D$6&"'!"&D$4&ROW()-33)="",NOT(ISNUMBER(INDIRECT("'"&D$6&"'!"&D$4&ROW()-33)))),"-",INDIRECT("'"&D$6&"'!"&D$4&ROW()-33))} -> - | E67: {=IF(OR(TRIM(INDIRECT("'"&E$6&"'!"&E$4&ROW()-33))="0",INDIRECT("'"&E$6&"'!"&E$4&ROW()-33)="",NOT(ISNUMBER(INDIRECT("'"&E$6&"'!"&E$4&ROW()-33)))),"-",INDIRECT("'"&E$6&"'!"&E$4&ROW()-33))} -> - | F67: {=IF(OR(TRIM(INDIRECT("'"&F$6&"'!"&F$4&ROW()-33))="0",INDIRECT("'"&F$6&"'!"&F$4&ROW()-33)="",NOT(ISNUMBER(INDIRECT("'"&F$6&"'!"&F$4&ROW()-33)))),"-",INDIRECT("'"&F$6&"'!"&F$4&ROW()-33))} -> - | G67: {=IF(OR(TRIM(INDIRECT("'"&G$6&"'!"&G$4&ROW()-33))="0",INDIRECT("'"&G$6&"'!"&G$4&ROW()-33)="",NOT(ISNUMBER(INDIRECT("'"&G$6&"'!"&G$4&ROW()-33)))),"-",INDIRECT("'"&G$6&"'!"&G$4&ROW()-33))} -> - | H67: {=IF(OR(TRIM(INDIRECT("'"&H$6&"'!"&H$4&ROW()-33))="0",INDIRECT("'"&H$6&"'!"&H$4&ROW()-33)="",NOT(ISNUMBER(INDIRECT("'"&H$6&"'!"&H$4&ROW()-33)))),"-",INDIRECT("'"&H$6&"'!"&H$4&ROW()-33))} -> - | I67: {=IF(OR(TRIM(INDIRECT("'"&I$6&"'!"&I$4&ROW()-33))="0",INDIRECT("'"&I$6&"'!"&I$4&ROW()-33)="",NOT(ISNUMBER(INDIRECT("'"&I$6&"'!"&I$4&ROW()-33)))),"-",INDIRECT("'"&I$6&"'!"&I$4&ROW()-33))} -> - | ... M67: {=IF(OR(TRIM(INDIRECT("'"&M$6&"'!"&M$4&ROW()-33))="0",INDIRECT("'"&M$6&"'!"&M$4&ROW()-33)="",NOT(ISNUMBER(INDIRECT("'"&M$6&"'!"&M$4&ROW()-33)))),"-",INDIRECT("'"&M$6&"'!"&M$4&ROW()-33))} -> - | N67: =SUM(B67:M67) -> 0 | O67: =N67/COLUMNS(B67:M67) -> 0
A68: ='Section-Category'!A22 -> Electricity | B68: {=IF(OR(TRIM(INDIRECT("'"&B$6&"'!"&B$4&ROW()-33))="0",INDIRECT("'"&B$6&"'!"&B$4&ROW()-33)="",NOT(ISNUMBER(INDIRECT("'"&B$6&"'!"&B$4&ROW()-33)))),"-",INDIRECT("'"&B$6&"'!"&B$4&ROW()-33))} -> - | C68: {=IF(OR(TRIM(INDIRECT("'"&C$6&"'!"&C$4&ROW()-33))="0",INDIRECT("'"&C$6&"'!"&C$4&ROW()-33)="",NOT(ISNUMBER(INDIRECT("'"&C$6&"'!"&C$4&ROW()-33)))),"-",INDIRECT("'"&C$6&"'!"&C$4&ROW()-33))} -> - | D68: {=IF(OR(TRIM(INDIRECT("'"&D$6&"'!"&D$4&ROW()-33))="0",INDIRECT("'"&D$6&"'!"&D$4&ROW()-33)="",NOT(ISNUMBER(INDIRECT("'"&D$6&"'!"&D$4&ROW()-33)))),"-",INDIRECT("'"&D$6&"'!"&D$4&ROW()-33))} -> - | E68: {=IF(OR(TRIM(INDIRECT("'"&E$6&"'!"&E$4&ROW()-33))="0",INDIRECT("'"&E$6&"'!"&E$4&ROW()-33)="",NOT(ISNUMBER(INDIRECT("'"&E$6&"'!"&E$4&ROW()-33)))),"-",INDIRECT("'"&E$6&"'!"&E$4&ROW()-33))} -> - | F68: {=IF(OR(TRIM(INDIRECT("'"&F$6&"'!"&F$4&ROW()-33))="0",INDIRECT("'"&F$6&"'!"&F$4&ROW()-33)="",NOT(ISNUMBER(INDIRECT("'"&F$6&"'!"&F$4&ROW()-33)))),"-",INDIRECT("'"&F$6&"'!"&F$4&ROW()-33))} -> - | G68: {=IF(OR(TRIM(INDIRECT("'"&G$6&"'!"&G$4&ROW()-33))="0",INDIRECT("'"&G$6&"'!"&G$4&ROW()-33)="",NOT(ISNUMBER(INDIRECT("'"&G$6&"'!"&G$4&ROW()-33)))),"-",INDIRECT("'"&G$6&"'!"&G$4&ROW()-33))} -> - | H68: {=IF(OR(TRIM(INDIRECT("'"&H$6&"'!"&H$4&ROW()-33))="0",INDIRECT("'"&H$6&"'!"&H$4&ROW()-33)="",NOT(ISNUMBER(INDIRECT("'"&H$6&"'!"&H$4&ROW()-33)))),"-",INDIRECT("'"&H$6&"'!"&H$4&ROW()-33))} -> - | I68: {=IF(OR(TRIM(INDIRECT("'"&I$6&"'!"&I$4&ROW()-33))="0",INDIRECT("'"&I$6&"'!"&I$4&ROW()-33)="",NOT(ISNUMBER(INDIRECT("'"&I$6&"'!"&I$4&ROW()-33)))),"-",INDIRECT("'"&I$6&"'!"&I$4&ROW()-33))} -> - | ... M68: {=IF(OR(TRIM(INDIRECT("'"&M$6&"'!"&M$4&ROW()-33))="0",INDIRECT("'"&M$6&"'!"&M$4&ROW()-33)="",NOT(ISNUMBER(INDIRECT("'"&M$6&"'!"&M$4&ROW()-33)))),"-",INDIRECT("'"&M$6&"'!"&M$4&ROW()-33))} -> - | N68: =SUM(B68:M68) -> 0 | O68: =N68/COLUMNS(B68:M68) -> 0
A69: ='Section-Category'!A23 -> Gas/Oil | B69: {=IF(OR(TRIM(INDIRECT("'"&B$6&"'!"&B$4&ROW()-33))="0",INDIRECT("'"&B$6&"'!"&B$4&ROW()-33)="",NOT(ISNUMBER(INDIRECT("'"&B$6&"'!"&B$4&ROW()-33)))),"-",INDIRECT("'"&B$6&"'!"&B$4&ROW()-33))} -> - | C69: {=IF(OR(TRIM(INDIRECT("'"&C$6&"'!"&C$4&ROW()-33))="0",INDIRECT("'"&C$6&"'!"&C$4&ROW()-33)="",NOT(ISNUMBER(INDIRECT("'"&C$6&"'!"&C$4&ROW()-33)))),"-",INDIRECT("'"&C$6&"'!"&C$4&ROW()-33))} -> - | D69: {=IF(OR(TRIM(INDIRECT("'"&D$6&"'!"&D$4&ROW()-33))="0",INDIRECT("'"&D$6&"'!"&D$4&ROW()-33)="",NOT(ISNUMBER(INDIRECT("'"&D$6&"'!"&D$4&ROW()-33)))),"-",INDIRECT("'"&D$6&"'!"&D$4&ROW()-33))} -> - | E69: {=IF(OR(TRIM(INDIRECT("'"&E$6&"'!"&E$4&ROW()-33))="0",INDIRECT("'"&E$6&"'!"&E$4&ROW()-33)="",NOT(ISNUMBER(INDIRECT("'"&E$6&"'!"&E$4&ROW()-33)))),"-",INDIRECT("'"&E$6&"'!"&E$4&ROW()-33))} -> - | F69: {=IF(OR(TRIM(INDIRECT("'"&F$6&"'!"&F$4&ROW()-33))="0",INDIRECT("'"&F$6&"'!"&F$4&ROW()-33)="",NOT(ISNUMBER(INDIRECT("'"&F$6&"'!"&F$4&ROW()-33)))),"-",INDIRECT("'"&F$6&"'!"&F$4&ROW()-33))} -> - | G69: {=IF(OR(TRIM(INDIRECT("'"&G$6&"'!"&G$4&ROW()-33))="0",INDIRECT("'"&G$6&"'!"&G$4&ROW()-33)="",NOT(ISNUMBER(INDIRECT("'"&G$6&"'!"&G$4&ROW()-33)))),"-",INDIRECT("'"&G$6&"'!"&G$4&ROW()-33))} -> - | H69: {=IF(OR(TRIM(INDIRECT("'"&H$6&"'!"&H$4&ROW()-33))="0",INDIRECT("'"&H$6&"'!"&H$4&ROW()-33)="",NOT(ISNUMBER(INDIRECT("'"&H$6&"'!"&H$4&ROW()-33)))),"-",INDIRECT("'"&H$6&"'!"&H$4&ROW()-33))} -> - | I69: {=IF(OR(TRIM(INDIRECT("'"&I$6&"'!"&I$4&ROW()-33))="0",INDIRECT("'"&I$6&"'!"&I$4&ROW()-33)="",NOT(ISNUMBER(INDIRECT("'"&I$6&"'!"&I$4&ROW()-33)))),"-",INDIRECT("'"&I$6&"'!"&I$4&ROW()-33))} -> - | ... M69: {=IF(OR(TRIM(INDIRECT("'"&M$6&"'!"&M$4&ROW()-33))="0",INDIRECT("'"&M$6&"'!"&M$4&ROW()-33)="",NOT(ISNUMBER(INDIRECT("'"&M$6&"'!"&M$4&ROW()-33)))),"-",INDIRECT("'"&M$6&"'!"&M$4&ROW()-33))} -> - | N69: =SUM(B69:M69) -> 0 | O69: =N69/COLUMNS(B69:M69) -> 0
A70: ='Section-Category'!A24 -> Water/Sewer/Trash | B70: {=IF(OR(TRIM(INDIRECT("'"&B$6&"'!"&B$4&ROW()-33))="0",INDIRECT("'"&B$6&"'!"&B$4&ROW()-33)="",NOT(ISNUMBER(INDIRECT("'"&B$6&"'!"&B$4&ROW()-33)))),"-",INDIRECT("'"&B$6&"'!"&B$4&ROW()-33))} -> - | C70: {=IF(OR(TRIM(INDIRECT("'"&C$6&"'!"&C$4&ROW()-33))="0",INDIRECT("'"&C$6&"'!"&C$4&ROW()-33)="",NOT(ISNUMBER(INDIRECT("'"&C$6&"'!"&C$4&ROW()-33)))),"-",INDIRECT("'"&C$6&"'!"&C$4&ROW()-33))} -> - | D70: {=IF(OR(TRIM(INDIRECT("'"&D$6&"'!"&D$4&ROW()-33))="0",INDIRECT("'"&D$6&"'!"&D$4&ROW()-33)="",NOT(ISNUMBER(INDIRECT("'"&D$6&"'!"&D$4&ROW()-33)))),"-",INDIRECT("'"&D$6&"'!"&D$4&ROW()-33))} -> - | E70: {=IF(OR(TRIM(INDIRECT("'"&E$6&"'!"&E$4&ROW()-33))="0",INDIRECT("'"&E$6&"'!"&E$4&ROW()-33)="",NOT(ISNUMBER(INDIRECT("'"&E$6&"'!"&E$4&ROW()-33)))),"-",INDIRECT("'"&E$6&"'!"&E$4&ROW()-33))} -> - | F70: {=IF(OR(TRIM(INDIRECT("'"&F$6&"'!"&F$4&ROW()-33))="0",INDIRECT("'"&F$6&"'!"&F$4&ROW()-33)="",NOT(ISNUMBER(INDIRECT("'"&F$6&"'!"&F$4&ROW()-33)))),"-",INDIRECT("'"&F$6&"'!"&F$4&ROW()-33))} -> - | G70: {=IF(OR(TRIM(INDIRECT("'"&G$6&"'!"&G$4&ROW()-33))="0",INDIRECT("'"&G$6&"'!"&G$4&ROW()-33)="",NOT(ISNUMBER(INDIRECT("'"&G$6&"'!"&G$4&ROW()-33)))),"-",INDIRECT("'"&G$6&"'!"&G$4&ROW()-33))} -> - | H70: {=IF(OR(TRIM(INDIRECT("'"&H$6&"'!"&H$4&ROW()-33))="0",INDIRECT("'"&H$6&"'!"&H$4&ROW()-33)="",NOT(ISNUMBER(INDIRECT("'"&H$6&"'!"&H$4&ROW()-33)))),"-",INDIRECT("'"&H$6&"'!"&H$4&ROW()-33))} -> - | I70: {=IF(OR(TRIM(INDIRECT("'"&I$6&"'!"&I$4&ROW()-33))="0",INDIRECT("'"&I$6&"'!"&I$4&ROW()-33)="",NOT(ISNUMBER(INDIRECT("'"&I$6&"'!"&I$4&ROW()-33)))),"-",INDIRECT("'"&I$6&"'!"&I$4&ROW()-33))} -> - | ... M70: {=IF(OR(TRIM(INDIRECT("'"&M$6&"'!"&M$4&ROW()-33))="0",INDIRECT("'"&M$6&"'!"&M$4&ROW()-33)="",NOT(ISNUMBER(INDIRECT("'"&M$6&"'!"&M$4&ROW()-33)))),"-",INDIRECT("'"&M$6&"'!"&M$4&ROW()-33))} -> - | N70: =SUM(B70:M70) -> 0 | O70: =N70/COLUMNS(B70:M70) -> 0
A71: ='Section-Category'!A25 -> Phone | B71: {=IF(OR(TRIM(INDIRECT("'"&B$6&"'!"&B$4&ROW()-33))="0",INDIRECT("'"&B$6&"'!"&B$4&ROW()-33)="",NOT(ISNUMBER(INDIRECT("'"&B$6&"'!"&B$4&ROW()-33)))),"-",INDIRECT("'"&B$6&"'!"&B$4&ROW()-33))} -> - | C71: {=IF(OR(TRIM(INDIRECT("'"&C$6&"'!"&C$4&ROW()-33))="0",INDIRECT("'"&C$6&"'!"&C$4&ROW()-33)="",NOT(ISNUMBER(INDIRECT("'"&C$6&"'!"&C$4&ROW()-33)))),"-",INDIRECT("'"&C$6&"'!"&C$4&ROW()-33))} -> - | D71: {=IF(OR(TRIM(INDIRECT("'"&D$6&"'!"&D$4&ROW()-33))="0",INDIRECT("'"&D$6&"'!"&D$4&ROW()-33)="",NOT(ISNUMBER(INDIRECT("'"&D$6&"'!"&D$4&ROW()-33)))),"-",INDIRECT("'"&D$6&"'!"&D$4&ROW()-33))} -> - | E71: {=IF(OR(TRIM(INDIRECT("'"&E$6&"'!"&E$4&ROW()-33))="0",INDIRECT("'"&E$6&"'!"&E$4&ROW()-33)="",NOT(ISNUMBER(INDIRECT("'"&E$6&"'!"&E$4&ROW()-33)))),"-",INDIRECT("'"&E$6&"'!"&E$4&ROW()-33))} -> - | F71: {=IF(OR(TRIM(INDIRECT("'"&F$6&"'!"&F$4&ROW()-33))="0",INDIRECT("'"&F$6&"'!"&F$4&ROW()-33)="",NOT(ISNUMBER(INDIRECT("'"&F$6&"'!"&F$4&ROW()-33)))),"-",INDIRECT("'"&F$6&"'!"&F$4&ROW()-33))} -> - | G71: {=IF(OR(TRIM(INDIRECT("'"&G$6&"'!"&G$4&ROW()-33))="0",INDIRECT("'"&G$6&"'!"&G$4&ROW()-33)="",NOT(ISNUMBER(INDIRECT("'"&G$6&"'!"&G$4&ROW()-33)))),"-",INDIRECT("'"&G$6&"'!"&G$4&ROW()-33))} -> - | H71: {=IF(OR(TRIM(INDIRECT("'"&H$6&"'!"&H$4&ROW()-33))="0",INDIRECT("'"&H$6&"'!"&H$4&ROW()-33)="",NOT(ISNUMBER(INDIRECT("'"&H$6&"'!"&H$4&ROW()-33)))),"-",INDIRECT("'"&H$6&"'!"&H$4&ROW()-33))} -> - | I71: {=IF(OR(TRIM(INDIRECT("'"&I$6&"'!"&I$4&ROW()-33))="0",INDIRECT("'"&I$6&"'!"&I$4&ROW()-33)="",NOT(ISNUMBER(INDIRECT("'"&I$6&"'!"&I$4&ROW()-33)))),"-",INDIRECT("'"&I$6&"'!"&I$4&ROW()-33))} -> - | ... M71: {=IF(OR(TRIM(INDIRECT("'"&M$6&"'!"&M$4&ROW()-33))="0",INDIRECT("'"&M$6&"'!"&M$4&ROW()-33)="",NOT(ISNUMBER(INDIRECT("'"&M$6&"'!"&M$4&ROW()-33)))),"-",INDIRECT("'"&M$6&"'!"&M$4&ROW()-33))} -> - | N71: =SUM(B71:M71) -> 0 | O71: =N71/COLUMNS(B71:M71) -> 0
A72: ='Section-Category'!A26 -> Cable/Satellite | B72: {=IF(OR(TRIM(INDIRECT("'"&B$6&"'!"&B$4&ROW()-33))="0",INDIRECT("'"&B$6&"'!"&B$4&ROW()-33)="",NOT(ISNUMBER(INDIRECT("'"&B$6&"'!"&B$4&ROW()-33)))),"-",INDIRECT("'"&B$6&"'!"&B$4&ROW()-33))} -> - | C72: {=IF(OR(TRIM(INDIRECT("'"&C$6&"'!"&C$4&ROW()-33))="0",INDIRECT("'"&C$6&"'!"&C$4&ROW()-33)="",NOT(ISNUMBER(INDIRECT("'"&C$6&"'!"&C$4&ROW()-33)))),"-",INDIRECT("'"&C$6&"'!"&C$4&ROW()-33))} -> - | D72: {=IF(OR(TRIM(INDIRECT("'"&D$6&"'!"&D$4&ROW()-33))="0",INDIRECT("'"&D$6&"'!"&D$4&ROW()-33)="",NOT(ISNUMBER(INDIRECT("'"&D$6&"'!"&D$4&ROW()-33)))),"-",INDIRECT("'"&D$6&"'!"&D$4&ROW()-33))} -> - | E72: {=IF(OR(TRIM(INDIRECT("'"&E$6&"'!"&E$4&ROW()-33))="0",INDIRECT("'"&E$6&"'!"&E$4&ROW()-33)="",NOT(ISNUMBER(INDIRECT("'"&E$6&"'!"&E$4&ROW()-33)))),"-",INDIRECT("'"&E$6&"'!"&E$4&ROW()-33))} -> - | F72: {=IF(OR(TRIM(INDIRECT("'"&F$6&"'!"&F$4&ROW()-33))="0",INDIRECT("'"&F$6&"'!"&F$4&ROW()-33)="",NOT(ISNUMBER(INDIRECT("'"&F$6&"'!"&F$4&ROW()-33)))),"-",INDIRECT("'"&F$6&"'!"&F$4&ROW()-33))} -> - | G72: {=IF(OR(TRIM(INDIRECT("'"&G$6&"'!"&G$4&ROW()-33))="0",INDIRECT("'"&G$6&"'!"&G$4&ROW()-33)="",NOT(ISNUMBER(INDIRECT("'"&G$6&"'!"&G$4&ROW()-33)))),"-",INDIRECT("'"&G$6&"'!"&G$4&ROW()-33))} -> - | H72: {=IF(OR(TRIM(INDIRECT("'"&H$6&"'!"&H$4&ROW()-33))="0",INDIRECT("'"&H$6&"'!"&H$4&ROW()-33)="",NOT(ISNUMBER(INDIRECT("'"&H$6&"'!"&H$4&ROW()-33)))),"-",INDIRECT("'"&H$6&"'!"&H$4&ROW()-33))} -> - | I72: {=IF(OR(TRIM(INDIRECT("'"&I$6&"'!"&I$4&ROW()-33))="0",INDIRECT("'"&I$6&"'!"&I$4&ROW()-33)="",NOT(ISNUMBER(INDIRECT("'"&I$6&"'!"&I$4&ROW()-33)))),"-",INDIRECT("'"&I$6&"'!"&I$4&ROW()-33))} -> - | ... M72: {=IF(OR(TRIM(INDIRECT("'"&M$6&"'!"&M$4&ROW()-33))="0",INDIRECT("'"&M$6&"'!"&M$4&ROW()-33)="",NOT(ISNUMBER(INDIRECT("'"&M$6&"'!"&M$4&ROW()-33)))),"-",INDIRECT("'"&M$6&"'!"&M$4&ROW()-33))} -> - | N72: =SUM(B72:M72) -> 0 | O72: =N72/COLUMNS(B72:M72) -> 0
A73: ='Section-Category'!A27 -> Internet | B73: {=IF(OR(TRIM(INDIRECT("'"&B$6&"'!"&B$4&ROW()-33))="0",INDIRECT("'"&B$6&"'!"&B$4&ROW()-33)="",NOT(ISNUMBER(INDIRECT("'"&B$6&"'!"&B$4&ROW()-33)))),"-",INDIRECT("'"&B$6&"'!"&B$4&ROW()-33))} -> - | C73: {=IF(OR(TRIM(INDIRECT("'"&C$6&"'!"&C$4&ROW()-33))="0",INDIRECT("'"&C$6&"'!"&C$4&ROW()-33)="",NOT(ISNUMBER(INDIRECT("'"&C$6&"'!"&C$4&ROW()-33)))),"-",INDIRECT("'"&C$6&"'!"&C$4&ROW()-33))} -> - | D73: {=IF(OR(TRIM(INDIRECT("'"&D$6&"'!"&D$4&ROW()-33))="0",INDIRECT("'"&D$6&"'!"&D$4&ROW()-33)="",NOT(ISNUMBER(INDIRECT("'"&D$6&"'!"&D$4&ROW()-33)))),"-",INDIRECT("'"&D$6&"'!"&D$4&ROW()-33))} -> - | E73: {=IF(OR(TRIM(INDIRECT("'"&E$6&"'!"&E$4&ROW()-33))="0",INDIRECT("'"&E$6&"'!"&E$4&ROW()-33)="",NOT(ISNUMBER(INDIRECT("'"&E$6&"'!"&E$4&ROW()-33)))),"-",INDIRECT("'"&E$6&"'!"&E$4&ROW()-33))} -> - | F73: {=IF(OR(TRIM(INDIRECT("'"&F$6&"'!"&F$4&ROW()-33))="0",INDIRECT("'"&F$6&"'!"&F$4&ROW()-33)="",NOT(ISNUMBER(INDIRECT("'"&F$6&"'!"&F$4&ROW()-33)))),"-",INDIRECT("'"&F$6&"'!"&F$4&ROW()-33))} -> - | G73: {=IF(OR(TRIM(INDIRECT("'"&G$6&"'!"&G$4&ROW()-33))="0",INDIRECT("'"&G$6&"'!"&G$4&ROW()-33)="",NOT(ISNUMBER(INDIRECT("'"&G$6&"'!"&G$4&ROW()-33)))),"-",INDIRECT("'"&G$6&"'!"&G$4&ROW()-33))} -> - | H73: {=IF(OR(TRIM(INDIRECT("'"&H$6&"'!"&H$4&ROW()-33))="0",INDIRECT("'"&H$6&"'!"&H$4&ROW()-33)="",NOT(ISNUMBER(INDIRECT("'"&H$6&"'!"&H$4&ROW()-33)))),"-",INDIRECT("'"&H$6&"'!"&H$4&ROW()-33))} -> - | I73: {=IF(OR(TRIM(INDIRECT("'"&I$6&"'!"&I$4&ROW()-33))="0",INDIRECT("'"&I$6&"'!"&I$4&ROW()-33)="",NOT(ISNUMBER(INDIRECT("'"&I$6&"'!"&I$4&ROW()-33)))),"-",INDIRECT("'"&I$6&"'!"&I$4&ROW()-33))} -> - | ... M73: {=IF(OR(TRIM(INDIRECT("'"&M$6&"'!"&M$4&ROW()-33))="0",INDIRECT("'"&M$6&"'!"&M$4&ROW()-33)="",NOT(ISNUMBER(INDIRECT("'"&M$6&"'!"&M$4&ROW()-33)))),"-",INDIRECT("'"&M$6&"'!"&M$4&ROW()-33))} -> - | N73: =SUM(B73:M73) -> 0 | O73: =N73/COLUMNS(B73:M73) -> 0
A74: ='Section-Category'!A28 -> Furnishings/Appliances | B74: {=IF(OR(TRIM(INDIRECT("'"&B$6&"'!"&B$4&ROW()-33))="0",INDIRECT("'"&B$6&"'!"&B$4&ROW()-33)="",NOT(ISNUMBER(INDIRECT("'"&B$6&"'!"&B$4&ROW()-33)))),"-",INDIRECT("'"&B$6&"'!"&B$4&ROW()-33))} -> - | C74: {=IF(OR(TRIM(INDIRECT("'"&C$6&"'!"&C$4&ROW()-33))="0",INDIRECT("'"&C$6&"'!"&C$4&ROW()-33)="",NOT(ISNUMBER(INDIRECT("'"&C$6&"'!"&C$4&ROW()-33)))),"-",INDIRECT("'"&C$6&"'!"&C$4&ROW()-33))} -> - | D74: {=IF(OR(TRIM(INDIRECT("'"&D$6&"'!"&D$4&ROW()-33))="0",INDIRECT("'"&D$6&"'!"&D$4&ROW()-33)="",NOT(ISNUMBER(INDIRECT("'"&D$6&"'!"&D$4&ROW()-33)))),"-",INDIRECT("'"&D$6&"'!"&D$4&ROW()-33))} -> - | E74: {=IF(OR(TRIM(INDIRECT("'"&E$6&"'!"&E$4&ROW()-33))="0",INDIRECT("'"&E$6&"'!"&E$4&ROW()-33)="",NOT(ISNUMBER(INDIRECT("'"&E$6&"'!"&E$4&ROW()-33)))),"-",INDIRECT("'"&E$6&"'!"&E$4&ROW()-33))} -> - | F74: {=IF(OR(TRIM(INDIRECT("'"&F$6&"'!"&F$4&ROW()-33))="0",INDIRECT("'"&F$6&"'!"&F$4&ROW()-33)="",NOT(ISNUMBER(INDIRECT("'"&F$6&"'!"&F$4&ROW()-33)))),"-",INDIRECT("'"&F$6&"'!"&F$4&ROW()-33))} -> - | G74: {=IF(OR(TRIM(INDIRECT("'"&G$6&"'!"&G$4&ROW()-33))="0",INDIRECT("'"&G$6&"'!"&G$4&ROW()-33)="",NOT(ISNUMBER(INDIRECT("'"&G$6&"'!"&G$4&ROW()-33)))),"-",INDIRECT("'"&G$6&"'!"&G$4&ROW()-33))} -> - | H74: {=IF(OR(TRIM(INDIRECT("'"&H$6&"'!"&H$4&ROW()-33))="0",INDIRECT("'"&H$6&"'!"&H$4&ROW()-33)="",NOT(ISNUMBER(INDIRECT("'"&H$6&"'!"&H$4&ROW()-33)))),"-",INDIRECT("'"&H$6&"'!"&H$4&ROW()-33))} -> - | I74: {=IF(OR(TRIM(INDIRECT("'"&I$6&"'!"&I$4&ROW()-33))="0",INDIRECT("'"&I$6&"'!"&I$4&ROW()-33)="",NOT(ISNUMBER(INDIRECT("'"&I$6&"'!"&I$4&ROW()-33)))),"-",INDIRECT("'"&I$6&"'!"&I$4&ROW()-33))} -> - | ... M74: {=IF(OR(TRIM(INDIRECT("'"&M$6&"'!"&M$4&ROW()-33))="0",INDIRECT("'"&M$6&"'!"&M$4&ROW()-33)="",NOT(ISNUMBER(INDIRECT("'"&M$6&"'!"&M$4&ROW()-33)))),"-",INDIRECT("'"&M$6&"'!"&M$4&ROW()-33))} -> - | N74: =SUM(B74:M74) -> 0 | O74: =N74/COLUMNS(B74:M74) -> 0
A75: ='Section-Category'!A29 -> Lawn/Garden | B75: {=IF(OR(TRIM(INDIRECT("'"&B$6&"'!"&B$4&ROW()-33))="0",INDIRECT("'"&B$6&"'!"&B$4&ROW()-33)="",NOT(ISNUMBER(INDIRECT("'"&B$6&"'!"&B$4&ROW()-33)))),"-",INDIRECT("'"&B$6&"'!"&B$4&ROW()-33))} -> - | C75: {=IF(OR(TRIM(INDIRECT("'"&C$6&"'!"&C$4&ROW()-33))="0",INDIRECT("'"&C$6&"'!"&C$4&ROW()-33)="",NOT(ISNUMBER(INDIRECT("'"&C$6&"'!"&C$4&ROW()-33)))),"-",INDIRECT("'"&C$6&"'!"&C$4&ROW()-33))} -> - | D75: {=IF(OR(TRIM(INDIRECT("'"&D$6&"'!"&D$4&ROW()-33))="0",INDIRECT("'"&D$6&"'!"&D$4&ROW()-33)="",NOT(ISNUMBER(INDIRECT("'"&D$6&"'!"&D$4&ROW()-33)))),"-",INDIRECT("'"&D$6&"'!"&D$4&ROW()-33))} -> - | E75: {=IF(OR(TRIM(INDIRECT("'"&E$6&"'!"&E$4&ROW()-33))="0",INDIRECT("'"&E$6&"'!"&E$4&ROW()-33)="",NOT(ISNUMBER(INDIRECT("'"&E$6&"'!"&E$4&ROW()-33)))),"-",INDIRECT("'"&E$6&"'!"&E$4&ROW()-33))} -> - | F75: {=IF(OR(TRIM(INDIRECT("'"&F$6&"'!"&F$4&ROW()-33))="0",INDIRECT("'"&F$6&"'!"&F$4&ROW()-33)="",NOT(ISNUMBER(INDIRECT("'"&F$6&"'!"&F$4&ROW()-33)))),"-",INDIRECT("'"&F$6&"'!"&F$4&ROW()-33))} -> - | G75: {=IF(OR(TRIM(INDIRECT("'"&G$6&"'!"&G$4&ROW()-33))="0",INDIRECT("'"&G$6&"'!"&G$4&ROW()-33)="",NOT(ISNUMBER(INDIRECT("'"&G$6&"'!"&G$4&ROW()-33)))),"-",INDIRECT("'"&G$6&"'!"&G$4&ROW()-33))} -> - | H75: {=IF(OR(TRIM(INDIRECT("'"&H$6&"'!"&H$4&ROW()-33))="0",INDIRECT("'"&H$6&"'!"&H$4&ROW()-33)="",NOT(ISNUMBER(INDIRECT("'"&H$6&"'!"&H$4&ROW()-33)))),"-",INDIRECT("'"&H$6&"'!"&H$4&ROW()-33))} -> - | I75: {=IF(OR(TRIM(INDIRECT("'"&I$6&"'!"&I$4&ROW()-33))="0",INDIRECT("'"&I$6&"'!"&I$4&ROW()-33)="",NOT(ISNUMBER(INDIRECT("'"&I$6&"'!"&I$4&ROW()-33)))),"-",INDIRECT("'"&I$6&"'!"&I$4&ROW()-33))} -> - | ... M75: {=IF(OR(TRIM(INDIRECT("'"&M$6&"'!"&M$4&ROW()-33))="0",INDIRECT("'"&M$6&"'!"&M$4&ROW()-33)="",NOT(ISNUMBER(INDIRECT("'"&M$6&"'!"&M$4&ROW()-33)))),"-",INDIRECT("'"&M$6&"'!"&M$4&ROW()-33))} -> - | N75: =SUM(B75:M75) -> 0 | O75: =N75/COLUMNS(B75:M75) -> 0
A76: ='Section-Category'!A30 -> Home Supplies | B76: {=IF(OR(TRIM(INDIRECT("'"&B$6&"'!"&B$4&ROW()-33))="0",INDIRECT("'"&B$6&"'!"&B$4&ROW()-33)="",NOT(ISNUMBER(INDIRECT("'"&B$6&"'!"&B$4&ROW()-33)))),"-",INDIRECT("'"&B$6&"'!"&B$4&ROW()-33))} -> - | C76: {=IF(OR(TRIM(INDIRECT("'"&C$6&"'!"&C$4&ROW()-33))="0",INDIRECT("'"&C$6&"'!"&C$4&ROW()-33)="",NOT(ISNUMBER(INDIRECT("'"&C$6&"'!"&C$4&ROW()-33)))),"-",INDIRECT("'"&C$6&"'!"&C$4&ROW()-33))} -> - | D76: {=IF(OR(TRIM(INDIRECT("'"&D$6&"'!"&D$4&ROW()-33))="0",INDIRECT("'"&D$6&"'!"&D$4&ROW()-33)="",NOT(ISNUMBER(INDIRECT("'"&D$6&"'!"&D$4&ROW()-33)))),"-",INDIRECT("'"&D$6&"'!"&D$4&ROW()-33))} -> - | E76: {=IF(OR(TRIM(INDIRECT("'"&E$6&"'!"&E$4&ROW()-33))="0",INDIRECT("'"&E$6&"'!"&E$4&ROW()-33)="",NOT(ISNUMBER(INDIRECT("'"&E$6&"'!"&E$4&ROW()-33)))),"-",INDIRECT("'"&E$6&"'!"&E$4&ROW()-33))} -> - | F76: {=IF(OR(TRIM(INDIRECT("'"&F$6&"'!"&F$4&ROW()-33))="0",INDIRECT("'"&F$6&"'!"&F$4&ROW()-33)="",NOT(ISNUMBER(INDIRECT("'"&F$6&"'!"&F$4&ROW()-33)))),"-",INDIRECT("'"&F$6&"'!"&F$4&ROW()-33))} -> - | G76: {=IF(OR(TRIM(INDIRECT("'"&G$6&"'!"&G$4&ROW()-33))="0",INDIRECT("'"&G$6&"'!"&G$4&ROW()-33)="",NOT(ISNUMBER(INDIRECT("'"&G$6&"'!"&G$4&ROW()-33)))),"-",INDIRECT("'"&G$6&"'!"&G$4&ROW()-33))} -> - | H76: {=IF(OR(TRIM(INDIRECT("'"&H$6&"'!"&H$4&ROW()-33))="0",INDIRECT("'"&H$6&"'!"&H$4&ROW()-33)="",NOT(ISNUMBER(INDIRECT("'"&H$6&"'!"&H$4&ROW()-33)))),"-",INDIRECT("'"&H$6&"'!"&H$4&ROW()-33))} -> - | I76: {=IF(OR(TRIM(INDIRECT("'"&I$6&"'!"&I$4&ROW()-33))="0",INDIRECT("'"&I$6&"'!"&I$4&ROW()-33)="",NOT(ISNUMBER(INDIRECT("'"&I$6&"'!"&I$4&ROW()-33)))),"-",INDIRECT("'"&I$6&"'!"&I$4&ROW()-33))} -> - | ... M76: {=IF(OR(TRIM(INDIRECT("'"&M$6&"'!"&M$4&ROW()-33))="0",INDIRECT("'"&M$6&"'!"&M$4&ROW()-33)="",NOT(ISNUMBER(INDIRECT("'"&M$6&"'!"&M$4&ROW()-33)))),"-",INDIRECT("'"&M$6&"'!"&M$4&ROW()-33))} -> - | N76: =SUM(B76:M76) -> 0 | O76: =N76/COLUMNS(B76:M76) -> 0
A77: ='Section-Category'!A31 -> Maintenance | B77: {=IF(OR(TRIM(INDIRECT("'"&B$6&"'!"&B$4&ROW()-33))="0",INDIRECT("'"&B$6&"'!"&B$4&ROW()-33)="",NOT(ISNUMBER(INDIRECT("'"&B$6&"'!"&B$4&ROW()-33)))),"-",INDIRECT("'"&B$6&"'!"&B$4&ROW()-33))} -> - | C77: {=IF(OR(TRIM(INDIRECT("'"&C$6&"'!"&C$4&ROW()-33))="0",INDIRECT("'"&C$6&"'!"&C$4&ROW()-33)="",NOT(ISNUMBER(INDIRECT("'"&C$6&"'!"&C$4&ROW()-33)))),"-",INDIRECT("'"&C$6&"'!"&C$4&ROW()-33))} -> - | D77: {=IF(OR(TRIM(INDIRECT("'"&D$6&"'!"&D$4&ROW()-33))="0",INDIRECT("'"&D$6&"'!"&D$4&ROW()-33)="",NOT(ISNUMBER(INDIRECT("'"&D$6&"'!"&D$4&ROW()-33)))),"-",INDIRECT("'"&D$6&"'!"&D$4&ROW()-33))} -> - | E77: {=IF(OR(TRIM(INDIRECT("'"&E$6&"'!"&E$4&ROW()-33))="0",INDIRECT("'"&E$6&"'!"&E$4&ROW()-33)="",NOT(ISNUMBER(INDIRECT("'"&E$6&"'!"&E$4&ROW()-33)))),"-",INDIRECT("'"&E$6&"'!"&E$4&ROW()-33))} -> - | F77: {=IF(OR(TRIM(INDIRECT("'"&F$6&"'!"&F$4&ROW()-33))="0",INDIRECT("'"&F$6&"'!"&F$4&ROW()-33)="",NOT(ISNUMBER(INDIRECT("'"&F$6&"'!"&F$4&ROW()-33)))),"-",INDIRECT("'"&F$6&"'!"&F$4&ROW()-33))} -> - | G77: {=IF(OR(TRIM(INDIRECT("'"&G$6&"'!"&G$4&ROW()-33))="0",INDIRECT("'"&G$6&"'!"&G$4&ROW()-33)="",NOT(ISNUMBER(INDIRECT("'"&G$6&"'!"&G$4&ROW()-33)))),"-",INDIRECT("'"&G$6&"'!"&G$4&ROW()-33))} -> - | H77: {=IF(OR(TRIM(INDIRECT("'"&H$6&"'!"&H$4&ROW()-33))="0",INDIRECT("'"&H$6&"'!"&H$4&ROW()-33)="",NOT(ISNUMBER(INDIRECT("'"&H$6&"'!"&H$4&ROW()-33)))),"-",INDIRECT("'"&H$6&"'!"&H$4&ROW()-33))} -> - | I77: {=IF(OR(TRIM(INDIRECT("'"&I$6&"'!"&I$4&ROW()-33))="0",INDIRECT("'"&I$6&"'!"&I$4&ROW()-33)="",NOT(ISNUMBER(INDIRECT("'"&I$6&"'!"&I$4&ROW()-33)))),"-",INDIRECT("'"&I$6&"'!"&I$4&ROW()-33))} -> - | ... M77: {=IF(OR(TRIM(INDIRECT("'"&M$6&"'!"&M$4&ROW()-33))="0",INDIRECT("'"&M$6&"'!"&M$4&ROW()-33)="",NOT(ISNUMBER(INDIRECT("'"&M$6&"'!"&M$4&ROW()-33)))),"-",INDIRECT("'"&M$6&"'!"&M$4&ROW()-33))} -> - | N77: =SUM(B77:M77) -> 0 | O77: =N77/COLUMNS(B77:M77) -> 0
A78: ='Section-Category'!A32 -> Improvements | B78: {=IF(OR(TRIM(INDIRECT("'"&B$6&"'!"&B$4&ROW()-33))="0",INDIRECT("'"&B$6&"'!"&B$4&ROW()-33)="",NOT(ISNUMBER(INDIRECT("'"&B$6&"'!"&B$4&ROW()-33)))),"-",INDIRECT("'"&B$6&"'!"&B$4&ROW()-33))} -> - | C78: {=IF(OR(TRIM(INDIRECT("'"&C$6&"'!"&C$4&ROW()-33))="0",INDIRECT("'"&C$6&"'!"&C$4&ROW()-33)="",NOT(ISNUMBER(INDIRECT("'"&C$6&"'!"&C$4&ROW()-33)))),"-",INDIRECT("'"&C$6&"'!"&C$4&ROW()-33))} -> - | D78: {=IF(OR(TRIM(INDIRECT("'"&D$6&"'!"&D$4&ROW()-33))="0",INDIRECT("'"&D$6&"'!"&D$4&ROW()-33)="",NOT(ISNUMBER(INDIRECT("'"&D$6&"'!"&D$4&ROW()-33)))),"-",INDIRECT("'"&D$6&"'!"&D$4&ROW()-33))} -> - | E78: {=IF(OR(TRIM(INDIRECT("'"&E$6&"'!"&E$4&ROW()-33))="0",INDIRECT("'"&E$6&"'!"&E$4&ROW()-33)="",NOT(ISNUMBER(INDIRECT("'"&E$6&"'!"&E$4&ROW()-33)))),"-",INDIRECT("'"&E$6&"'!"&E$4&ROW()-33))} -> - | F78: {=IF(OR(TRIM(INDIRECT("'"&F$6&"'!"&F$4&ROW()-33))="0",INDIRECT("'"&F$6&"'!"&F$4&ROW()-33)="",NOT(ISNUMBER(INDIRECT("'"&F$6&"'!"&F$4&ROW()-33)))),"-",INDIRECT("'"&F$6&"'!"&F$4&ROW()-33))} -> - | G78: {=IF(OR(TRIM(INDIRECT("'"&G$6&"'!"&G$4&ROW()-33))="0",INDIRECT("'"&G$6&"'!"&G$4&ROW()-33)="",NOT(ISNUMBER(INDIRECT("'"&G$6&"'!"&G$4&ROW()-33)))),"-",INDIRECT("'"&G$6&"'!"&G$4&ROW()-33))} -> - | H78: {=IF(OR(TRIM(INDIRECT("'"&H$6&"'!"&H$4&ROW()-33))="0",INDIRECT("'"&H$6&"'!"&H$4&ROW()-33)="",NOT(ISNUMBER(INDIRECT("'"&H$6&"'!"&H$4&ROW()-33)))),"-",INDIRECT("'"&H$6&"'!"&H$4&ROW()-33))} -> - | I78: {=IF(OR(TRIM(INDIRECT("'"&I$6&"'!"&I$4&ROW()-33))="0",INDIRECT("'"&I$6&"'!"&I$4&ROW()-33)="",NOT(ISNUMBER(INDIRECT("'"&I$6&"'!"&I$4&ROW()-33)))),"-",INDIRECT("'"&I$6&"'!"&I$4&ROW()-33))} -> - | ... M78: {=IF(OR(TRIM(INDIRECT("'"&M$6&"'!"&M$4&ROW()-33))="0",INDIRECT("'"&M$6&"'!"&M$4&ROW()-33)="",NOT(ISNUMBER(INDIRECT("'"&M$6&"'!"&M$4&ROW()-33)))),"-",INDIRECT("'"&M$6&"'!"&M$4&ROW()-33))} -> - | N78: =SUM(B78:M78) -> 0 | O78: =N78/COLUMNS(B78:M78) -> 0
A79: ='Section-Category'!A33 -> Other | B79: {=IF(OR(TRIM(INDIRECT("'"&B$6&"'!"&B$4&ROW()-33))="0",INDIRECT("'"&B$6&"'!"&B$4&ROW()-33)="",NOT(ISNUMBER(INDIRECT("'"&B$6&"'!"&B$4&ROW()-33)))),"-",INDIRECT("'"&B$6&"'!"&B$4&ROW()-33))} -> - | C79: {=IF(OR(TRIM(INDIRECT("'"&C$6&"'!"&C$4&ROW()-33))="0",INDIRECT("'"&C$6&"'!"&C$4&ROW()-33)="",NOT(ISNUMBER(INDIRECT("'"&C$6&"'!"&C$4&ROW()-33)))),"-",INDIRECT("'"&C$6&"'!"&C$4&ROW()-33))} -> - | D79: {=IF(OR(TRIM(INDIRECT("'"&D$6&"'!"&D$4&ROW()-33))="0",INDIRECT("'"&D$6&"'!"&D$4&ROW()-33)="",NOT(ISNUMBER(INDIRECT("'"&D$6&"'!"&D$4&ROW()-33)))),"-",INDIRECT("'"&D$6&"'!"&D$4&ROW()-33))} -> - | E79: {=IF(OR(TRIM(INDIRECT("'"&E$6&"'!"&E$4&ROW()-33))="0",INDIRECT("'"&E$6&"'!"&E$4&ROW()-33)="",NOT(ISNUMBER(INDIRECT("'"&E$6&"'!"&E$4&ROW()-33)))),"-",INDIRECT("'"&E$6&"'!"&E$4&ROW()-33))} -> - | F79: {=IF(OR(TRIM(INDIRECT("'"&F$6&"'!"&F$4&ROW()-33))="0",INDIRECT("'"&F$6&"'!"&F$4&ROW()-33)="",NOT(ISNUMBER(INDIRECT("'"&F$6&"'!"&F$4&ROW()-33)))),"-",INDIRECT("'"&F$6&"'!"&F$4&ROW()-33))} -> - | G79: {=IF(OR(TRIM(INDIRECT("'"&G$6&"'!"&G$4&ROW()-33))="0",INDIRECT("'"&G$6&"'!"&G$4&ROW()-33)="",NOT(ISNUMBER(INDIRECT("'"&G$6&"'!"&G$4&ROW()-33)))),"-",INDIRECT("'"&G$6&"'!"&G$4&ROW()-33))} -> - | H79: {=IF(OR(TRIM(INDIRECT("'"&H$6&"'!"&H$4&ROW()-33))="0",INDIRECT("'"&H$6&"'!"&H$4&ROW()-33)="",NOT(ISNUMBER(INDIRECT("'"&H$6&"'!"&H$4&ROW()-33)))),"-",INDIRECT("'"&H$6&"'!"&H$4&ROW()-33))} -> - | I79: {=IF(OR(TRIM(INDIRECT("'"&I$6&"'!"&I$4&ROW()-33))="0",INDIRECT("'"&I$6&"'!"&I$4&ROW()-33)="",NOT(ISNUMBER(INDIRECT("'"&I$6&"'!"&I$4&ROW()-33)))),"-",INDIRECT("'"&I$6&"'!"&I$4&ROW()-33))} -> - | ... M79: {=IF(OR(TRIM(INDIRECT("'"&M$6&"'!"&M$4&ROW()-33))="0",INDIRECT("'"&M$6&"'!"&M$4&ROW()-33)="",NOT(ISNUMBER(INDIRECT("'"&M$6&"'!"&M$4&ROW()-33)))),"-",INDIRECT("'"&M$6&"'!"&M$4&ROW()-33))} -> - | N79: =SUM(B79:M79) -> 0 | O79: =N79/COLUMNS(B79:M79) -> 0
A80: ='Section-Category'!A34 -> Total HOME EXPENSES | B80: =SUM(B67:B79) -> 0 | C80: =SUM(C67:C79) -> 0 | D80: =SUM(D67:D79) -> 0 | E80: =SUM(E67:E79) -> 0 | F80: =SUM(F67:F79) -> 0 | G80: =SUM(G67:G79) -> 0 | H80: =SUM(H67:H79) -> 0 | I80: =SUM(I67:I79) -> 0 | ... O80: =SUM(O67:O79) -> 0
A81: ='Section-Category'!A35 -> % of Total Expenses | B81: =IF(B$17=0," - ",B80/B$17) -> - | C81: =IF(C$17=0," - ",C80/C$17) -> - | D81: =IF(D$17=0," - ",D80/D$17) -> - | E81: =IF(E$17=0," - ",E80/E$17) -> - | F81: =IF(F$17=0," - ",F80/F$17) -> - | G81: =IF(G$17=0," - ",G80/G$17) -> - | H81: =IF(H$17=0," - ",H80/H$17) -> - | I81: =IF(I$17=0," - ",I80/I$17) -> - | ... O81: =IF(O$17=0," - ",O80/O$17) -> -
A83: ='Section-Category'!A37 -> DAILY LIVING | B83: =B$6 -> Jan | C83: =C$6 -> Feb | D83: =D$6 -> Mar | E83: =E$6 -> Apr | F83: =F$6 -> May | G83: =G$6 -> Jun | H83: =H$6 -> Jul | I83: =I$6 -> Aug | ... M83: =M$6 -> Dec | N83: Total | O83: Avg
A84: ='Section-Category'!A38 -> Groceries | B84: {=IF(OR(TRIM(INDIRECT("'"&B$6&"'!"&B$4&ROW()-34))="0",INDIRECT("'"&B$6&"'!"&B$4&ROW()-34)="",NOT(ISNUMBER(INDIRECT("'"&B$6&"'!"&B$4&ROW()-34)))),"-",INDIRECT("'"&B$6&"'!"&B$4&ROW()-34))} -> - | C84: {=IF(OR(TRIM(INDIRECT("'"&C$6&"'!"&C$4&ROW()-34))="0",INDIRECT("'"&C$6&"'!"&C$4&ROW()-34)="",NOT(ISNUMBER(INDIRECT("'"&C$6&"'!"&C$4&ROW()-34)))),"-",INDIRECT("'"&C$6&"'!"&C$4&ROW()-34))} -> - | D84: {=IF(OR(TRIM(INDIRECT("'"&D$6&"'!"&D$4&ROW()-34))="0",INDIRECT("'"&D$6&"'!"&D$4&ROW()-34)="",NOT(ISNUMBER(INDIRECT("'"&D$6&"'!"&D$4&ROW()-34)))),"-",INDIRECT("'"&D$6&"'!"&D$4&ROW()-34))} -> - | E84: {=IF(OR(TRIM(INDIRECT("'"&E$6&"'!"&E$4&ROW()-34))="0",INDIRECT("'"&E$6&"'!"&E$4&ROW()-34)="",NOT(ISNUMBER(INDIRECT("'"&E$6&"'!"&E$4&ROW()-34)))),"-",INDIRECT("'"&E$6&"'!"&E$4&ROW()-34))} -> - | F84: {=IF(OR(TRIM(INDIRECT("'"&F$6&"'!"&F$4&ROW()-34))="0",INDIRECT("'"&F$6&"'!"&F$4&ROW()-34)="",NOT(ISNUMBER(INDIRECT("'"&F$6&"'!"&F$4&ROW()-34)))),"-",INDIRECT("'"&F$6&"'!"&F$4&ROW()-34))} -> - | G84: {=IF(OR(TRIM(INDIRECT("'"&G$6&"'!"&G$4&ROW()-34))="0",INDIRECT("'"&G$6&"'!"&G$4&ROW()-34)="",NOT(ISNUMBER(INDIRECT("'"&G$6&"'!"&G$4&ROW()-34)))),"-",INDIRECT("'"&G$6&"'!"&G$4&ROW()-34))} -> - | H84: {=IF(OR(TRIM(INDIRECT("'"&H$6&"'!"&H$4&ROW()-34))="0",INDIRECT("'"&H$6&"'!"&H$4&ROW()-34)="",NOT(ISNUMBER(INDIRECT("'"&H$6&"'!"&H$4&ROW()-34)))),"-",INDIRECT("'"&H$6&"'!"&H$4&ROW()-34))} -> - | I84: {=IF(OR(TRIM(INDIRECT("'"&I$6&"'!"&I$4&ROW()-34))="0",INDIRECT("'"&I$6&"'!"&I$4&ROW()-34)="",NOT(ISNUMBER(INDIRECT("'"&I$6&"'!"&I$4&ROW()-34)))),"-",INDIRECT("'"&I$6&"'!"&I$4&ROW()-34))} -> - | ... M84: {=IF(OR(TRIM(INDIRECT("'"&M$6&"'!"&M$4&ROW()-34))="0",INDIRECT("'"&M$6&"'!"&M$4&ROW()-34)="",NOT(ISNUMBER(INDIRECT("'"&M$6&"'!"&M$4&ROW()-34)))),"-",INDIRECT("'"&M$6&"'!"&M$4&ROW()-34))} -> - | N84: =SUM(B84:M84) -> 0 | O84: =N84/COLUMNS(B84:M84) -> 0
A85: ='Section-Category'!A39 -> Personal Supplies | B85: {=IF(OR(TRIM(INDIRECT("'"&B$6&"'!"&B$4&ROW()-34))="0",INDIRECT("'"&B$6&"'!"&B$4&ROW()-34)="",NOT(ISNUMBER(INDIRECT("'"&B$6&"'!"&B$4&ROW()-34)))),"-",INDIRECT("'"&B$6&"'!"&B$4&ROW()-34))} -> - | C85: {=IF(OR(TRIM(INDIRECT("'"&C$6&"'!"&C$4&ROW()-34))="0",INDIRECT("'"&C$6&"'!"&C$4&ROW()-34)="",NOT(ISNUMBER(INDIRECT("'"&C$6&"'!"&C$4&ROW()-34)))),"-",INDIRECT("'"&C$6&"'!"&C$4&ROW()-34))} -> - | D85: {=IF(OR(TRIM(INDIRECT("'"&D$6&"'!"&D$4&ROW()-34))="0",INDIRECT("'"&D$6&"'!"&D$4&ROW()-34)="",NOT(ISNUMBER(INDIRECT("'"&D$6&"'!"&D$4&ROW()-34)))),"-",INDIRECT("'"&D$6&"'!"&D$4&ROW()-34))} -> - | E85: {=IF(OR(TRIM(INDIRECT("'"&E$6&"'!"&E$4&ROW()-34))="0",INDIRECT("'"&E$6&"'!"&E$4&ROW()-34)="",NOT(ISNUMBER(INDIRECT("'"&E$6&"'!"&E$4&ROW()-34)))),"-",INDIRECT("'"&E$6&"'!"&E$4&ROW()-34))} -> - | F85: {=IF(OR(TRIM(INDIRECT("'"&F$6&"'!"&F$4&ROW()-34))="0",INDIRECT("'"&F$6&"'!"&F$4&ROW()-34)="",NOT(ISNUMBER(INDIRECT("'"&F$6&"'!"&F$4&ROW()-34)))),"-",INDIRECT("'"&F$6&"'!"&F$4&ROW()-34))} -> - | G85: {=IF(OR(TRIM(INDIRECT("'"&G$6&"'!"&G$4&ROW()-34))="0",INDIRECT("'"&G$6&"'!"&G$4&ROW()-34)="",NOT(ISNUMBER(INDIRECT("'"&G$6&"'!"&G$4&ROW()-34)))),"-",INDIRECT("'"&G$6&"'!"&G$4&ROW()-34))} -> - | H85: {=IF(OR(TRIM(INDIRECT("'"&H$6&"'!"&H$4&ROW()-34))="0",INDIRECT("'"&H$6&"'!"&H$4&ROW()-34)="",NOT(ISNUMBER(INDIRECT("'"&H$6&"'!"&H$4&ROW()-34)))),"-",INDIRECT("'"&H$6&"'!"&H$4&ROW()-34))} -> - | I85: {=IF(OR(TRIM(INDIRECT("'"&I$6&"'!"&I$4&ROW()-34))="0",INDIRECT("'"&I$6&"'!"&I$4&ROW()-34)="",NOT(ISNUMBER(INDIRECT("'"&I$6&"'!"&I$4&ROW()-34)))),"-",INDIRECT("'"&I$6&"'!"&I$4&ROW()-34))} -> - | ... M85: {=IF(OR(TRIM(INDIRECT("'"&M$6&"'!"&M$4&ROW()-34))="0",INDIRECT("'"&M$6&"'!"&M$4&ROW()-34)="",NOT(ISNUMBER(INDIRECT("'"&M$6&"'!"&M$4&ROW()-34)))),"-",INDIRECT("'"&M$6&"'!"&M$4&ROW()-34))} -> - | N85: =SUM(B85:M85) -> 0 | O85: =N85/COLUMNS(B85:M85) -> 0
A86: ='Section-Category'!A40 -> Clothing | B86: {=IF(OR(TRIM(INDIRECT("'"&B$6&"'!"&B$4&ROW()-34))="0",INDIRECT("'"&B$6&"'!"&B$4&ROW()-34)="",NOT(ISNUMBER(INDIRECT("'"&B$6&"'!"&B$4&ROW()-34)))),"-",INDIRECT("'"&B$6&"'!"&B$4&ROW()-34))} -> - | C86: {=IF(OR(TRIM(INDIRECT("'"&C$6&"'!"&C$4&ROW()-34))="0",INDIRECT("'"&C$6&"'!"&C$4&ROW()-34)="",NOT(ISNUMBER(INDIRECT("'"&C$6&"'!"&C$4&ROW()-34)))),"-",INDIRECT("'"&C$6&"'!"&C$4&ROW()-34))} -> - | D86: {=IF(OR(TRIM(INDIRECT("'"&D$6&"'!"&D$4&ROW()-34))="0",INDIRECT("'"&D$6&"'!"&D$4&ROW()-34)="",NOT(ISNUMBER(INDIRECT("'"&D$6&"'!"&D$4&ROW()-34)))),"-",INDIRECT("'"&D$6&"'!"&D$4&ROW()-34))} -> - | E86: {=IF(OR(TRIM(INDIRECT("'"&E$6&"'!"&E$4&ROW()-34))="0",INDIRECT("'"&E$6&"'!"&E$4&ROW()-34)="",NOT(ISNUMBER(INDIRECT("'"&E$6&"'!"&E$4&ROW()-34)))),"-",INDIRECT("'"&E$6&"'!"&E$4&ROW()-34))} -> - | F86: {=IF(OR(TRIM(INDIRECT("'"&F$6&"'!"&F$4&ROW()-34))="0",INDIRECT("'"&F$6&"'!"&F$4&ROW()-34)="",NOT(ISNUMBER(INDIRECT("'"&F$6&"'!"&F$4&ROW()-34)))),"-",INDIRECT("'"&F$6&"'!"&F$4&ROW()-34))} -> - | G86: {=IF(OR(TRIM(INDIRECT("'"&G$6&"'!"&G$4&ROW()-34))="0",INDIRECT("'"&G$6&"'!"&G$4&ROW()-34)="",NOT(ISNUMBER(INDIRECT("'"&G$6&"'!"&G$4&ROW()-34)))),"-",INDIRECT("'"&G$6&"'!"&G$4&ROW()-34))} -> - | H86: {=IF(OR(TRIM(INDIRECT("'"&H$6&"'!"&H$4&ROW()-34))="0",INDIRECT("'"&H$6&"'!"&H$4&ROW()-34)="",NOT(ISNUMBER(INDIRECT("'"&H$6&"'!"&H$4&ROW()-34)))),"-",INDIRECT("'"&H$6&"'!"&H$4&ROW()-34))} -> - | I86: {=IF(OR(TRIM(INDIRECT("'"&I$6&"'!"&I$4&ROW()-34))="0",INDIRECT("'"&I$6&"'!"&I$4&ROW()-34)="",NOT(ISNUMBER(INDIRECT("'"&I$6&"'!"&I$4&ROW()-34)))),"-",INDIRECT("'"&I$6&"'!"&I$4&ROW()-34))} -> - | ... M86: {=IF(OR(TRIM(INDIRECT("'"&M$6&"'!"&M$4&ROW()-34))="0",INDIRECT("'"&M$6&"'!"&M$4&ROW()-34)="",NOT(ISNUMBER(INDIRECT("'"&M$6&"'!"&M$4&ROW()-34)))),"-",INDIRECT("'"&M$6&"'!"&M$4&ROW()-34))} -> - | N86: =SUM(B86:M86) -> 0 | O86: =N86/COLUMNS(B86:M86) -> 0
A87: ='Section-Category'!A41 -> Cleaning Services | B87: {=IF(OR(TRIM(INDIRECT("'"&B$6&"'!"&B$4&ROW()-34))="0",INDIRECT("'"&B$6&"'!"&B$4&ROW()-34)="",NOT(ISNUMBER(INDIRECT("'"&B$6&"'!"&B$4&ROW()-34)))),"-",INDIRECT("'"&B$6&"'!"&B$4&ROW()-34))} -> - | C87: {=IF(OR(TRIM(INDIRECT("'"&C$6&"'!"&C$4&ROW()-34))="0",INDIRECT("'"&C$6&"'!"&C$4&ROW()-34)="",NOT(ISNUMBER(INDIRECT("'"&C$6&"'!"&C$4&ROW()-34)))),"-",INDIRECT("'"&C$6&"'!"&C$4&ROW()-34))} -> - | D87: {=IF(OR(TRIM(INDIRECT("'"&D$6&"'!"&D$4&ROW()-34))="0",INDIRECT("'"&D$6&"'!"&D$4&ROW()-34)="",NOT(ISNUMBER(INDIRECT("'"&D$6&"'!"&D$4&ROW()-34)))),"-",INDIRECT("'"&D$6&"'!"&D$4&ROW()-34))} -> - | E87: {=IF(OR(TRIM(INDIRECT("'"&E$6&"'!"&E$4&ROW()-34))="0",INDIRECT("'"&E$6&"'!"&E$4&ROW()-34)="",NOT(ISNUMBER(INDIRECT("'"&E$6&"'!"&E$4&ROW()-34)))),"-",INDIRECT("'"&E$6&"'!"&E$4&ROW()-34))} -> - | F87: {=IF(OR(TRIM(INDIRECT("'"&F$6&"'!"&F$4&ROW()-34))="0",INDIRECT("'"&F$6&"'!"&F$4&ROW()-34)="",NOT(ISNUMBER(INDIRECT("'"&F$6&"'!"&F$4&ROW()-34)))),"-",INDIRECT("'"&F$6&"'!"&F$4&ROW()-34))} -> - | G87: {=IF(OR(TRIM(INDIRECT("'"&G$6&"'!"&G$4&ROW()-34))="0",INDIRECT("'"&G$6&"'!"&G$4&ROW()-34)="",NOT(ISNUMBER(INDIRECT("'"&G$6&"'!"&G$4&ROW()-34)))),"-",INDIRECT("'"&G$6&"'!"&G$4&ROW()-34))} -> - | H87: {=IF(OR(TRIM(INDIRECT("'"&H$6&"'!"&H$4&ROW()-34))="0",INDIRECT("'"&H$6&"'!"&H$4&ROW()-34)="",NOT(ISNUMBER(INDIRECT("'"&H$6&"'!"&H$4&ROW()-34)))),"-",INDIRECT("'"&H$6&"'!"&H$4&ROW()-34))} -> - | I87: {=IF(OR(TRIM(INDIRECT("'"&I$6&"'!"&I$4&ROW()-34))="0",INDIRECT("'"&I$6&"'!"&I$4&ROW()-34)="",NOT(ISNUMBER(INDIRECT("'"&I$6&"'!"&I$4&ROW()-34)))),"-",INDIRECT("'"&I$6&"'!"&I$4&ROW()-34))} -> - | ... M87: {=IF(OR(TRIM(INDIRECT("'"&M$6&"'!"&M$4&ROW()-34))="0",INDIRECT("'"&M$6&"'!"&M$4&ROW()-34)="",NOT(ISNUMBER(INDIRECT("'"&M$6&"'!"&M$4&ROW()-34)))),"-",INDIRECT("'"&M$6&"'!"&M$4&ROW()-34))} -> - | N87: =SUM(B87:M87) -> 0 | O87: =N87/COLUMNS(B87:M87) -> 0
A88: ='Section-Category'!A42 -> Dining/Eating Out | B88: {=IF(OR(TRIM(INDIRECT("'"&B$6&"'!"&B$4&ROW()-34))="0",INDIRECT("'"&B$6&"'!"&B$4&ROW()-34)="",NOT(ISNUMBER(INDIRECT("'"&B$6&"'!"&B$4&ROW()-34)))),"-",INDIRECT("'"&B$6&"'!"&B$4&ROW()-34))} -> - | C88: {=IF(OR(TRIM(INDIRECT("'"&C$6&"'!"&C$4&ROW()-34))="0",INDIRECT("'"&C$6&"'!"&C$4&ROW()-34)="",NOT(ISNUMBER(INDIRECT("'"&C$6&"'!"&C$4&ROW()-34)))),"-",INDIRECT("'"&C$6&"'!"&C$4&ROW()-34))} -> - | D88: {=IF(OR(TRIM(INDIRECT("'"&D$6&"'!"&D$4&ROW()-34))="0",INDIRECT("'"&D$6&"'!"&D$4&ROW()-34)="",NOT(ISNUMBER(INDIRECT("'"&D$6&"'!"&D$4&ROW()-34)))),"-",INDIRECT("'"&D$6&"'!"&D$4&ROW()-34))} -> - | E88: {=IF(OR(TRIM(INDIRECT("'"&E$6&"'!"&E$4&ROW()-34))="0",INDIRECT("'"&E$6&"'!"&E$4&ROW()-34)="",NOT(ISNUMBER(INDIRECT("'"&E$6&"'!"&E$4&ROW()-34)))),"-",INDIRECT("'"&E$6&"'!"&E$4&ROW()-34))} -> - | F88: {=IF(OR(TRIM(INDIRECT("'"&F$6&"'!"&F$4&ROW()-34))="0",INDIRECT("'"&F$6&"'!"&F$4&ROW()-34)="",NOT(ISNUMBER(INDIRECT("'"&F$6&"'!"&F$4&ROW()-34)))),"-",INDIRECT("'"&F$6&"'!"&F$4&ROW()-34))} -> - | G88: {=IF(OR(TRIM(INDIRECT("'"&G$6&"'!"&G$4&ROW()-34))="0",INDIRECT("'"&G$6&"'!"&G$4&ROW()-34)="",NOT(ISNUMBER(INDIRECT("'"&G$6&"'!"&G$4&ROW()-34)))),"-",INDIRECT("'"&G$6&"'!"&G$4&ROW()-34))} -> - | H88: {=IF(OR(TRIM(INDIRECT("'"&H$6&"'!"&H$4&ROW()-34))="0",INDIRECT("'"&H$6&"'!"&H$4&ROW()-34)="",NOT(ISNUMBER(INDIRECT("'"&H$6&"'!"&H$4&ROW()-34)))),"-",INDIRECT("'"&H$6&"'!"&H$4&ROW()-34))} -> - | I88: {=IF(OR(TRIM(INDIRECT("'"&I$6&"'!"&I$4&ROW()-34))="0",INDIRECT("'"&I$6&"'!"&I$4&ROW()-34)="",NOT(ISNUMBER(INDIRECT("'"&I$6&"'!"&I$4&ROW()-34)))),"-",INDIRECT("'"&I$6&"'!"&I$4&ROW()-34))} -> - | ... M88: {=IF(OR(TRIM(INDIRECT("'"&M$6&"'!"&M$4&ROW()-34))="0",INDIRECT("'"&M$6&"'!"&M$4&ROW()-34)="",NOT(ISNUMBER(INDIRECT("'"&M$6&"'!"&M$4&ROW()-34)))),"-",INDIRECT("'"&M$6&"'!"&M$4&ROW()-34))} -> - | N88: =SUM(B88:M88) -> 0 | O88: =N88/COLUMNS(B88:M88) -> 0
A89: ='Section-Category'!A43 -> Dry Cleaning | B89: {=IF(OR(TRIM(INDIRECT("'"&B$6&"'!"&B$4&ROW()-34))="0",INDIRECT("'"&B$6&"'!"&B$4&ROW()-34)="",NOT(ISNUMBER(INDIRECT("'"&B$6&"'!"&B$4&ROW()-34)))),"-",INDIRECT("'"&B$6&"'!"&B$4&ROW()-34))} -> - | C89: {=IF(OR(TRIM(INDIRECT("'"&C$6&"'!"&C$4&ROW()-34))="0",INDIRECT("'"&C$6&"'!"&C$4&ROW()-34)="",NOT(ISNUMBER(INDIRECT("'"&C$6&"'!"&C$4&ROW()-34)))),"-",INDIRECT("'"&C$6&"'!"&C$4&ROW()-34))} -> - | D89: {=IF(OR(TRIM(INDIRECT("'"&D$6&"'!"&D$4&ROW()-34))="0",INDIRECT("'"&D$6&"'!"&D$4&ROW()-34)="",NOT(ISNUMBER(INDIRECT("'"&D$6&"'!"&D$4&ROW()-34)))),"-",INDIRECT("'"&D$6&"'!"&D$4&ROW()-34))} -> - | E89: {=IF(OR(TRIM(INDIRECT("'"&E$6&"'!"&E$4&ROW()-34))="0",INDIRECT("'"&E$6&"'!"&E$4&ROW()-34)="",NOT(ISNUMBER(INDIRECT("'"&E$6&"'!"&E$4&ROW()-34)))),"-",INDIRECT("'"&E$6&"'!"&E$4&ROW()-34))} -> - | F89: {=IF(OR(TRIM(INDIRECT("'"&F$6&"'!"&F$4&ROW()-34))="0",INDIRECT("'"&F$6&"'!"&F$4&ROW()-34)="",NOT(ISNUMBER(INDIRECT("'"&F$6&"'!"&F$4&ROW()-34)))),"-",INDIRECT("'"&F$6&"'!"&F$4&ROW()-34))} -> - | G89: {=IF(OR(TRIM(INDIRECT("'"&G$6&"'!"&G$4&ROW()-34))="0",INDIRECT("'"&G$6&"'!"&G$4&ROW()-34)="",NOT(ISNUMBER(INDIRECT("'"&G$6&"'!"&G$4&ROW()-34)))),"-",INDIRECT("'"&G$6&"'!"&G$4&ROW()-34))} -> - | H89: {=IF(OR(TRIM(INDIRECT("'"&H$6&"'!"&H$4&ROW()-34))="0",INDIRECT("'"&H$6&"'!"&H$4&ROW()-34)="",NOT(ISNUMBER(INDIRECT("'"&H$6&"'!"&H$4&ROW()-34)))),"-",INDIRECT("'"&H$6&"'!"&H$4&ROW()-34))} -> - | I89: {=IF(OR(TRIM(INDIRECT("'"&I$6&"'!"&I$4&ROW()-34))="0",INDIRECT("'"&I$6&"'!"&I$4&ROW()-34)="",NOT(ISNUMBER(INDIRECT("'"&I$6&"'!"&I$4&ROW()-34)))),"-",INDIRECT("'"&I$6&"'!"&I$4&ROW()-34))} -> - | ... M89: {=IF(OR(TRIM(INDIRECT("'"&M$6&"'!"&M$4&ROW()-34))="0",INDIRECT("'"&M$6&"'!"&M$4&ROW()-34)="",NOT(ISNUMBER(INDIRECT("'"&M$6&"'!"&M$4&ROW()-34)))),"-",INDIRECT("'"&M$6&"'!"&M$4&ROW()-34))} -> - | N89: =SUM(B89:M89) -> 0 | O89: =N89/COLUMNS(B89:M89) -> 0
A90: ='Section-Category'!A44 -> Salon/Barber | B90: {=IF(OR(TRIM(INDIRECT("'"&B$6&"'!"&B$4&ROW()-34))="0",INDIRECT("'"&B$6&"'!"&B$4&ROW()-34)="",NOT(ISNUMBER(INDIRECT("'"&B$6&"'!"&B$4&ROW()-34)))),"-",INDIRECT("'"&B$6&"'!"&B$4&ROW()-34))} -> - | C90: {=IF(OR(TRIM(INDIRECT("'"&C$6&"'!"&C$4&ROW()-34))="0",INDIRECT("'"&C$6&"'!"&C$4&ROW()-34)="",NOT(ISNUMBER(INDIRECT("'"&C$6&"'!"&C$4&ROW()-34)))),"-",INDIRECT("'"&C$6&"'!"&C$4&ROW()-34))} -> - | D90: {=IF(OR(TRIM(INDIRECT("'"&D$6&"'!"&D$4&ROW()-34))="0",INDIRECT("'"&D$6&"'!"&D$4&ROW()-34)="",NOT(ISNUMBER(INDIRECT("'"&D$6&"'!"&D$4&ROW()-34)))),"-",INDIRECT("'"&D$6&"'!"&D$4&ROW()-34))} -> - | E90: {=IF(OR(TRIM(INDIRECT("'"&E$6&"'!"&E$4&ROW()-34))="0",INDIRECT("'"&E$6&"'!"&E$4&ROW()-34)="",NOT(ISNUMBER(INDIRECT("'"&E$6&"'!"&E$4&ROW()-34)))),"-",INDIRECT("'"&E$6&"'!"&E$4&ROW()-34))} -> - | F90: {=IF(OR(TRIM(INDIRECT("'"&F$6&"'!"&F$4&ROW()-34))="0",INDIRECT("'"&F$6&"'!"&F$4&ROW()-34)="",NOT(ISNUMBER(INDIRECT("'"&F$6&"'!"&F$4&ROW()-34)))),"-",INDIRECT("'"&F$6&"'!"&F$4&ROW()-34))} -> - | G90: {=IF(OR(TRIM(INDIRECT("'"&G$6&"'!"&G$4&ROW()-34))="0",INDIRECT("'"&G$6&"'!"&G$4&ROW()-34)="",NOT(ISNUMBER(INDIRECT("'"&G$6&"'!"&G$4&ROW()-34)))),"-",INDIRECT("'"&G$6&"'!"&G$4&ROW()-34))} -> - | H90: {=IF(OR(TRIM(INDIRECT("'"&H$6&"'!"&H$4&ROW()-34))="0",INDIRECT("'"&H$6&"'!"&H$4&ROW()-34)="",NOT(ISNUMBER(INDIRECT("'"&H$6&"'!"&H$4&ROW()-34)))),"-",INDIRECT("'"&H$6&"'!"&H$4&ROW()-34))} -> - | I90: {=IF(OR(TRIM(INDIRECT("'"&I$6&"'!"&I$4&ROW()-34))="0",INDIRECT("'"&I$6&"'!"&I$4&ROW()-34)="",NOT(ISNUMBER(INDIRECT("'"&I$6&"'!"&I$4&ROW()-34)))),"-",INDIRECT("'"&I$6&"'!"&I$4&ROW()-34))} -> - | ... M90: {=IF(OR(TRIM(INDIRECT("'"&M$6&"'!"&M$4&ROW()-34))="0",INDIRECT("'"&M$6&"'!"&M$4&ROW()-34)="",NOT(ISNUMBER(INDIRECT("'"&M$6&"'!"&M$4&ROW()-34)))),"-",INDIRECT("'"&M$6&"'!"&M$4&ROW()-34))} -> - | N90: =SUM(B90:M90) -> 0 | O90: =N90/COLUMNS(B90:M90) -> 0
A91: ='Section-Category'!A45 -> FoodPanda | B91: {=IF(OR(TRIM(INDIRECT("'"&B$6&"'!"&B$4&ROW()-34))="0",INDIRECT("'"&B$6&"'!"&B$4&ROW()-34)="",NOT(ISNUMBER(INDIRECT("'"&B$6&"'!"&B$4&ROW()-34)))),"-",INDIRECT("'"&B$6&"'!"&B$4&ROW()-34))} -> - | C91: {=IF(OR(TRIM(INDIRECT("'"&C$6&"'!"&C$4&ROW()-34))="0",INDIRECT("'"&C$6&"'!"&C$4&ROW()-34)="",NOT(ISNUMBER(INDIRECT("'"&C$6&"'!"&C$4&ROW()-34)))),"-",INDIRECT("'"&C$6&"'!"&C$4&ROW()-34))} -> - | D91: {=IF(OR(TRIM(INDIRECT("'"&D$6&"'!"&D$4&ROW()-34))="0",INDIRECT("'"&D$6&"'!"&D$4&ROW()-34)="",NOT(ISNUMBER(INDIRECT("'"&D$6&"'!"&D$4&ROW()-34)))),"-",INDIRECT("'"&D$6&"'!"&D$4&ROW()-34))} -> - | E91: {=IF(OR(TRIM(INDIRECT("'"&E$6&"'!"&E$4&ROW()-34))="0",INDIRECT("'"&E$6&"'!"&E$4&ROW()-34)="",NOT(ISNUMBER(INDIRECT("'"&E$6&"'!"&E$4&ROW()-34)))),"-",INDIRECT("'"&E$6&"'!"&E$4&ROW()-34))} -> - | F91: {=IF(OR(TRIM(INDIRECT("'"&F$6&"'!"&F$4&ROW()-34))="0",INDIRECT("'"&F$6&"'!"&F$4&ROW()-34)="",NOT(ISNUMBER(INDIRECT("'"&F$6&"'!"&F$4&ROW()-34)))),"-",INDIRECT("'"&F$6&"'!"&F$4&ROW()-34))} -> - | G91: {=IF(OR(TRIM(INDIRECT("'"&G$6&"'!"&G$4&ROW()-34))="0",INDIRECT("'"&G$6&"'!"&G$4&ROW()-34)="",NOT(ISNUMBER(INDIRECT("'"&G$6&"'!"&G$4&ROW()-34)))),"-",INDIRECT("'"&G$6&"'!"&G$4&ROW()-34))} -> - | H91: {=IF(OR(TRIM(INDIRECT("'"&H$6&"'!"&H$4&ROW()-34))="0",INDIRECT("'"&H$6&"'!"&H$4&ROW()-34)="",NOT(ISNUMBER(INDIRECT("'"&H$6&"'!"&H$4&ROW()-34)))),"-",INDIRECT("'"&H$6&"'!"&H$4&ROW()-34))} -> - | I91: {=IF(OR(TRIM(INDIRECT("'"&I$6&"'!"&I$4&ROW()-34))="0",INDIRECT("'"&I$6&"'!"&I$4&ROW()-34)="",NOT(ISNUMBER(INDIRECT("'"&I$6&"'!"&I$4&ROW()-34)))),"-",INDIRECT("'"&I$6&"'!"&I$4&ROW()-34))} -> - | ... M91: {=IF(OR(TRIM(INDIRECT("'"&M$6&"'!"&M$4&ROW()-34))="0",INDIRECT("'"&M$6&"'!"&M$4&ROW()-34)="",NOT(ISNUMBER(INDIRECT("'"&M$6&"'!"&M$4&ROW()-34)))),"-",INDIRECT("'"&M$6&"'!"&M$4&ROW()-34))} -> - | N91: =SUM(B91:M91) -> 0 | O91: =N91/COLUMNS(B91:M91) -> 0
A92: ='Section-Category'!A46 -> JazzCash/EasyPaisa | B92: {=IF(OR(TRIM(INDIRECT("'"&B$6&"'!"&B$4&ROW()-34))="0",INDIRECT("'"&B$6&"'!"&B$4&ROW()-34)="",NOT(ISNUMBER(INDIRECT("'"&B$6&"'!"&B$4&ROW()-34)))),"-",INDIRECT("'"&B$6&"'!"&B$4&ROW()-34))} -> - | C92: {=IF(OR(TRIM(INDIRECT("'"&C$6&"'!"&C$4&ROW()-34))="0",INDIRECT("'"&C$6&"'!"&C$4&ROW()-34)="",NOT(ISNUMBER(INDIRECT("'"&C$6&"'!"&C$4&ROW()-34)))),"-",INDIRECT("'"&C$6&"'!"&C$4&ROW()-34))} -> - | D92: {=IF(OR(TRIM(INDIRECT("'"&D$6&"'!"&D$4&ROW()-34))="0",INDIRECT("'"&D$6&"'!"&D$4&ROW()-34)="",NOT(ISNUMBER(INDIRECT("'"&D$6&"'!"&D$4&ROW()-34)))),"-",INDIRECT("'"&D$6&"'!"&D$4&ROW()-34))} -> - | E92: {=IF(OR(TRIM(INDIRECT("'"&E$6&"'!"&E$4&ROW()-34))="0",INDIRECT("'"&E$6&"'!"&E$4&ROW()-34)="",NOT(ISNUMBER(INDIRECT("'"&E$6&"'!"&E$4&ROW()-34)))),"-",INDIRECT("'"&E$6&"'!"&E$4&ROW()-34))} -> - | F92: {=IF(OR(TRIM(INDIRECT("'"&F$6&"'!"&F$4&ROW()-34))="0",INDIRECT("'"&F$6&"'!"&F$4&ROW()-34)="",NOT(ISNUMBER(INDIRECT("'"&F$6&"'!"&F$4&ROW()-34)))),"-",INDIRECT("'"&F$6&"'!"&F$4&ROW()-34))} -> - | G92: {=IF(OR(TRIM(INDIRECT("'"&G$6&"'!"&G$4&ROW()-34))="0",INDIRECT("'"&G$6&"'!"&G$4&ROW()-34)="",NOT(ISNUMBER(INDIRECT("'"&G$6&"'!"&G$4&ROW()-34)))),"-",INDIRECT("'"&G$6&"'!"&G$4&ROW()-34))} -> - | H92: {=IF(OR(TRIM(INDIRECT("'"&H$6&"'!"&H$4&ROW()-34))="0",INDIRECT("'"&H$6&"'!"&H$4&ROW()-34)="",NOT(ISNUMBER(INDIRECT("'"&H$6&"'!"&H$4&ROW()-34)))),"-",INDIRECT("'"&H$6&"'!"&H$4&ROW()-34))} -> - | I92: {=IF(OR(TRIM(INDIRECT("'"&I$6&"'!"&I$4&ROW()-34))="0",INDIRECT("'"&I$6&"'!"&I$4&ROW()-34)="",NOT(ISNUMBER(INDIRECT("'"&I$6&"'!"&I$4&ROW()-34)))),"-",INDIRECT("'"&I$6&"'!"&I$4&ROW()-34))} -> - | ... M92: {=IF(OR(TRIM(INDIRECT("'"&M$6&"'!"&M$4&ROW()-34))="0",INDIRECT("'"&M$6&"'!"&M$4&ROW()-34)="",NOT(ISNUMBER(INDIRECT("'"&M$6&"'!"&M$4&ROW()-34)))),"-",INDIRECT("'"&M$6&"'!"&M$4&ROW()-34))} -> - | N92: =SUM(B92:M92) -> 0 | O92: =N92/COLUMNS(B92:M92) -> 0
A93: ='Section-Category'!A47 -> Other | B93: {=IF(OR(TRIM(INDIRECT("'"&B$6&"'!"&B$4&ROW()-34))="0",INDIRECT("'"&B$6&"'!"&B$4&ROW()-34)="",NOT(ISNUMBER(INDIRECT("'"&B$6&"'!"&B$4&ROW()-34)))),"-",INDIRECT("'"&B$6&"'!"&B$4&ROW()-34))} -> - | C93: {=IF(OR(TRIM(INDIRECT("'"&C$6&"'!"&C$4&ROW()-34))="0",INDIRECT("'"&C$6&"'!"&C$4&ROW()-34)="",NOT(ISNUMBER(INDIRECT("'"&C$6&"'!"&C$4&ROW()-34)))),"-",INDIRECT("'"&C$6&"'!"&C$4&ROW()-34))} -> - | D93: {=IF(OR(TRIM(INDIRECT("'"&D$6&"'!"&D$4&ROW()-34))="0",INDIRECT("'"&D$6&"'!"&D$4&ROW()-34)="",NOT(ISNUMBER(INDIRECT("'"&D$6&"'!"&D$4&ROW()-34)))),"-",INDIRECT("'"&D$6&"'!"&D$4&ROW()-34))} -> - | E93: {=IF(OR(TRIM(INDIRECT("'"&E$6&"'!"&E$4&ROW()-34))="0",INDIRECT("'"&E$6&"'!"&E$4&ROW()-34)="",NOT(ISNUMBER(INDIRECT("'"&E$6&"'!"&E$4&ROW()-34)))),"-",INDIRECT("'"&E$6&"'!"&E$4&ROW()-34))} -> - | F93: {=IF(OR(TRIM(INDIRECT("'"&F$6&"'!"&F$4&ROW()-34))="0",INDIRECT("'"&F$6&"'!"&F$4&ROW()-34)="",NOT(ISNUMBER(INDIRECT("'"&F$6&"'!"&F$4&ROW()-34)))),"-",INDIRECT("'"&F$6&"'!"&F$4&ROW()-34))} -> - | G93: {=IF(OR(TRIM(INDIRECT("'"&G$6&"'!"&G$4&ROW()-34))="0",INDIRECT("'"&G$6&"'!"&G$4&ROW()-34)="",NOT(ISNUMBER(INDIRECT("'"&G$6&"'!"&G$4&ROW()-34)))),"-",INDIRECT("'"&G$6&"'!"&G$4&ROW()-34))} -> - | H93: {=IF(OR(TRIM(INDIRECT("'"&H$6&"'!"&H$4&ROW()-34))="0",INDIRECT("'"&H$6&"'!"&H$4&ROW()-34)="",NOT(ISNUMBER(INDIRECT("'"&H$6&"'!"&H$4&ROW()-34)))),"-",INDIRECT("'"&H$6&"'!"&H$4&ROW()-34))} -> - | I93: {=IF(OR(TRIM(INDIRECT("'"&I$6&"'!"&I$4&ROW()-34))="0",INDIRECT("'"&I$6&"'!"&I$4&ROW()-34)="",NOT(ISNUMBER(INDIRECT("'"&I$6&"'!"&I$4&ROW()-34)))),"-",INDIRECT("'"&I$6&"'!"&I$4&ROW()-34))} -> - | ... M93: {=IF(OR(TRIM(INDIRECT("'"&M$6&"'!"&M$4&ROW()-34))="0",INDIRECT("'"&M$6&"'!"&M$4&ROW()-34)="",NOT(ISNUMBER(INDIRECT("'"&M$6&"'!"&M$4&ROW()-34)))),"-",INDIRECT("'"&M$6&"'!"&M$4&ROW()-34))} -> - | N93: =SUM(B93:M93) -> 0 | O93: =N93/COLUMNS(B93:M93) -> 0
A94: ='Section-Category'!A48 -> Total DAILY LIVING | B94: =SUM(B84:B93) -> 0 | C94: =SUM(C84:C93) -> 0 | D94: =SUM(D84:D93) -> 0 | E94: =SUM(E84:E93) -> 0 | F94: =SUM(F84:F93) -> 0 | G94: =SUM(G84:G93) -> 0 | H94: =SUM(H84:H93) -> 0 | I94: =SUM(I84:I93) -> 0 | ... O94: =SUM(O84:O93) -> 0
A95: ='Section-Category'!A49 -> % of Total Expenses | B95: =IF(B$17=0," - ",B94/B$17) -> - | C95: =IF(C$17=0," - ",C94/C$17) -> - | D95: =IF(D$17=0," - ",D94/D$17) -> - | E95: =IF(E$17=0," - ",E94/E$17) -> - | F95: =IF(F$17=0," - ",F94/F$17) -> - | G95: =IF(G$17=0," - ",G94/G$17) -> - | H95: =IF(H$17=0," - ",H94/H$17) -> - | I95: =IF(I$17=0," - ",I94/I$17) -> - | ... O95: =IF(O$17=0," - ",O94/O$17) -> -
A97: ='Section-Category'!A51 -> CHILDREN | B97: =B$6 -> Jan | C97: =C$6 -> Feb | D97: =D$6 -> Mar | E97: =E$6 -> Apr | F97: =F$6 -> May | G97: =G$6 -> Jun | H97: =H$6 -> Jul | I97: =I$6 -> Aug | ... M97: =M$6 -> Dec | N97: Total | O97: Avg
A98: ='Section-Category'!A52 -> Medical | B98: {=IF(OR(TRIM(INDIRECT("'"&B$6&"'!"&B$4&ROW()-35))="0",INDIRECT("'"&B$6&"'!"&B$4&ROW()-35)="",NOT(ISNUMBER(INDIRECT("'"&B$6&"'!"&B$4&ROW()-35)))),"-",INDIRECT("'"&B$6&"'!"&B$4&ROW()-35))} -> - | C98: {=IF(OR(TRIM(INDIRECT("'"&C$6&"'!"&C$4&ROW()-35))="0",INDIRECT("'"&C$6&"'!"&C$4&ROW()-35)="",NOT(ISNUMBER(INDIRECT("'"&C$6&"'!"&C$4&ROW()-35)))),"-",INDIRECT("'"&C$6&"'!"&C$4&ROW()-35))} -> - | D98: {=IF(OR(TRIM(INDIRECT("'"&D$6&"'!"&D$4&ROW()-35))="0",INDIRECT("'"&D$6&"'!"&D$4&ROW()-35)="",NOT(ISNUMBER(INDIRECT("'"&D$6&"'!"&D$4&ROW()-35)))),"-",INDIRECT("'"&D$6&"'!"&D$4&ROW()-35))} -> - | E98: {=IF(OR(TRIM(INDIRECT("'"&E$6&"'!"&E$4&ROW()-35))="0",INDIRECT("'"&E$6&"'!"&E$4&ROW()-35)="",NOT(ISNUMBER(INDIRECT("'"&E$6&"'!"&E$4&ROW()-35)))),"-",INDIRECT("'"&E$6&"'!"&E$4&ROW()-35))} -> - | F98: {=IF(OR(TRIM(INDIRECT("'"&F$6&"'!"&F$4&ROW()-35))="0",INDIRECT("'"&F$6&"'!"&F$4&ROW()-35)="",NOT(ISNUMBER(INDIRECT("'"&F$6&"'!"&F$4&ROW()-35)))),"-",INDIRECT("'"&F$6&"'!"&F$4&ROW()-35))} -> - | G98: {=IF(OR(TRIM(INDIRECT("'"&G$6&"'!"&G$4&ROW()-35))="0",INDIRECT("'"&G$6&"'!"&G$4&ROW()-35)="",NOT(ISNUMBER(INDIRECT("'"&G$6&"'!"&G$4&ROW()-35)))),"-",INDIRECT("'"&G$6&"'!"&G$4&ROW()-35))} -> - | H98: {=IF(OR(TRIM(INDIRECT("'"&H$6&"'!"&H$4&ROW()-35))="0",INDIRECT("'"&H$6&"'!"&H$4&ROW()-35)="",NOT(ISNUMBER(INDIRECT("'"&H$6&"'!"&H$4&ROW()-35)))),"-",INDIRECT("'"&H$6&"'!"&H$4&ROW()-35))} -> - | I98: {=IF(OR(TRIM(INDIRECT("'"&I$6&"'!"&I$4&ROW()-35))="0",INDIRECT("'"&I$6&"'!"&I$4&ROW()-35)="",NOT(ISNUMBER(INDIRECT("'"&I$6&"'!"&I$4&ROW()-35)))),"-",INDIRECT("'"&I$6&"'!"&I$4&ROW()-35))} -> - | ... M98: {=IF(OR(TRIM(INDIRECT("'"&M$6&"'!"&M$4&ROW()-35))="0",INDIRECT("'"&M$6&"'!"&M$4&ROW()-35)="",NOT(ISNUMBER(INDIRECT("'"&M$6&"'!"&M$4&ROW()-35)))),"-",INDIRECT("'"&M$6&"'!"&M$4&ROW()-35))} -> - | N98: =SUM(B98:M98) -> 0 | O98: =N98/COLUMNS(B98:M98) -> 0
A99: ='Section-Category'!A53 -> Clothing | B99: {=IF(OR(TRIM(INDIRECT("'"&B$6&"'!"&B$4&ROW()-35))="0",INDIRECT("'"&B$6&"'!"&B$4&ROW()-35)="",NOT(ISNUMBER(INDIRECT("'"&B$6&"'!"&B$4&ROW()-35)))),"-",INDIRECT("'"&B$6&"'!"&B$4&ROW()-35))} -> - | C99: {=IF(OR(TRIM(INDIRECT("'"&C$6&"'!"&C$4&ROW()-35))="0",INDIRECT("'"&C$6&"'!"&C$4&ROW()-35)="",NOT(ISNUMBER(INDIRECT("'"&C$6&"'!"&C$4&ROW()-35)))),"-",INDIRECT("'"&C$6&"'!"&C$4&ROW()-35))} -> - | D99: {=IF(OR(TRIM(INDIRECT("'"&D$6&"'!"&D$4&ROW()-35))="0",INDIRECT("'"&D$6&"'!"&D$4&ROW()-35)="",NOT(ISNUMBER(INDIRECT("'"&D$6&"'!"&D$4&ROW()-35)))),"-",INDIRECT("'"&D$6&"'!"&D$4&ROW()-35))} -> - | E99: {=IF(OR(TRIM(INDIRECT("'"&E$6&"'!"&E$4&ROW()-35))="0",INDIRECT("'"&E$6&"'!"&E$4&ROW()-35)="",NOT(ISNUMBER(INDIRECT("'"&E$6&"'!"&E$4&ROW()-35)))),"-",INDIRECT("'"&E$6&"'!"&E$4&ROW()-35))} -> - | F99: {=IF(OR(TRIM(INDIRECT("'"&F$6&"'!"&F$4&ROW()-35))="0",INDIRECT("'"&F$6&"'!"&F$4&ROW()-35)="",NOT(ISNUMBER(INDIRECT("'"&F$6&"'!"&F$4&ROW()-35)))),"-",INDIRECT("'"&F$6&"'!"&F$4&ROW()-35))} -> - | G99: {=IF(OR(TRIM(INDIRECT("'"&G$6&"'!"&G$4&ROW()-35))="0",INDIRECT("'"&G$6&"'!"&G$4&ROW()-35)="",NOT(ISNUMBER(INDIRECT("'"&G$6&"'!"&G$4&ROW()-35)))),"-",INDIRECT("'"&G$6&"'!"&G$4&ROW()-35))} -> - | H99: {=IF(OR(TRIM(INDIRECT("'"&H$6&"'!"&H$4&ROW()-35))="0",INDIRECT("'"&H$6&"'!"&H$4&ROW()-35)="",NOT(ISNUMBER(INDIRECT("'"&H$6&"'!"&H$4&ROW()-35)))),"-",INDIRECT("'"&H$6&"'!"&H$4&ROW()-35))} -> - | I99: {=IF(OR(TRIM(INDIRECT("'"&I$6&"'!"&I$4&ROW()-35))="0",INDIRECT("'"&I$6&"'!"&I$4&ROW()-35)="",NOT(ISNUMBER(INDIRECT("'"&I$6&"'!"&I$4&ROW()-35)))),"-",INDIRECT("'"&I$6&"'!"&I$4&ROW()-35))} -> - | ... M99: {=IF(OR(TRIM(INDIRECT("'"&M$6&"'!"&M$4&ROW()-35))="0",INDIRECT("'"&M$6&"'!"&M$4&ROW()-35)="",NOT(ISNUMBER(INDIRECT("'"&M$6&"'!"&M$4&ROW()-35)))),"-",INDIRECT("'"&M$6&"'!"&M$4&ROW()-35))} -> - | N99: =SUM(B99:M99) -> 0 | O99: =N99/COLUMNS(B99:M99) -> 0
A100: ='Section-Category'!A54 -> School Tuition | B100: {=IF(OR(TRIM(INDIRECT("'"&B$6&"'!"&B$4&ROW()-35))="0",INDIRECT("'"&B$6&"'!"&B$4&ROW()-35)="",NOT(ISNUMBER(INDIRECT("'"&B$6&"'!"&B$4&ROW()-35)))),"-",INDIRECT("'"&B$6&"'!"&B$4&ROW()-35))} -> - | C100: {=IF(OR(TRIM(INDIRECT("'"&C$6&"'!"&C$4&ROW()-35))="0",INDIRECT("'"&C$6&"'!"&C$4&ROW()-35)="",NOT(ISNUMBER(INDIRECT("'"&C$6&"'!"&C$4&ROW()-35)))),"-",INDIRECT("'"&C$6&"'!"&C$4&ROW()-35))} -> - | D100: {=IF(OR(TRIM(INDIRECT("'"&D$6&"'!"&D$4&ROW()-35))="0",INDIRECT("'"&D$6&"'!"&D$4&ROW()-35)="",NOT(ISNUMBER(INDIRECT("'"&D$6&"'!"&D$4&ROW()-35)))),"-",INDIRECT("'"&D$6&"'!"&D$4&ROW()-35))} -> - | E100: {=IF(OR(TRIM(INDIRECT("'"&E$6&"'!"&E$4&ROW()-35))="0",INDIRECT("'"&E$6&"'!"&E$4&ROW()-35)="",NOT(ISNUMBER(INDIRECT("'"&E$6&"'!"&E$4&ROW()-35)))),"-",INDIRECT("'"&E$6&"'!"&E$4&ROW()-35))} -> - | F100: {=IF(OR(TRIM(INDIRECT("'"&F$6&"'!"&F$4&ROW()-35))="0",INDIRECT("'"&F$6&"'!"&F$4&ROW()-35)="",NOT(ISNUMBER(INDIRECT("'"&F$6&"'!"&F$4&ROW()-35)))),"-",INDIRECT("'"&F$6&"'!"&F$4&ROW()-35))} -> - | G100: {=IF(OR(TRIM(INDIRECT("'"&G$6&"'!"&G$4&ROW()-35))="0",INDIRECT("'"&G$6&"'!"&G$4&ROW()-35)="",NOT(ISNUMBER(INDIRECT("'"&G$6&"'!"&G$4&ROW()-35)))),"-",INDIRECT("'"&G$6&"'!"&G$4&ROW()-35))} -> - | H100: {=IF(OR(TRIM(INDIRECT("'"&H$6&"'!"&H$4&ROW()-35))="0",INDIRECT("'"&H$6&"'!"&H$4&ROW()-35)="",NOT(ISNUMBER(INDIRECT("'"&H$6&"'!"&H$4&ROW()-35)))),"-",INDIRECT("'"&H$6&"'!"&H$4&ROW()-35))} -> - | I100: {=IF(OR(TRIM(INDIRECT("'"&I$6&"'!"&I$4&ROW()-35))="0",INDIRECT("'"&I$6&"'!"&I$4&ROW()-35)="",NOT(ISNUMBER(INDIRECT("'"&I$6&"'!"&I$4&ROW()-35)))),"-",INDIRECT("'"&I$6&"'!"&I$4&ROW()-35))} -> - | ... M100: {=IF(OR(TRIM(INDIRECT("'"&M$6&"'!"&M$4&ROW()-35))="0",INDIRECT("'"&M$6&"'!"&M$4&ROW()-35)="",NOT(ISNUMBER(INDIRECT("'"&M$6&"'!"&M$4&ROW()-35)))),"-",INDIRECT("'"&M$6&"'!"&M$4&ROW()-35))} -> - | N100: =SUM(B100:M100) -> 0 | O100: =N100/COLUMNS(B100:M100) -> 0
A101: ='Section-Category'!A55 -> School Lunch | B101: {=IF(OR(TRIM(INDIRECT("'"&B$6&"'!"&B$4&ROW()-35))="0",INDIRECT("'"&B$6&"'!"&B$4&ROW()-35)="",NOT(ISNUMBER(INDIRECT("'"&B$6&"'!"&B$4&ROW()-35)))),"-",INDIRECT("'"&B$6&"'!"&B$4&ROW()-35))} -> - | C101: {=IF(OR(TRIM(INDIRECT("'"&C$6&"'!"&C$4&ROW()-35))="0",INDIRECT("'"&C$6&"'!"&C$4&ROW()-35)="",NOT(ISNUMBER(INDIRECT("'"&C$6&"'!"&C$4&ROW()-35)))),"-",INDIRECT("'"&C$6&"'!"&C$4&ROW()-35))} -> - | D101: {=IF(OR(TRIM(INDIRECT("'"&D$6&"'!"&D$4&ROW()-35))="0",INDIRECT("'"&D$6&"'!"&D$4&ROW()-35)="",NOT(ISNUMBER(INDIRECT("'"&D$6&"'!"&D$4&ROW()-35)))),"-",INDIRECT("'"&D$6&"'!"&D$4&ROW()-35))} -> - | E101: {=IF(OR(TRIM(INDIRECT("'"&E$6&"'!"&E$4&ROW()-35))="0",INDIRECT("'"&E$6&"'!"&E$4&ROW()-35)="",NOT(ISNUMBER(INDIRECT("'"&E$6&"'!"&E$4&ROW()-35)))),"-",INDIRECT("'"&E$6&"'!"&E$4&ROW()-35))} -> - | F101: {=IF(OR(TRIM(INDIRECT("'"&F$6&"'!"&F$4&ROW()-35))="0",INDIRECT("'"&F$6&"'!"&F$4&ROW()-35)="",NOT(ISNUMBER(INDIRECT("'"&F$6&"'!"&F$4&ROW()-35)))),"-",INDIRECT("'"&F$6&"'!"&F$4&ROW()-35))} -> - | G101: {=IF(OR(TRIM(INDIRECT("'"&G$6&"'!"&G$4&ROW()-35))="0",INDIRECT("'"&G$6&"'!"&G$4&ROW()-35)="",NOT(ISNUMBER(INDIRECT("'"&G$6&"'!"&G$4&ROW()-35)))),"-",INDIRECT("'"&G$6&"'!"&G$4&ROW()-35))} -> - | H101: {=IF(OR(TRIM(INDIRECT("'"&H$6&"'!"&H$4&ROW()-35))="0",INDIRECT("'"&H$6&"'!"&H$4&ROW()-35)="",NOT(ISNUMBER(INDIRECT("'"&H$6&"'!"&H$4&ROW()-35)))),"-",INDIRECT("'"&H$6&"'!"&H$4&ROW()-35))} -> - | I101: {=IF(OR(TRIM(INDIRECT("'"&I$6&"'!"&I$4&ROW()-35))="0",INDIRECT("'"&I$6&"'!"&I$4&ROW()-35)="",NOT(ISNUMBER(INDIRECT("'"&I$6&"'!"&I$4&ROW()-35)))),"-",INDIRECT("'"&I$6&"'!"&I$4&ROW()-35))} -> - | ... M101: {=IF(OR(TRIM(INDIRECT("'"&M$6&"'!"&M$4&ROW()-35))="0",INDIRECT("'"&M$6&"'!"&M$4&ROW()-35)="",NOT(ISNUMBER(INDIRECT("'"&M$6&"'!"&M$4&ROW()-35)))),"-",INDIRECT("'"&M$6&"'!"&M$4&ROW()-35))} -> - | N101: =SUM(B101:M101) -> 0 | O101: =N101/COLUMNS(B101:M101) -> 0
A102: ='Section-Category'!A56 -> School Supplies | B102: {=IF(OR(TRIM(INDIRECT("'"&B$6&"'!"&B$4&ROW()-35))="0",INDIRECT("'"&B$6&"'!"&B$4&ROW()-35)="",NOT(ISNUMBER(INDIRECT("'"&B$6&"'!"&B$4&ROW()-35)))),"-",INDIRECT("'"&B$6&"'!"&B$4&ROW()-35))} -> - | C102: {=IF(OR(TRIM(INDIRECT("'"&C$6&"'!"&C$4&ROW()-35))="0",INDIRECT("'"&C$6&"'!"&C$4&ROW()-35)="",NOT(ISNUMBER(INDIRECT("'"&C$6&"'!"&C$4&ROW()-35)))),"-",INDIRECT("'"&C$6&"'!"&C$4&ROW()-35))} -> - | D102: {=IF(OR(TRIM(INDIRECT("'"&D$6&"'!"&D$4&ROW()-35))="0",INDIRECT("'"&D$6&"'!"&D$4&ROW()-35)="",NOT(ISNUMBER(INDIRECT("'"&D$6&"'!"&D$4&ROW()-35)))),"-",INDIRECT("'"&D$6&"'!"&D$4&ROW()-35))} -> - | E102: {=IF(OR(TRIM(INDIRECT("'"&E$6&"'!"&E$4&ROW()-35))="0",INDIRECT("'"&E$6&"'!"&E$4&ROW()-35)="",NOT(ISNUMBER(INDIRECT("'"&E$6&"'!"&E$4&ROW()-35)))),"-",INDIRECT("'"&E$6&"'!"&E$4&ROW()-35))} -> - | F102: {=IF(OR(TRIM(INDIRECT("'"&F$6&"'!"&F$4&ROW()-35))="0",INDIRECT("'"&F$6&"'!"&F$4&ROW()-35)="",NOT(ISNUMBER(INDIRECT("'"&F$6&"'!"&F$4&ROW()-35)))),"-",INDIRECT("'"&F$6&"'!"&F$4&ROW()-35))} -> - | G102: {=IF(OR(TRIM(INDIRECT("'"&G$6&"'!"&G$4&ROW()-35))="0",INDIRECT("'"&G$6&"'!"&G$4&ROW()-35)="",NOT(ISNUMBER(INDIRECT("'"&G$6&"'!"&G$4&ROW()-35)))),"-",INDIRECT("'"&G$6&"'!"&G$4&ROW()-35))} -> - | H102: {=IF(OR(TRIM(INDIRECT("'"&H$6&"'!"&H$4&ROW()-35))="0",INDIRECT("'"&H$6&"'!"&H$4&ROW()-35)="",NOT(ISNUMBER(INDIRECT("'"&H$6&"'!"&H$4&ROW()-35)))),"-",INDIRECT("'"&H$6&"'!"&H$4&ROW()-35))} -> - | I102: {=IF(OR(TRIM(INDIRECT("'"&I$6&"'!"&I$4&ROW()-35))="0",INDIRECT("'"&I$6&"'!"&I$4&ROW()-35)="",NOT(ISNUMBER(INDIRECT("'"&I$6&"'!"&I$4&ROW()-35)))),"-",INDIRECT("'"&I$6&"'!"&I$4&ROW()-35))} -> - | ... M102: {=IF(OR(TRIM(INDIRECT("'"&M$6&"'!"&M$4&ROW()-35))="0",INDIRECT("'"&M$6&"'!"&M$4&ROW()-35)="",NOT(ISNUMBER(INDIRECT("'"&M$6&"'!"&M$4&ROW()-35)))),"-",INDIRECT("'"&M$6&"'!"&M$4&ROW()-35))} -> - | N102: =SUM(B102:M102) -> 0 | O102: =N102/COLUMNS(B102:M102) -> 0
A103: ='Section-Category'!A57 -> Babysitting | B103: {=IF(OR(TRIM(INDIRECT("'"&B$6&"'!"&B$4&ROW()-35))="0",INDIRECT("'"&B$6&"'!"&B$4&ROW()-35)="",NOT(ISNUMBER(INDIRECT("'"&B$6&"'!"&B$4&ROW()-35)))),"-",INDIRECT("'"&B$6&"'!"&B$4&ROW()-35))} -> - | C103: {=IF(OR(TRIM(INDIRECT("'"&C$6&"'!"&C$4&ROW()-35))="0",INDIRECT("'"&C$6&"'!"&C$4&ROW()-35)="",NOT(ISNUMBER(INDIRECT("'"&C$6&"'!"&C$4&ROW()-35)))),"-",INDIRECT("'"&C$6&"'!"&C$4&ROW()-35))} -> - | D103: {=IF(OR(TRIM(INDIRECT("'"&D$6&"'!"&D$4&ROW()-35))="0",INDIRECT("'"&D$6&"'!"&D$4&ROW()-35)="",NOT(ISNUMBER(INDIRECT("'"&D$6&"'!"&D$4&ROW()-35)))),"-",INDIRECT("'"&D$6&"'!"&D$4&ROW()-35))} -> - | E103: {=IF(OR(TRIM(INDIRECT("'"&E$6&"'!"&E$4&ROW()-35))="0",INDIRECT("'"&E$6&"'!"&E$4&ROW()-35)="",NOT(ISNUMBER(INDIRECT("'"&E$6&"'!"&E$4&ROW()-35)))),"-",INDIRECT("'"&E$6&"'!"&E$4&ROW()-35))} -> - | F103: {=IF(OR(TRIM(INDIRECT("'"&F$6&"'!"&F$4&ROW()-35))="0",INDIRECT("'"&F$6&"'!"&F$4&ROW()-35)="",NOT(ISNUMBER(INDIRECT("'"&F$6&"'!"&F$4&ROW()-35)))),"-",INDIRECT("'"&F$6&"'!"&F$4&ROW()-35))} -> - | G103: {=IF(OR(TRIM(INDIRECT("'"&G$6&"'!"&G$4&ROW()-35))="0",INDIRECT("'"&G$6&"'!"&G$4&ROW()-35)="",NOT(ISNUMBER(INDIRECT("'"&G$6&"'!"&G$4&ROW()-35)))),"-",INDIRECT("'"&G$6&"'!"&G$4&ROW()-35))} -> - | H103: {=IF(OR(TRIM(INDIRECT("'"&H$6&"'!"&H$4&ROW()-35))="0",INDIRECT("'"&H$6&"'!"&H$4&ROW()-35)="",NOT(ISNUMBER(INDIRECT("'"&H$6&"'!"&H$4&ROW()-35)))),"-",INDIRECT("'"&H$6&"'!"&H$4&ROW()-35))} -> - | I103: {=IF(OR(TRIM(INDIRECT("'"&I$6&"'!"&I$4&ROW()-35))="0",INDIRECT("'"&I$6&"'!"&I$4&ROW()-35)="",NOT(ISNUMBER(INDIRECT("'"&I$6&"'!"&I$4&ROW()-35)))),"-",INDIRECT("'"&I$6&"'!"&I$4&ROW()-35))} -> - | ... M103: {=IF(OR(TRIM(INDIRECT("'"&M$6&"'!"&M$4&ROW()-35))="0",INDIRECT("'"&M$6&"'!"&M$4&ROW()-35)="",NOT(ISNUMBER(INDIRECT("'"&M$6&"'!"&M$4&ROW()-35)))),"-",INDIRECT("'"&M$6&"'!"&M$4&ROW()-35))} -> - | N103: =SUM(B103:M103) -> 0 | O103: =N103/COLUMNS(B103:M103) -> 0
A104: ='Section-Category'!A58 -> Toys/Games | B104: {=IF(OR(TRIM(INDIRECT("'"&B$6&"'!"&B$4&ROW()-35))="0",INDIRECT("'"&B$6&"'!"&B$4&ROW()-35)="",NOT(ISNUMBER(INDIRECT("'"&B$6&"'!"&B$4&ROW()-35)))),"-",INDIRECT("'"&B$6&"'!"&B$4&ROW()-35))} -> - | C104: {=IF(OR(TRIM(INDIRECT("'"&C$6&"'!"&C$4&ROW()-35))="0",INDIRECT("'"&C$6&"'!"&C$4&ROW()-35)="",NOT(ISNUMBER(INDIRECT("'"&C$6&"'!"&C$4&ROW()-35)))),"-",INDIRECT("'"&C$6&"'!"&C$4&ROW()-35))} -> - | D104: {=IF(OR(TRIM(INDIRECT("'"&D$6&"'!"&D$4&ROW()-35))="0",INDIRECT("'"&D$6&"'!"&D$4&ROW()-35)="",NOT(ISNUMBER(INDIRECT("'"&D$6&"'!"&D$4&ROW()-35)))),"-",INDIRECT("'"&D$6&"'!"&D$4&ROW()-35))} -> - | E104: {=IF(OR(TRIM(INDIRECT("'"&E$6&"'!"&E$4&ROW()-35))="0",INDIRECT("'"&E$6&"'!"&E$4&ROW()-35)="",NOT(ISNUMBER(INDIRECT("'"&E$6&"'!"&E$4&ROW()-35)))),"-",INDIRECT("'"&E$6&"'!"&E$4&ROW()-35))} -> - | F104: {=IF(OR(TRIM(INDIRECT("'"&F$6&"'!"&F$4&ROW()-35))="0",INDIRECT("'"&F$6&"'!"&F$4&ROW()-35)="",NOT(ISNUMBER(INDIRECT("'"&F$6&"'!"&F$4&ROW()-35)))),"-",INDIRECT("'"&F$6&"'!"&F$4&ROW()-35))} -> - | G104: {=IF(OR(TRIM(INDIRECT("'"&G$6&"'!"&G$4&ROW()-35))="0",INDIRECT("'"&G$6&"'!"&G$4&ROW()-35)="",NOT(ISNUMBER(INDIRECT("'"&G$6&"'!"&G$4&ROW()-35)))),"-",INDIRECT("'"&G$6&"'!"&G$4&ROW()-35))} -> - | H104: {=IF(OR(TRIM(INDIRECT("'"&H$6&"'!"&H$4&ROW()-35))="0",INDIRECT("'"&H$6&"'!"&H$4&ROW()-35)="",NOT(ISNUMBER(INDIRECT("'"&H$6&"'!"&H$4&ROW()-35)))),"-",INDIRECT("'"&H$6&"'!"&H$4&ROW()-35))} -> - | I104: {=IF(OR(TRIM(INDIRECT("'"&I$6&"'!"&I$4&ROW()-35))="0",INDIRECT("'"&I$6&"'!"&I$4&ROW()-35)="",NOT(ISNUMBER(INDIRECT("'"&I$6&"'!"&I$4&ROW()-35)))),"-",INDIRECT("'"&I$6&"'!"&I$4&ROW()-35))} -> - | ... M104: {=IF(OR(TRIM(INDIRECT("'"&M$6&"'!"&M$4&ROW()-35))="0",INDIRECT("'"&M$6&"'!"&M$4&ROW()-35)="",NOT(ISNUMBER(INDIRECT("'"&M$6&"'!"&M$4&ROW()-35)))),"-",INDIRECT("'"&M$6&"'!"&M$4&ROW()-35))} -> - | N104: =SUM(B104:M104) -> 0 | O104: =N104/COLUMNS(B104:M104) -> 0
A105: ='Section-Category'!A59 -> Other | B105: {=IF(OR(TRIM(INDIRECT("'"&B$6&"'!"&B$4&ROW()-35))="0",INDIRECT("'"&B$6&"'!"&B$4&ROW()-35)="",NOT(ISNUMBER(INDIRECT("'"&B$6&"'!"&B$4&ROW()-35)))),"-",INDIRECT("'"&B$6&"'!"&B$4&ROW()-35))} -> - | C105: {=IF(OR(TRIM(INDIRECT("'"&C$6&"'!"&C$4&ROW()-35))="0",INDIRECT("'"&C$6&"'!"&C$4&ROW()-35)="",NOT(ISNUMBER(INDIRECT("'"&C$6&"'!"&C$4&ROW()-35)))),"-",INDIRECT("'"&C$6&"'!"&C$4&ROW()-35))} -> - | D105: {=IF(OR(TRIM(INDIRECT("'"&D$6&"'!"&D$4&ROW()-35))="0",INDIRECT("'"&D$6&"'!"&D$4&ROW()-35)="",NOT(ISNUMBER(INDIRECT("'"&D$6&"'!"&D$4&ROW()-35)))),"-",INDIRECT("'"&D$6&"'!"&D$4&ROW()-35))} -> - | E105: {=IF(OR(TRIM(INDIRECT("'"&E$6&"'!"&E$4&ROW()-35))="0",INDIRECT("'"&E$6&"'!"&E$4&ROW()-35)="",NOT(ISNUMBER(INDIRECT("'"&E$6&"'!"&E$4&ROW()-35)))),"-",INDIRECT("'"&E$6&"'!"&E$4&ROW()-35))} -> - | F105: {=IF(OR(TRIM(INDIRECT("'"&F$6&"'!"&F$4&ROW()-35))="0",INDIRECT("'"&F$6&"'!"&F$4&ROW()-35)="",NOT(ISNUMBER(INDIRECT("'"&F$6&"'!"&F$4&ROW()-35)))),"-",INDIRECT("'"&F$6&"'!"&F$4&ROW()-35))} -> - | G105: {=IF(OR(TRIM(INDIRECT("'"&G$6&"'!"&G$4&ROW()-35))="0",INDIRECT("'"&G$6&"'!"&G$4&ROW()-35)="",NOT(ISNUMBER(INDIRECT("'"&G$6&"'!"&G$4&ROW()-35)))),"-",INDIRECT("'"&G$6&"'!"&G$4&ROW()-35))} -> - | H105: {=IF(OR(TRIM(INDIRECT("'"&H$6&"'!"&H$4&ROW()-35))="0",INDIRECT("'"&H$6&"'!"&H$4&ROW()-35)="",NOT(ISNUMBER(INDIRECT("'"&H$6&"'!"&H$4&ROW()-35)))),"-",INDIRECT("'"&H$6&"'!"&H$4&ROW()-35))} -> - | I105: {=IF(OR(TRIM(INDIRECT("'"&I$6&"'!"&I$4&ROW()-35))="0",INDIRECT("'"&I$6&"'!"&I$4&ROW()-35)="",NOT(ISNUMBER(INDIRECT("'"&I$6&"'!"&I$4&ROW()-35)))),"-",INDIRECT("'"&I$6&"'!"&I$4&ROW()-35))} -> - | ... M105: {=IF(OR(TRIM(INDIRECT("'"&M$6&"'!"&M$4&ROW()-35))="0",INDIRECT("'"&M$6&"'!"&M$4&ROW()-35)="",NOT(ISNUMBER(INDIRECT("'"&M$6&"'!"&M$4&ROW()-35)))),"-",INDIRECT("'"&M$6&"'!"&M$4&ROW()-35))} -> - | N105: =SUM(B105:M105) -> 0 | O105: =N105/COLUMNS(B105:M105) -> 0
A106: ='Section-Category'!A60 -> Total CHILDREN | B106: =SUM(B98:B105) -> 0 | C106: =SUM(C98:C105) -> 0 | D106: =SUM(D98:D105) -> 0 | E106: =SUM(E98:E105) -> 0 | F106: =SUM(F98:F105) -> 0 | G106: =SUM(G98:G105) -> 0 | H106: =SUM(H98:H105) -> 0 | I106: =SUM(I98:I105) -> 0 | ... O106: =SUM(O98:O105) -> 0
A107: ='Section-Category'!A61 -> % of Total Expenses | B107: =IF(B$17=0," - ",B106/B$17) -> - | C107: =IF(C$17=0," - ",C106/C$17) -> - | D107: =IF(D$17=0," - ",D106/D$17) -> - | E107: =IF(E$17=0," - ",E106/E$17) -> - | F107: =IF(F$17=0," - ",F106/F$17) -> - | G107: =IF(G$17=0," - ",G106/G$17) -> - | H107: =IF(H$17=0," - ",H106/H$17) -> - | I107: =IF(I$17=0," - ",I106/I$17) -> - | ... O107: =IF(O$17=0," - ",O106/O$17) -> -
A109: ='Section-Category'!A63 -> TRANSPORTATION | B109: =B$6 -> Jan | C109: =C$6 -> Feb | D109: =D$6 -> Mar | E109: =E$6 -> Apr | F109: =F$6 -> May | G109: =G$6 -> Jun | H109: =H$6 -> Jul | I109: =I$6 -> Aug | ... M109: =M$6 -> Dec | N109: Total | O109: Avg
A110: ='Section-Category'!A64 -> Vehicle Payments | B110: {=IF(OR(TRIM(INDIRECT("'"&B$6&"'!"&B$4&ROW()-36))="0",INDIRECT("'"&B$6&"'!"&B$4&ROW()-36)="",NOT(ISNUMBER(INDIRECT("'"&B$6&"'!"&B$4&ROW()-36)))),"-",INDIRECT("'"&B$6&"'!"&B$4&ROW()-36))} -> - | C110: {=IF(OR(TRIM(INDIRECT("'"&C$6&"'!"&C$4&ROW()-36))="0",INDIRECT("'"&C$6&"'!"&C$4&ROW()-36)="",NOT(ISNUMBER(INDIRECT("'"&C$6&"'!"&C$4&ROW()-36)))),"-",INDIRECT("'"&C$6&"'!"&C$4&ROW()-36))} -> - | D110: {=IF(OR(TRIM(INDIRECT("'"&D$6&"'!"&D$4&ROW()-36))="0",INDIRECT("'"&D$6&"'!"&D$4&ROW()-36)="",NOT(ISNUMBER(INDIRECT("'"&D$6&"'!"&D$4&ROW()-36)))),"-",INDIRECT("'"&D$6&"'!"&D$4&ROW()-36))} -> - | E110: {=IF(OR(TRIM(INDIRECT("'"&E$6&"'!"&E$4&ROW()-36))="0",INDIRECT("'"&E$6&"'!"&E$4&ROW()-36)="",NOT(ISNUMBER(INDIRECT("'"&E$6&"'!"&E$4&ROW()-36)))),"-",INDIRECT("'"&E$6&"'!"&E$4&ROW()-36))} -> - | F110: {=IF(OR(TRIM(INDIRECT("'"&F$6&"'!"&F$4&ROW()-36))="0",INDIRECT("'"&F$6&"'!"&F$4&ROW()-36)="",NOT(ISNUMBER(INDIRECT("'"&F$6&"'!"&F$4&ROW()-36)))),"-",INDIRECT("'"&F$6&"'!"&F$4&ROW()-36))} -> - | G110: {=IF(OR(TRIM(INDIRECT("'"&G$6&"'!"&G$4&ROW()-36))="0",INDIRECT("'"&G$6&"'!"&G$4&ROW()-36)="",NOT(ISNUMBER(INDIRECT("'"&G$6&"'!"&G$4&ROW()-36)))),"-",INDIRECT("'"&G$6&"'!"&G$4&ROW()-36))} -> - | H110: {=IF(OR(TRIM(INDIRECT("'"&H$6&"'!"&H$4&ROW()-36))="0",INDIRECT("'"&H$6&"'!"&H$4&ROW()-36)="",NOT(ISNUMBER(INDIRECT("'"&H$6&"'!"&H$4&ROW()-36)))),"-",INDIRECT("'"&H$6&"'!"&H$4&ROW()-36))} -> - | I110: {=IF(OR(TRIM(INDIRECT("'"&I$6&"'!"&I$4&ROW()-36))="0",INDIRECT("'"&I$6&"'!"&I$4&ROW()-36)="",NOT(ISNUMBER(INDIRECT("'"&I$6&"'!"&I$4&ROW()-36)))),"-",INDIRECT("'"&I$6&"'!"&I$4&ROW()-36))} -> - | ... M110: {=IF(OR(TRIM(INDIRECT("'"&M$6&"'!"&M$4&ROW()-36))="0",INDIRECT("'"&M$6&"'!"&M$4&ROW()-36)="",NOT(ISNUMBER(INDIRECT("'"&M$6&"'!"&M$4&ROW()-36)))),"-",INDIRECT("'"&M$6&"'!"&M$4&ROW()-36))} -> - | N110: =SUM(B110:M110) -> 0 | O110: =N110/COLUMNS(B110:M110) -> 0
A111: ='Section-Category'!A65 -> Fuel | B111: {=IF(OR(TRIM(INDIRECT("'"&B$6&"'!"&B$4&ROW()-36))="0",INDIRECT("'"&B$6&"'!"&B$4&ROW()-36)="",NOT(ISNUMBER(INDIRECT("'"&B$6&"'!"&B$4&ROW()-36)))),"-",INDIRECT("'"&B$6&"'!"&B$4&ROW()-36))} -> - | C111: {=IF(OR(TRIM(INDIRECT("'"&C$6&"'!"&C$4&ROW()-36))="0",INDIRECT("'"&C$6&"'!"&C$4&ROW()-36)="",NOT(ISNUMBER(INDIRECT("'"&C$6&"'!"&C$4&ROW()-36)))),"-",INDIRECT("'"&C$6&"'!"&C$4&ROW()-36))} -> - | D111: {=IF(OR(TRIM(INDIRECT("'"&D$6&"'!"&D$4&ROW()-36))="0",INDIRECT("'"&D$6&"'!"&D$4&ROW()-36)="",NOT(ISNUMBER(INDIRECT("'"&D$6&"'!"&D$4&ROW()-36)))),"-",INDIRECT("'"&D$6&"'!"&D$4&ROW()-36))} -> - | E111: {=IF(OR(TRIM(INDIRECT("'"&E$6&"'!"&E$4&ROW()-36))="0",INDIRECT("'"&E$6&"'!"&E$4&ROW()-36)="",NOT(ISNUMBER(INDIRECT("'"&E$6&"'!"&E$4&ROW()-36)))),"-",INDIRECT("'"&E$6&"'!"&E$4&ROW()-36))} -> - | F111: {=IF(OR(TRIM(INDIRECT("'"&F$6&"'!"&F$4&ROW()-36))="0",INDIRECT("'"&F$6&"'!"&F$4&ROW()-36)="",NOT(ISNUMBER(INDIRECT("'"&F$6&"'!"&F$4&ROW()-36)))),"-",INDIRECT("'"&F$6&"'!"&F$4&ROW()-36))} -> - | G111: {=IF(OR(TRIM(INDIRECT("'"&G$6&"'!"&G$4&ROW()-36))="0",INDIRECT("'"&G$6&"'!"&G$4&ROW()-36)="",NOT(ISNUMBER(INDIRECT("'"&G$6&"'!"&G$4&ROW()-36)))),"-",INDIRECT("'"&G$6&"'!"&G$4&ROW()-36))} -> - | H111: {=IF(OR(TRIM(INDIRECT("'"&H$6&"'!"&H$4&ROW()-36))="0",INDIRECT("'"&H$6&"'!"&H$4&ROW()-36)="",NOT(ISNUMBER(INDIRECT("'"&H$6&"'!"&H$4&ROW()-36)))),"-",INDIRECT("'"&H$6&"'!"&H$4&ROW()-36))} -> - | I111: {=IF(OR(TRIM(INDIRECT("'"&I$6&"'!"&I$4&ROW()-36))="0",INDIRECT("'"&I$6&"'!"&I$4&ROW()-36)="",NOT(ISNUMBER(INDIRECT("'"&I$6&"'!"&I$4&ROW()-36)))),"-",INDIRECT("'"&I$6&"'!"&I$4&ROW()-36))} -> - | ... M111: {=IF(OR(TRIM(INDIRECT("'"&M$6&"'!"&M$4&ROW()-36))="0",INDIRECT("'"&M$6&"'!"&M$4&ROW()-36)="",NOT(ISNUMBER(INDIRECT("'"&M$6&"'!"&M$4&ROW()-36)))),"-",INDIRECT("'"&M$6&"'!"&M$4&ROW()-36))} -> - | N111: =SUM(B111:M111) -> 0 | O111: =N111/COLUMNS(B111:M111) -> 0
A112: ='Section-Category'!A66 -> Bus/Taxi/Train Fare | B112: {=IF(OR(TRIM(INDIRECT("'"&B$6&"'!"&B$4&ROW()-36))="0",INDIRECT("'"&B$6&"'!"&B$4&ROW()-36)="",NOT(ISNUMBER(INDIRECT("'"&B$6&"'!"&B$4&ROW()-36)))),"-",INDIRECT("'"&B$6&"'!"&B$4&ROW()-36))} -> - | C112: {=IF(OR(TRIM(INDIRECT("'"&C$6&"'!"&C$4&ROW()-36))="0",INDIRECT("'"&C$6&"'!"&C$4&ROW()-36)="",NOT(ISNUMBER(INDIRECT("'"&C$6&"'!"&C$4&ROW()-36)))),"-",INDIRECT("'"&C$6&"'!"&C$4&ROW()-36))} -> - | D112: {=IF(OR(TRIM(INDIRECT("'"&D$6&"'!"&D$4&ROW()-36))="0",INDIRECT("'"&D$6&"'!"&D$4&ROW()-36)="",NOT(ISNUMBER(INDIRECT("'"&D$6&"'!"&D$4&ROW()-36)))),"-",INDIRECT("'"&D$6&"'!"&D$4&ROW()-36))} -> - | E112: {=IF(OR(TRIM(INDIRECT("'"&E$6&"'!"&E$4&ROW()-36))="0",INDIRECT("'"&E$6&"'!"&E$4&ROW()-36)="",NOT(ISNUMBER(INDIRECT("'"&E$6&"'!"&E$4&ROW()-36)))),"-",INDIRECT("'"&E$6&"'!"&E$4&ROW()-36))} -> - | F112: {=IF(OR(TRIM(INDIRECT("'"&F$6&"'!"&F$4&ROW()-36))="0",INDIRECT("'"&F$6&"'!"&F$4&ROW()-36)="",NOT(ISNUMBER(INDIRECT("'"&F$6&"'!"&F$4&ROW()-36)))),"-",INDIRECT("'"&F$6&"'!"&F$4&ROW()-36))} -> - | G112: {=IF(OR(TRIM(INDIRECT("'"&G$6&"'!"&G$4&ROW()-36))="0",INDIRECT("'"&G$6&"'!"&G$4&ROW()-36)="",NOT(ISNUMBER(INDIRECT("'"&G$6&"'!"&G$4&ROW()-36)))),"-",INDIRECT("'"&G$6&"'!"&G$4&ROW()-36))} -> - | H112: {=IF(OR(TRIM(INDIRECT("'"&H$6&"'!"&H$4&ROW()-36))="0",INDIRECT("'"&H$6&"'!"&H$4&ROW()-36)="",NOT(ISNUMBER(INDIRECT("'"&H$6&"'!"&H$4&ROW()-36)))),"-",INDIRECT("'"&H$6&"'!"&H$4&ROW()-36))} -> - | I112: {=IF(OR(TRIM(INDIRECT("'"&I$6&"'!"&I$4&ROW()-36))="0",INDIRECT("'"&I$6&"'!"&I$4&ROW()-36)="",NOT(ISNUMBER(INDIRECT("'"&I$6&"'!"&I$4&ROW()-36)))),"-",INDIRECT("'"&I$6&"'!"&I$4&ROW()-36))} -> - | ... M112: {=IF(OR(TRIM(INDIRECT("'"&M$6&"'!"&M$4&ROW()-36))="0",INDIRECT("'"&M$6&"'!"&M$4&ROW()-36)="",NOT(ISNUMBER(INDIRECT("'"&M$6&"'!"&M$4&ROW()-36)))),"-",INDIRECT("'"&M$6&"'!"&M$4&ROW()-36))} -> - | N112: =SUM(B112:M112) -> 0 | O112: =N112/COLUMNS(B112:M112) -> 0
A113: ='Section-Category'!A67 -> Repairs | B113: {=IF(OR(TRIM(INDIRECT("'"&B$6&"'!"&B$4&ROW()-36))="0",INDIRECT("'"&B$6&"'!"&B$4&ROW()-36)="",NOT(ISNUMBER(INDIRECT("'"&B$6&"'!"&B$4&ROW()-36)))),"-",INDIRECT("'"&B$6&"'!"&B$4&ROW()-36))} -> - | C113: {=IF(OR(TRIM(INDIRECT("'"&C$6&"'!"&C$4&ROW()-36))="0",INDIRECT("'"&C$6&"'!"&C$4&ROW()-36)="",NOT(ISNUMBER(INDIRECT("'"&C$6&"'!"&C$4&ROW()-36)))),"-",INDIRECT("'"&C$6&"'!"&C$4&ROW()-36))} -> - | D113: {=IF(OR(TRIM(INDIRECT("'"&D$6&"'!"&D$4&ROW()-36))="0",INDIRECT("'"&D$6&"'!"&D$4&ROW()-36)="",NOT(ISNUMBER(INDIRECT("'"&D$6&"'!"&D$4&ROW()-36)))),"-",INDIRECT("'"&D$6&"'!"&D$4&ROW()-36))} -> - | E113: {=IF(OR(TRIM(INDIRECT("'"&E$6&"'!"&E$4&ROW()-36))="0",INDIRECT("'"&E$6&"'!"&E$4&ROW()-36)="",NOT(ISNUMBER(INDIRECT("'"&E$6&"'!"&E$4&ROW()-36)))),"-",INDIRECT("'"&E$6&"'!"&E$4&ROW()-36))} -> - | F113: {=IF(OR(TRIM(INDIRECT("'"&F$6&"'!"&F$4&ROW()-36))="0",INDIRECT("'"&F$6&"'!"&F$4&ROW()-36)="",NOT(ISNUMBER(INDIRECT("'"&F$6&"'!"&F$4&ROW()-36)))),"-",INDIRECT("'"&F$6&"'!"&F$4&ROW()-36))} -> - | G113: {=IF(OR(TRIM(INDIRECT("'"&G$6&"'!"&G$4&ROW()-36))="0",INDIRECT("'"&G$6&"'!"&G$4&ROW()-36)="",NOT(ISNUMBER(INDIRECT("'"&G$6&"'!"&G$4&ROW()-36)))),"-",INDIRECT("'"&G$6&"'!"&G$4&ROW()-36))} -> - | H113: {=IF(OR(TRIM(INDIRECT("'"&H$6&"'!"&H$4&ROW()-36))="0",INDIRECT("'"&H$6&"'!"&H$4&ROW()-36)="",NOT(ISNUMBER(INDIRECT("'"&H$6&"'!"&H$4&ROW()-36)))),"-",INDIRECT("'"&H$6&"'!"&H$4&ROW()-36))} -> - | I113: {=IF(OR(TRIM(INDIRECT("'"&I$6&"'!"&I$4&ROW()-36))="0",INDIRECT("'"&I$6&"'!"&I$4&ROW()-36)="",NOT(ISNUMBER(INDIRECT("'"&I$6&"'!"&I$4&ROW()-36)))),"-",INDIRECT("'"&I$6&"'!"&I$4&ROW()-36))} -> - | ... M113: {=IF(OR(TRIM(INDIRECT("'"&M$6&"'!"&M$4&ROW()-36))="0",INDIRECT("'"&M$6&"'!"&M$4&ROW()-36)="",NOT(ISNUMBER(INDIRECT("'"&M$6&"'!"&M$4&ROW()-36)))),"-",INDIRECT("'"&M$6&"'!"&M$4&ROW()-36))} -> - | N113: =SUM(B113:M113) -> 0 | O113: =N113/COLUMNS(B113:M113) -> 0
A114: ='Section-Category'!A68 -> Registration/License | B114: {=IF(OR(TRIM(INDIRECT("'"&B$6&"'!"&B$4&ROW()-36))="0",INDIRECT("'"&B$6&"'!"&B$4&ROW()-36)="",NOT(ISNUMBER(INDIRECT("'"&B$6&"'!"&B$4&ROW()-36)))),"-",INDIRECT("'"&B$6&"'!"&B$4&ROW()-36))} -> - | C114: {=IF(OR(TRIM(INDIRECT("'"&C$6&"'!"&C$4&ROW()-36))="0",INDIRECT("'"&C$6&"'!"&C$4&ROW()-36)="",NOT(ISNUMBER(INDIRECT("'"&C$6&"'!"&C$4&ROW()-36)))),"-",INDIRECT("'"&C$6&"'!"&C$4&ROW()-36))} -> - | D114: {=IF(OR(TRIM(INDIRECT("'"&D$6&"'!"&D$4&ROW()-36))="0",INDIRECT("'"&D$6&"'!"&D$4&ROW()-36)="",NOT(ISNUMBER(INDIRECT("'"&D$6&"'!"&D$4&ROW()-36)))),"-",INDIRECT("'"&D$6&"'!"&D$4&ROW()-36))} -> - | E114: {=IF(OR(TRIM(INDIRECT("'"&E$6&"'!"&E$4&ROW()-36))="0",INDIRECT("'"&E$6&"'!"&E$4&ROW()-36)="",NOT(ISNUMBER(INDIRECT("'"&E$6&"'!"&E$4&ROW()-36)))),"-",INDIRECT("'"&E$6&"'!"&E$4&ROW()-36))} -> - | F114: {=IF(OR(TRIM(INDIRECT("'"&F$6&"'!"&F$4&ROW()-36))="0",INDIRECT("'"&F$6&"'!"&F$4&ROW()-36)="",NOT(ISNUMBER(INDIRECT("'"&F$6&"'!"&F$4&ROW()-36)))),"-",INDIRECT("'"&F$6&"'!"&F$4&ROW()-36))} -> - | G114: {=IF(OR(TRIM(INDIRECT("'"&G$6&"'!"&G$4&ROW()-36))="0",INDIRECT("'"&G$6&"'!"&G$4&ROW()-36)="",NOT(ISNUMBER(INDIRECT("'"&G$6&"'!"&G$4&ROW()-36)))),"-",INDIRECT("'"&G$6&"'!"&G$4&ROW()-36))} -> - | H114: {=IF(OR(TRIM(INDIRECT("'"&H$6&"'!"&H$4&ROW()-36))="0",INDIRECT("'"&H$6&"'!"&H$4&ROW()-36)="",NOT(ISNUMBER(INDIRECT("'"&H$6&"'!"&H$4&ROW()-36)))),"-",INDIRECT("'"&H$6&"'!"&H$4&ROW()-36))} -> - | I114: {=IF(OR(TRIM(INDIRECT("'"&I$6&"'!"&I$4&ROW()-36))="0",INDIRECT("'"&I$6&"'!"&I$4&ROW()-36)="",NOT(ISNUMBER(INDIRECT("'"&I$6&"'!"&I$4&ROW()-36)))),"-",INDIRECT("'"&I$6&"'!"&I$4&ROW()-36))} -> - | ... M114: {=IF(OR(TRIM(INDIRECT("'"&M$6&"'!"&M$4&ROW()-36))="0",INDIRECT("'"&M$6&"'!"&M$4&ROW()-36)="",NOT(ISNUMBER(INDIRECT("'"&M$6&"'!"&M$4&ROW()-36)))),"-",INDIRECT("'"&M$6&"'!"&M$4&ROW()-36))} -> - | N114: =SUM(B114:M114) -> 0 | O114: =N114/COLUMNS(B114:M114) -> 0
A115: ='Section-Category'!A69 -> Other | B115: {=IF(OR(TRIM(INDIRECT("'"&B$6&"'!"&B$4&ROW()-36))="0",INDIRECT("'"&B$6&"'!"&B$4&ROW()-36)="",NOT(ISNUMBER(INDIRECT("'"&B$6&"'!"&B$4&ROW()-36)))),"-",INDIRECT("'"&B$6&"'!"&B$4&ROW()-36))} -> - | C115: {=IF(OR(TRIM(INDIRECT("'"&C$6&"'!"&C$4&ROW()-36))="0",INDIRECT("'"&C$6&"'!"&C$4&ROW()-36)="",NOT(ISNUMBER(INDIRECT("'"&C$6&"'!"&C$4&ROW()-36)))),"-",INDIRECT("'"&C$6&"'!"&C$4&ROW()-36))} -> - | D115: {=IF(OR(TRIM(INDIRECT("'"&D$6&"'!"&D$4&ROW()-36))="0",INDIRECT("'"&D$6&"'!"&D$4&ROW()-36)="",NOT(ISNUMBER(INDIRECT("'"&D$6&"'!"&D$4&ROW()-36)))),"-",INDIRECT("'"&D$6&"'!"&D$4&ROW()-36))} -> - | E115: {=IF(OR(TRIM(INDIRECT("'"&E$6&"'!"&E$4&ROW()-36))="0",INDIRECT("'"&E$6&"'!"&E$4&ROW()-36)="",NOT(ISNUMBER(INDIRECT("'"&E$6&"'!"&E$4&ROW()-36)))),"-",INDIRECT("'"&E$6&"'!"&E$4&ROW()-36))} -> - | F115: {=IF(OR(TRIM(INDIRECT("'"&F$6&"'!"&F$4&ROW()-36))="0",INDIRECT("'"&F$6&"'!"&F$4&ROW()-36)="",NOT(ISNUMBER(INDIRECT("'"&F$6&"'!"&F$4&ROW()-36)))),"-",INDIRECT("'"&F$6&"'!"&F$4&ROW()-36))} -> - | G115: {=IF(OR(TRIM(INDIRECT("'"&G$6&"'!"&G$4&ROW()-36))="0",INDIRECT("'"&G$6&"'!"&G$4&ROW()-36)="",NOT(ISNUMBER(INDIRECT("'"&G$6&"'!"&G$4&ROW()-36)))),"-",INDIRECT("'"&G$6&"'!"&G$4&ROW()-36))} -> - | H115: {=IF(OR(TRIM(INDIRECT("'"&H$6&"'!"&H$4&ROW()-36))="0",INDIRECT("'"&H$6&"'!"&H$4&ROW()-36)="",NOT(ISNUMBER(INDIRECT("'"&H$6&"'!"&H$4&ROW()-36)))),"-",INDIRECT("'"&H$6&"'!"&H$4&ROW()-36))} -> - | I115: {=IF(OR(TRIM(INDIRECT("'"&I$6&"'!"&I$4&ROW()-36))="0",INDIRECT("'"&I$6&"'!"&I$4&ROW()-36)="",NOT(ISNUMBER(INDIRECT("'"&I$6&"'!"&I$4&ROW()-36)))),"-",INDIRECT("'"&I$6&"'!"&I$4&ROW()-36))} -> - | ... M115: {=IF(OR(TRIM(INDIRECT("'"&M$6&"'!"&M$4&ROW()-36))="0",INDIRECT("'"&M$6&"'!"&M$4&ROW()-36)="",NOT(ISNUMBER(INDIRECT("'"&M$6&"'!"&M$4&ROW()-36)))),"-",INDIRECT("'"&M$6&"'!"&M$4&ROW()-36))} -> - | N115: =SUM(B115:M115) -> 0 | O115: =N115/COLUMNS(B115:M115) -> 0
A116: ='Section-Category'!A70 -> Total TRANSPORTATION | B116: =SUM(B110:B115) -> 0 | C116: =SUM(C110:C115) -> 0 | D116: =SUM(D110:D115) -> 0 | E116: =SUM(E110:E115) -> 0 | F116: =SUM(F110:F115) -> 0 | G116: =SUM(G110:G115) -> 0 | H116: =SUM(H110:H115) -> 0 | I116: =SUM(I110:I115) -> 0 | ... O116: =SUM(O110:O115) -> 0
A117: ='Section-Category'!A71 -> % of Total Expenses | B117: =IF(B$17=0," - ",B116/B$17) -> - | C117: =IF(C$17=0," - ",C116/C$17) -> - | D117: =IF(D$17=0," - ",D116/D$17) -> - | E117: =IF(E$17=0," - ",E116/E$17) -> - | F117: =IF(F$17=0," - ",F116/F$17) -> - | G117: =IF(G$17=0," - ",G116/G$17) -> - | H117: =IF(H$17=0," - ",H116/H$17) -> - | I117: =IF(I$17=0," - ",I116/I$17) -> - | ... O117: =IF(O$17=0," - ",O116/O$17) -> -
A119: ='Section-Category'!A73 -> HEALTH | B119: =B$6 -> Jan | C119: =C$6 -> Feb | D119: =D$6 -> Mar | E119: =E$6 -> Apr | F119: =F$6 -> May | G119: =G$6 -> Jun | H119: =H$6 -> Jul | I119: =I$6 -> Aug | ... M119: =M$6 -> Dec | N119: Total | O119: Avg
A120: ='Section-Category'!A74 -> Doctor/Dentist | B120: {=IF(OR(TRIM(INDIRECT("'"&B$6&"'!"&B$4&ROW()-37))="0",INDIRECT("'"&B$6&"'!"&B$4&ROW()-37)="",NOT(ISNUMBER(INDIRECT("'"&B$6&"'!"&B$4&ROW()-37)))),"-",INDIRECT("'"&B$6&"'!"&B$4&ROW()-37))} -> - | C120: {=IF(OR(TRIM(INDIRECT("'"&C$6&"'!"&C$4&ROW()-37))="0",INDIRECT("'"&C$6&"'!"&C$4&ROW()-37)="",NOT(ISNUMBER(INDIRECT("'"&C$6&"'!"&C$4&ROW()-37)))),"-",INDIRECT("'"&C$6&"'!"&C$4&ROW()-37))} -> - | D120: {=IF(OR(TRIM(INDIRECT("'"&D$6&"'!"&D$4&ROW()-37))="0",INDIRECT("'"&D$6&"'!"&D$4&ROW()-37)="",NOT(ISNUMBER(INDIRECT("'"&D$6&"'!"&D$4&ROW()-37)))),"-",INDIRECT("'"&D$6&"'!"&D$4&ROW()-37))} -> - | E120: {=IF(OR(TRIM(INDIRECT("'"&E$6&"'!"&E$4&ROW()-37))="0",INDIRECT("'"&E$6&"'!"&E$4&ROW()-37)="",NOT(ISNUMBER(INDIRECT("'"&E$6&"'!"&E$4&ROW()-37)))),"-",INDIRECT("'"&E$6&"'!"&E$4&ROW()-37))} -> - | F120: {=IF(OR(TRIM(INDIRECT("'"&F$6&"'!"&F$4&ROW()-37))="0",INDIRECT("'"&F$6&"'!"&F$4&ROW()-37)="",NOT(ISNUMBER(INDIRECT("'"&F$6&"'!"&F$4&ROW()-37)))),"-",INDIRECT("'"&F$6&"'!"&F$4&ROW()-37))} -> - | G120: {=IF(OR(TRIM(INDIRECT("'"&G$6&"'!"&G$4&ROW()-37))="0",INDIRECT("'"&G$6&"'!"&G$4&ROW()-37)="",NOT(ISNUMBER(INDIRECT("'"&G$6&"'!"&G$4&ROW()-37)))),"-",INDIRECT("'"&G$6&"'!"&G$4&ROW()-37))} -> - | H120: {=IF(OR(TRIM(INDIRECT("'"&H$6&"'!"&H$4&ROW()-37))="0",INDIRECT("'"&H$6&"'!"&H$4&ROW()-37)="",NOT(ISNUMBER(INDIRECT("'"&H$6&"'!"&H$4&ROW()-37)))),"-",INDIRECT("'"&H$6&"'!"&H$4&ROW()-37))} -> - | I120: {=IF(OR(TRIM(INDIRECT("'"&I$6&"'!"&I$4&ROW()-37))="0",INDIRECT("'"&I$6&"'!"&I$4&ROW()-37)="",NOT(ISNUMBER(INDIRECT("'"&I$6&"'!"&I$4&ROW()-37)))),"-",INDIRECT("'"&I$6&"'!"&I$4&ROW()-37))} -> - | ... M120: {=IF(OR(TRIM(INDIRECT("'"&M$6&"'!"&M$4&ROW()-37))="0",INDIRECT("'"&M$6&"'!"&M$4&ROW()-37)="",NOT(ISNUMBER(INDIRECT("'"&M$6&"'!"&M$4&ROW()-37)))),"-",INDIRECT("'"&M$6&"'!"&M$4&ROW()-37))} -> - | N120: 0 | O120: =N120/COLUMNS(B120:M120) -> 0
A121: ='Section-Category'!A75 -> Medicine/Drugs | B121: {=IF(OR(TRIM(INDIRECT("'"&B$6&"'!"&B$4&ROW()-37))="0",INDIRECT("'"&B$6&"'!"&B$4&ROW()-37)="",NOT(ISNUMBER(INDIRECT("'"&B$6&"'!"&B$4&ROW()-37)))),"-",INDIRECT("'"&B$6&"'!"&B$4&ROW()-37))} -> - | C121: {=IF(OR(TRIM(INDIRECT("'"&C$6&"'!"&C$4&ROW()-37))="0",INDIRECT("'"&C$6&"'!"&C$4&ROW()-37)="",NOT(ISNUMBER(INDIRECT("'"&C$6&"'!"&C$4&ROW()-37)))),"-",INDIRECT("'"&C$6&"'!"&C$4&ROW()-37))} -> - | D121: {=IF(OR(TRIM(INDIRECT("'"&D$6&"'!"&D$4&ROW()-37))="0",INDIRECT("'"&D$6&"'!"&D$4&ROW()-37)="",NOT(ISNUMBER(INDIRECT("'"&D$6&"'!"&D$4&ROW()-37)))),"-",INDIRECT("'"&D$6&"'!"&D$4&ROW()-37))} -> - | E121: {=IF(OR(TRIM(INDIRECT("'"&E$6&"'!"&E$4&ROW()-37))="0",INDIRECT("'"&E$6&"'!"&E$4&ROW()-37)="",NOT(ISNUMBER(INDIRECT("'"&E$6&"'!"&E$4&ROW()-37)))),"-",INDIRECT("'"&E$6&"'!"&E$4&ROW()-37))} -> - | F121: {=IF(OR(TRIM(INDIRECT("'"&F$6&"'!"&F$4&ROW()-37))="0",INDIRECT("'"&F$6&"'!"&F$4&ROW()-37)="",NOT(ISNUMBER(INDIRECT("'"&F$6&"'!"&F$4&ROW()-37)))),"-",INDIRECT("'"&F$6&"'!"&F$4&ROW()-37))} -> - | G121: {=IF(OR(TRIM(INDIRECT("'"&G$6&"'!"&G$4&ROW()-37))="0",INDIRECT("'"&G$6&"'!"&G$4&ROW()-37)="",NOT(ISNUMBER(INDIRECT("'"&G$6&"'!"&G$4&ROW()-37)))),"-",INDIRECT("'"&G$6&"'!"&G$4&ROW()-37))} -> - | H121: {=IF(OR(TRIM(INDIRECT("'"&H$6&"'!"&H$4&ROW()-37))="0",INDIRECT("'"&H$6&"'!"&H$4&ROW()-37)="",NOT(ISNUMBER(INDIRECT("'"&H$6&"'!"&H$4&ROW()-37)))),"-",INDIRECT("'"&H$6&"'!"&H$4&ROW()-37))} -> - | I121: {=IF(OR(TRIM(INDIRECT("'"&I$6&"'!"&I$4&ROW()-37))="0",INDIRECT("'"&I$6&"'!"&I$4&ROW()-37)="",NOT(ISNUMBER(INDIRECT("'"&I$6&"'!"&I$4&ROW()-37)))),"-",INDIRECT("'"&I$6&"'!"&I$4&ROW()-37))} -> - | ... M121: {=IF(OR(TRIM(INDIRECT("'"&M$6&"'!"&M$4&ROW()-37))="0",INDIRECT("'"&M$6&"'!"&M$4&ROW()-37)="",NOT(ISNUMBER(INDIRECT("'"&M$6&"'!"&M$4&ROW()-37)))),"-",INDIRECT("'"&M$6&"'!"&M$4&ROW()-37))} -> - | N121: 0 | O121: =N121/COLUMNS(B121:M121) -> 0
A122: ='Section-Category'!A76 -> Lab Test | B122: {=IF(OR(TRIM(INDIRECT("'"&B$6&"'!"&B$4&ROW()-37))="0",INDIRECT("'"&B$6&"'!"&B$4&ROW()-37)="",NOT(ISNUMBER(INDIRECT("'"&B$6&"'!"&B$4&ROW()-37)))),"-",INDIRECT("'"&B$6&"'!"&B$4&ROW()-37))} -> - | C122: {=IF(OR(TRIM(INDIRECT("'"&C$6&"'!"&C$4&ROW()-37))="0",INDIRECT("'"&C$6&"'!"&C$4&ROW()-37)="",NOT(ISNUMBER(INDIRECT("'"&C$6&"'!"&C$4&ROW()-37)))),"-",INDIRECT("'"&C$6&"'!"&C$4&ROW()-37))} -> - | D122: {=IF(OR(TRIM(INDIRECT("'"&D$6&"'!"&D$4&ROW()-37))="0",INDIRECT("'"&D$6&"'!"&D$4&ROW()-37)="",NOT(ISNUMBER(INDIRECT("'"&D$6&"'!"&D$4&ROW()-37)))),"-",INDIRECT("'"&D$6&"'!"&D$4&ROW()-37))} -> - | E122: {=IF(OR(TRIM(INDIRECT("'"&E$6&"'!"&E$4&ROW()-37))="0",INDIRECT("'"&E$6&"'!"&E$4&ROW()-37)="",NOT(ISNUMBER(INDIRECT("'"&E$6&"'!"&E$4&ROW()-37)))),"-",INDIRECT("'"&E$6&"'!"&E$4&ROW()-37))} -> - | F122: {=IF(OR(TRIM(INDIRECT("'"&F$6&"'!"&F$4&ROW()-37))="0",INDIRECT("'"&F$6&"'!"&F$4&ROW()-37)="",NOT(ISNUMBER(INDIRECT("'"&F$6&"'!"&F$4&ROW()-37)))),"-",INDIRECT("'"&F$6&"'!"&F$4&ROW()-37))} -> - | G122: {=IF(OR(TRIM(INDIRECT("'"&G$6&"'!"&G$4&ROW()-37))="0",INDIRECT("'"&G$6&"'!"&G$4&ROW()-37)="",NOT(ISNUMBER(INDIRECT("'"&G$6&"'!"&G$4&ROW()-37)))),"-",INDIRECT("'"&G$6&"'!"&G$4&ROW()-37))} -> - | H122: {=IF(OR(TRIM(INDIRECT("'"&H$6&"'!"&H$4&ROW()-37))="0",INDIRECT("'"&H$6&"'!"&H$4&ROW()-37)="",NOT(ISNUMBER(INDIRECT("'"&H$6&"'!"&H$4&ROW()-37)))),"-",INDIRECT("'"&H$6&"'!"&H$4&ROW()-37))} -> - | I122: {=IF(OR(TRIM(INDIRECT("'"&I$6&"'!"&I$4&ROW()-37))="0",INDIRECT("'"&I$6&"'!"&I$4&ROW()-37)="",NOT(ISNUMBER(INDIRECT("'"&I$6&"'!"&I$4&ROW()-37)))),"-",INDIRECT("'"&I$6&"'!"&I$4&ROW()-37))} -> - | ... M122: {=IF(OR(TRIM(INDIRECT("'"&M$6&"'!"&M$4&ROW()-37))="0",INDIRECT("'"&M$6&"'!"&M$4&ROW()-37)="",NOT(ISNUMBER(INDIRECT("'"&M$6&"'!"&M$4&ROW()-37)))),"-",INDIRECT("'"&M$6&"'!"&M$4&ROW()-37))} -> - | N122: 0 | O122: =N122/COLUMNS(B122:M122) -> 0
...

Sheet Jan
A1: =MID(CELL("filename",A1),FIND("]",CELL("filename",A1))+1,255) -> Jan | B1: =Budget!D1 -> 2026
A2: Summary/Date | B2: ='Section-Category'!D6 -> 46023 | C2: ='Section-Category'!E6 -> 46024 | D2: ='Section-Category'!F6 -> 46025 | E2: ='Section-Category'!G6 -> 46026 | F2: ='Section-Category'!H6 -> 46027 | G2: ='Section-Category'!I6 -> 46028 | H2: ='Section-Category'!J6 -> 46029 | I2: ='Section-Category'!K6 -> 46030 | ... AF2: ='Section-Category'!AH6 -> 46053 | AG2: Total Sum
A4: INCOME | AG4: Total
A5: Wages & Tips | AG5: =SUM(B5:AF5) -> 0
A6: Interest Income | AG6: =SUM(B6:AF6) -> 0
A7: Dividends | AG7: =SUM(B7:AF7) -> 0
A8: Gifts Received | AG8: =SUM(B8:AF8) -> 0
A9: Refunds/Reimbursements | AG9: =SUM(B9:AF9) -> 0
A10: Other | AG10: =SUM(B10:AF10) -> 0
A11: Transfer From Savings | AG11: =SUM(B11:AF11) -> 0
A12: ='Section-Category'!A9 -> Total INCOME | B12: =SUM(B5:B11) -> 0 | C12: =SUM(C5:C11) -> 0 | D12: =SUM(D5:D11) -> 0 | E12: =SUM(E5:E11) -> 0 | F12: =SUM(F5:F11) -> 0 | G12: =SUM(G5:G11) -> 0 | H12: =SUM(H5:H11) -> 0 | I12: =SUM(I5:I11) -> 0 | ... AD12: =SUM(AD5:AD11) -> 0 | AF12: =SUM(AF5:AF11) -> 0 | AG12: =SUM(AG5:AG11) -> 0
A14: ='Section-Category'!A82 -> Petty Cash Used | AG14: Total
A15: ='Section-Category'!A83 -> Pocket Money Wife | AG15: =SUM(B15:AF15) -> 0
A16: ='Section-Category'!A84 -> Car Repair / Workshop | AG16: =SUM(B16:AF16) -> 0
A17: ='Section-Category'!A85 -> Food | AG17: =SUM(B17:AF17) -> 0
A18: ='Section-Category'!A86 -> Donation | AG18: =SUM(B18:AF18) -> 0
A19: Eidi | AG19: =SUM(B19:AF19) -> 0
A20: ='Section-Category'!A88 -> Donation | AG20: =SUM(B20:AF20) -> 0
A21: ='Section-Category'!A89 -> Pocket Money Husband | AG21: =SUM(B21:AF21) -> 0
A22: ='Section-Category'!A90 -> Other | AG22: =SUM(B22:AF22) -> 0
A23: ='Section-Category'!A91 -> Total Petty Cash Used | B23: =SUM(B15:B22) -> 0 | C23: =SUM(C15:C22) -> 0 | D23: =SUM(D15:D22) -> 0 | E23: =SUM(E15:E22) -> 0 | F23: =SUM(F15:F22) -> 0 | G23: =SUM(G15:G22) -> 0 | H23: =SUM(H15:H22) -> 0 | I23: =SUM(I15:I22) -> 0 | ... AD23: =SUM(AD15:AD22) -> 0 | AF23: =SUM(AF15:AF22) -> 0 | AG23: =SUM(AG15:AG22) -> 0
A25: ='Section-Category'!A11 -> SAVINGS EXPENSE | AG25: Total
A26: ='Section-Category'!A12 -> Emergency Fund | AG26: =SUM(B26:AF26) -> 0
A27: ='Section-Category'!A13 -> Investments | AG27: =SUM(B27:AF27) -> 0
A28: ='Section-Category'!A14 -> Pocket Money Wife | AG28: =SUM(B28:AF28) -> 0
A29: ='Section-Category'!A15 -> <Name-Of-Entry> | AG29: =SUM(B29:AF29) -> 0
A30: ='Section-Category'!A16 -> <Name-Of-Entry> | AG30: =SUM(B30:AF30) -> 0
A31: ='Section-Category'!A17 -> Total SAVINGS EXPENSE | B31: =SUM(B26:B30) -> 0 | C31: =SUM(C26:C30) -> 0 | D31: =SUM(D26:D30) -> 0 | E31: =SUM(E26:E30) -> 0 | F31: =SUM(F26:F30) -> 0 | G31: =SUM(G26:G30) -> 0 | H31: =SUM(H26:H30) -> 0 | I31: =SUM(I26:I30) -> 0 | ... AD31: =SUM(AD26:AD30) -> 0 | AF31: =SUM(AF26:AF30) -> 0 | AG31: =SUM(AG26:AG30) -> 0
A33: ='Section-Category'!A20 -> HOME EXPENSES | AG33: Total
A34: ='Section-Category'!A21 -> Mortgage/Rent | AG34: =SUM(B34:AF34) -> 0
A35: ='Section-Category'!A22 -> Electricity | AG35: =SUM(B35:AF35) -> 0
A36: ='Section-Category'!A23 -> Gas/Oil | AG36: =SUM(B36:AF36) -> 0
A37: ='Section-Category'!A24 -> Water/Sewer/Trash | AG37: =SUM(B37:AF37) -> 0
A38: ='Section-Category'!A25 -> Phone | AG38: =SUM(B38:AF38) -> 0
A39: ='Section-Category'!A26 -> Cable/Satellite | AG39: =SUM(B39:AF39) -> 0
A40: ='Section-Category'!A27 -> Internet | AG40: =SUM(B40:AF40) -> 0
A41: ='Section-Category'!A28 -> Furnishings/Appliances | AG41: =SUM(B41:AF41) -> 0
A42: ='Section-Category'!A29 -> Lawn/Garden | AG42: =SUM(B42:AF42) -> 0
A43: ='Section-Category'!A30 -> Home Supplies | AG43: =SUM(B43:AF43) -> 0
A44: ='Section-Category'!A31 -> Maintenance | AG44: =SUM(B44:AF44) -> 0
A45: ='Section-Category'!A32 -> Improvements | AG45: =SUM(B45:AF45) -> 0
A46: ='Section-Category'!A33 -> Other | AG46: =SUM(B46:AF46) -> 0
A47: ='Section-Category'!A34 -> Total HOME EXPENSES | B47: =SUM(B34:B46) -> 0 | C47: =SUM(C34:C46) -> 0 | D47: =SUM(D34:D46) -> 0 | E47: =SUM(E34:E46) -> 0 | F47: =SUM(F34:F46) -> 0 | G47: =SUM(G34:G46) -> 0 | H47: =SUM(H34:H46) -> 0 | I47: =SUM(I34:I46) -> 0 | ... AD47: =SUM(AD34:AD46) -> 0 | AF47: =SUM(AF34:AF46) -> 0 | AG47: =SUM(AG34:AG46) -> 0
A49: ='Section-Category'!A37 -> DAILY LIVING | AG49: Total
A50: ='Section-Category'!A38 -> Groceries | AG50: =SUM(B50:AF50) -> 0
A51: ='Section-Category'!A39 -> Personal Supplies | AG51: =SUM(B51:AF51) -> 0
A52: ='Section-Category'!A40 -> Clothing | AG52: =SUM(B52:AF52) -> 0
A53: ='Section-Category'!A41 -> Cleaning Services | AG53: =SUM(B53:AF53) -> 0
A54: ='Section-Category'!A42 -> Dining/Eating Out | AG54: =SUM(B54:AF54) -> 0
A55: ='Section-Category'!A43 -> Dry Cleaning | AG55: =SUM(B55:AF55) -> 0
A56: ='Section-Category'!A44 -> Salon/Barber | AG56: =SUM(B56:AF56) -> 0
A57: ='Section-Category'!A45 -> FoodPanda | AG57: =SUM(B57:AF57) -> 0
A58: ='Section-Category'!A46 -> JazzCash/EasyPaisa | AG58: =SUM(B58:AF58) -> 0
A59: ='Section-Category'!A47 -> Other | AG59: =SUM(B59:AF59) -> 0
A60: ='Section-Category'!A48 -> Total DAILY LIVING | B60: =SUM(B50:B59) -> 0 | C60: =SUM(C50:C59) -> 0 | D60: =SUM(D50:D59) -> 0 | E60: =SUM(E50:E59) -> 0 | F60: =SUM(F50:F59) -> 0 | G60: =SUM(G50:G59) -> 0 | H60: =SUM(H50:H59) -> 0 | I60: =SUM(I50:I59) -> 0 | ... AD60: =SUM(AD50:AD59) -> 0 | AF60: =SUM(AF50:AF59) -> 0 | AG60: =SUM(AG50:AG59) -> 0
A62: ='Section-Category'!A51 -> CHILDREN | AG62: Total
A63: ='Section-Category'!A52 -> Medical | AG63: =SUM(B63:AF63) -> 0
A64: ='Section-Category'!A53 -> Clothing | AG64: =SUM(B64:AF64) -> 0
A65: ='Section-Category'!A54 -> School Tuition | AG65: =SUM(B65:AF65) -> 0
A66: ='Section-Category'!A55 -> School Lunch | AG66: =SUM(B66:AF66) -> 0
A67: ='Section-Category'!A56 -> School Supplies | AG67: =SUM(B67:AF67) -> 0
A68: ='Section-Category'!A57 -> Babysitting | AG68: =SUM(B68:AF68) -> 0
A69: ='Section-Category'!A58 -> Toys/Games | AG69: =SUM(B69:AF69) -> 0
A70: ='Section-Category'!A59 -> Other | AG70: =SUM(B70:AF70) -> 0
A71: ='Section-Category'!A60 -> Total CHILDREN | B71: =SUM(B63:B70) -> 0 | C71: =SUM(C63:C70) -> 0 | D71: =SUM(D63:D70) -> 0 | E71: =SUM(E63:E70) -> 0 | F71: =SUM(F63:F70) -> 0 | G71: =SUM(G63:G70) -> 0 | H71: =SUM(H63:H70) -> 0 | I71: =SUM(I63:I70) -> 0 | ... AD71: =SUM(AD63:AD70) -> 0 | AF71: =SUM(AF63:AF70) -> 0 | AG71: =SUM(AG63:AG70) -> 0
A73: ='Section-Category'!A63 -> TRANSPORTATION | AG73: Total
A74: ='Section-Category'!A64 -> Vehicle Payments | AG74: =SUM(B74:AF74) -> 0
A75: ='Section-Category'!A65 -> Fuel | AG75: =SUM(B75:AF75) -> 0
A76: ='Section-Category'!A66 -> Bus/Taxi/Train Fare | AG76: =SUM(B76:AF76) -> 0
A77: ='Section-Category'!A67 -> Repairs | AG77: =SUM(B77:AF77) -> 0
A78: ='Section-Category'!A68 -> Registration/License | AG78: =SUM(B78:AF78) -> 0
A79: ='Section-Category'!A69 -> Other | AG79: =SUM(B79:AF79) -> 0
A80: ='Section-Category'!A70 -> Total TRANSPORTATION | B80: =SUM(B74:B79) -> 0 | C80: =SUM(C74:C79) -> 0 | D80: =SUM(D74:D79) -> 0 | E80: =SUM(E74:E79) -> 0 | F80: =SUM(F74:F79) -> 0 | G80: =SUM(G74:G79) -> 0 | H80: =SUM(H74:H79) -> 0 | I80: =SUM(I74:I79) -> 0 | ... AD80: =SUM(AD74:AD79) -> 0 | AF80: =SUM(AF74:AF79) -> 0 | AG80: =SUM(AG74:AG79) -> 0
A82: ='Section-Category'!A73 -> HEALTH | AG82: Total
A83: ='Section-Category'!A74 -> Doctor/Dentist | AG83: =SUM(B83:AF83) -> 0
A84: ='Section-Category'!A75 -> Medicine/Drugs | AG84: =SUM(B84:AF84) -> 0
A85: ='Section-Category'!A76 -> Lab Test | AG85: =SUM(B85:AF85) -> 0
A86: ='Section-Category'!A77 -> Consultation | AG86: =SUM(B86:AF86) -> 0
A87: ='Section-Category'!A78 -> Other | AG87: =SUM(B87:AF87) -> 0
A88: ='Section-Category'!A79 -> Total HEALTH | B88: =SUM(B83:B87) -> 0 | C88: =SUM(C83:C87) -> 0 | D88: =SUM(D83:D87) -> 0 | E88: =SUM(E83:E87) -> 0 | F88: =SUM(F83:F87) -> 0 | G88: =SUM(G83:G87) -> 0 | H88: =SUM(H83:H87) -> 0 | I88: =SUM(I83:I87) -> 0 | ... AD88: =SUM(AD83:AD87) -> 0 | AF88: =SUM(AF83:AF87) -> 0 | AG88: =SUM(AG83:AG87) -> 0
A90: ='Section-Category'!A94 -> EDUCATION | AG90: Total
A91: ='Section-Category'!A95 -> Tuition | AG91: =SUM(B91:AF91) -> 0
A92: ='Section-Category'!A96 -> Books | AG92: =SUM(B92:AF92) -> 0
A93: ='Section-Category'!A97 -> Music Lessons | AG93: =SUM(B93:AF93) -> 0
A94: ='Section-Category'!A98 -> Other | AG94: =SUM(B94:AF94) -> 0
A95: ='Section-Category'!A99 -> Total EDUCATION | B95: =SUM(B91:B94) -> 0 | C95: =SUM(C91:C94) -> 0 | D95: =SUM(D91:D94) -> 0 | E95: =SUM(E91:E94) -> 0 | F95: =SUM(F91:F94) -> 0 | G95: =SUM(G91:G94) -> 0 | H95: =SUM(H91:H94) -> 0 | I95: =SUM(I91:I94) -> 0 | ... AD95: =SUM(AD91:AD94) -> 0 | AF95: =SUM(AF91:AF94) -> 0 | AG95: =SUM(AG91:AG94) -> 0
A97: ='Section-Category'!A102 -> CHARITY/GIFTS | AG97: Total
A98: ='Section-Category'!A103 -> Gifts Given | AG98: =SUM(B98:AF98) -> 0
A99: ='Section-Category'!A104 -> Couple Charity | AG99: =SUM(B99:AF99) -> 0
A100: ='Section-Category'!A105 -> Mother Charity | AG100: =SUM(B100:AF100) -> 0
A101: ='Section-Category'!A106 -> Other | AG101: =SUM(B101:AF101) -> 0
A102: ='Section-Category'!A107 -> Total CHARITY/GIFTS | B102: =SUM(B98:B101) -> 0 | C102: =SUM(C98:C101) -> 0 | D102: =SUM(D98:D101) -> 0 | E102: =SUM(E98:E101) -> 0 | F102: =SUM(F98:F101) -> 0 | G102: =SUM(G98:G101) -> 0 | H102: =SUM(H98:H101) -> 0 | I102: =SUM(I98:I101) -> 0 | ... AD102: =SUM(AD98:AD101) -> 0 | AF102: =SUM(AF98:AF101) -> 0 | AG102: =SUM(AG98:AG101) -> 0
A104: ='Section-Category'!A110 -> OBLIGATIONS | AG104: Total
A105: ='Section-Category'!A111 -> Credit Card Debt | AG105: =SUM(B105:AF105) -> 0
A106: ='Section-Category'!A112 -> Punjab ST on CC Fee @16 | AG106: =SUM(B106:AF106) -> 0
A107: ='Section-Category'!A113 -> Advance Tax 5% | AG107: =SUM(B107:AF107) -> 0
A108: ='Section-Category'!A114 -> Other | AG108: =SUM(B108:AF108) -> 0
A109: ='Section-Category'!A115 -> Total OBLIGATIONS | B109: =SUM(B105:B108) -> 0 | C109: =SUM(C105:C108) -> 0 | D109: =SUM(D105:D108) -> 0 | E109: =SUM(E105:E108) -> 0 | F109: =SUM(F105:F108) -> 0 | G109: =SUM(G105:G108) -> 0 | H109: =SUM(H105:H108) -> 0 | I109: =SUM(I105:I108) -> 0 | ... AD109: =SUM(AD105:AD108) -> 0 | AF109: =SUM(AF105:AF108) -> 0 | AG109: =SUM(AG105:AG108) -> 0
A111: ='Section-Category'!A118 -> 0
A112: ='Section-Category'!A119 -> <Name-Of-Entry>
...

Sheet Feb
A1: =MID(CELL("filename",A1),FIND("]",CELL("filename",A1))+1,255) -> Feb | B1: =Budget!D1 -> 2026
A2: Summary/Date | B2: ='Section-Category'!D7 -> 46054 | C2: ='Section-Category'!E7 -> 46055 | D2: ='Section-Category'!F7 -> 46056 | E2: ='Section-Category'!G7 -> 46057 | F2: ='Section-Category'!H7 -> 46058 | G2: ='Section-Category'!I7 -> 46059 | H2: ='Section-Category'!J7 -> 46060 | I2: ='Section-Category'!K7 -> 46061 | ... AE2: ='Section-Category'!AG7 -> # | AF2: Total Sum
A4: INCOME | AF4: Total
A5: Wages & Tips | AF5: =SUM(B5:AC5) -> 0
A6: Interest Income | AF6: =SUM(B6:AC6) -> 0
A7: Dividends | AF7: =SUM(B7:AC7) -> 0
A8: Gifts Received | AF8: =SUM(B8:AC8) -> 0
A9: Refunds/Reimbursements | AF9: =SUM(B9:AC9) -> 0
A10: Other | AF10: =SUM(B10:AC10) -> 0
A11: Transfer From Savings | AF11: =SUM(B11:AC11) -> 0
A12: ='Section-Category'!A9 -> Total INCOME | B12: =SUM(B5:B11) -> 0 | C12: =SUM(C5:C11) -> 0 | D12: =SUM(D5:D11) -> 0 | E12: =SUM(E5:E11) -> 0 | F12: =SUM(F5:F11) -> 0 | G12: =SUM(G5:G11) -> 0 | H12: =SUM(H5:H11) -> 0 | I12: =SUM(I5:I11) -> 0 | ... AC12: =SUM(AC5:AC11) -> 0 | AF12: =SUM(AF5:AF11) -> 0
A14: ='Section-Category'!A82 -> Petty Cash Used | AF14: Total
A15: ='Section-Category'!A83 -> Pocket Money Wife | AF15: =SUM(B15:AC15) -> 0
A16: ='Section-Category'!A84 -> Car Repair / Workshop | AF16: =SUM(B16:AC16) -> 0
A17: ='Section-Category'!A85 -> Food | AF17: =SUM(B17:AC17) -> 0
A18: ='Section-Category'!A86 -> Donation | AF18: =SUM(B18:AC18) -> 0
A19: Eidi | AF19: =SUM(B19:AC19) -> 0
A20: ='Section-Category'!A88 -> Donation | AF20: =SUM(B20:AC20) -> 0
A21: ='Section-Category'!A89 -> Pocket Money Husband | AF21: =SUM(B21:AC21) -> 0
A22: ='Section-Category'!A90 -> Other | AF22: =SUM(B22:AC22) -> 0
A23: ='Section-Category'!A91 -> Total Petty Cash Used | B23: =SUM(B15:B22) -> 0 | C23: =SUM(C15:C22) -> 0 | D23: =SUM(D15:D22) -> 0 | E23: =SUM(E15:E22) -> 0 | F23: =SUM(F15:F22) -> 0 | G23: =SUM(G15:G22) -> 0 | H23: =SUM(H15:H22) -> 0 | I23: =SUM(I15:I22) -> 0 | ... AC23: =SUM(AC15:AC22) -> 0 | AF23: =SUM(AF15:AF22) -> 0
A25: ='Section-Category'!A11 -> SAVINGS EXPENSE | AF25: Total
A26: ='Section-Category'!A12 -> Emergency Fund | AF26: =SUM(B26:AC26) -> 0
A27: ='Section-Category'!A13 -> Investments | AF27: =SUM(B27:AC27) -> 0
A28: ='Section-Category'!A14 -> Pocket Money Wife | AF28: =SUM(B28:AC28) -> 0
A29: ='Section-Category'!A15 -> <Name-Of-Entry> | AF29: =SUM(B29:AC29) -> 0
A30: ='Section-Category'!A16 -> <Name-Of-Entry> | AF30: =SUM(B30:AC30) -> 0
A31: ='Section-Category'!A17 -> Total SAVINGS EXPENSE | B31: =SUM(B26:B30) -> 0 | C31: =SUM(C26:C30) -> 0 | D31: =SUM(D26:D30) -> 0 | E31: =SUM(E26:E30) -> 0 | F31: =SUM(F26:F30) -> 0 | G31: =SUM(G26:G30) -> 0 | H31: =SUM(H26:H30) -> 0 | I31: =SUM(I26:I30) -> 0 | ... AC31: =SUM(AC26:AC30) -> 0 | AF31: =SUM(AF26:AF30) -> 0
A33: ='Section-Category'!A20 -> HOME EXPENSES | AF33: Total
A34: ='Section-Category'!A21 -> Mortgage/Rent | AF34: =SUM(B34:AC34) -> 0
A35: ='Section-Category'!A22 -> Electricity | AF35: =SUM(B35:AC35) -> 0
A36: ='Section-Category'!A23 -> Gas/Oil | AF36: =SUM(B36:AC36) -> 0
A37: ='Section-Category'!A24 -> Water/Sewer/Trash | AF37: =SUM(B37:AC37) -> 0
A38: ='Section-Category'!A25 -> Phone | AF38: =SUM(B38:AC38) -> 0
A39: ='Section-Category'!A26 -> Cable/Satellite | AF39: =SUM(B39:AC39) -> 0
A40: ='Section-Category'!A27 -> Internet | AF40: =SUM(B40:AC40) -> 0
A41: ='Section-Category'!A28 -> Furnishings/Appliances | AF41: =SUM(B41:AC41) -> 0
A42: ='Section-Category'!A29 -> Lawn/Garden | AF42: =SUM(B42:AC42) -> 0
A43: ='Section-Category'!A30 -> Home Supplies | AF43: =SUM(B43:AC43) -> 0
A44: ='Section-Category'!A31 -> Maintenance | AF44: =SUM(B44:AC44) -> 0
A45: ='Section-Category'!A32 -> Improvements | AF45: =SUM(B45:AC45) -> 0
A46: ='Section-Category'!A33 -> Other | AF46: =SUM(B46:AC46) -> 0
A47: ='Section-Category'!A34 -> Total HOME EXPENSES | B47: =SUM(B34:B46) -> 0 | C47: =SUM(C34:C46) -> 0 | D47: =SUM(D34:D46) -> 0 | E47: =SUM(E34:E46) -> 0 | F47: =SUM(F34:F46) -> 0 | G47: =SUM(G34:G46) -> 0 | H47: =SUM(H34:H46) -> 0 | I47: =SUM(I34:I46) -> 0 | ... AC47: =SUM(AC34:AC46) -> 0 | AF47: =SUM(AF34:AF46) -> 0
A49: ='Section-Category'!A37 -> DAILY LIVING | AF49: Total
A50: ='Section-Category'!A38 -> Groceries | AF50: =SUM(B50:AC50) -> 0
A51: ='Section-Category'!A39 -> Personal Supplies | AF51: =SUM(B51:AC51) -> 0
A52: ='Section-Category'!A40 -> Clothing | AF52: =SUM(B52:AC52) -> 0
A53: ='Section-Category'!A41 -> Cleaning Services | AF53: =SUM(B53:AC53) -> 0
A54: ='Section-Category'!A42 -> Dining/Eating Out | AF54: =SUM(B54:AC54) -> 0
A55: ='Section-Category'!A43 -> Dry Cleaning | AF55: =SUM(B55:AC55) -> 0
A56: ='Section-Category'!A44 -> Salon/Barber | AF56: =SUM(B56:AC56) -> 0
A57: ='Section-Category'!A45 -> FoodPanda | AF57: =SUM(B57:AC57) -> 0
A58: ='Section-Category'!A46 -> JazzCash/EasyPaisa | AF58: =SUM(B58:AC58) -> 0
A59: ='Section-Category'!A47 -> Other | AF59: =SUM(B59:AC59) -> 0
A60: ='Section-Category'!A48 -> Total DAILY LIVING | B60: =SUM(B50:B59) -> 0 | C60: =SUM(C50:C59) -> 0 | D60: =SUM(D50:D59) -> 0 | E60: =SUM(E50:E59) -> 0 | F60: =SUM(F50:F59) -> 0 | G60: =SUM(G50:G59) -> 0 | H60: =SUM(H50:H59) -> 0 | I60: =SUM(I50:I59) -> 0 | ... AC60: =SUM(AC50:AC59) -> 0 | AF60: =SUM(AF50:AF59) -> 0
A62: ='Section-Category'!A51 -> CHILDREN | AF62: Total
A63: ='Section-Category'!A52 -> Medical | AF63: =SUM(B63:AC63) -> 0
A64: ='Section-Category'!A53 -> Clothing | AF64: =SUM(B64:AC64) -> 0
A65: ='Section-Category'!A54 -> School Tuition | AF65: =SUM(B65:AC65) -> 0
A66: ='Section-Category'!A55 -> School Lunch | AF66: =SUM(B66:AC66) -> 0
A67: ='Section-Category'!A56 -> School Supplies | AF67: =SUM(B67:AC67) -> 0
A68: ='Section-Category'!A57 -> Babysitting | AF68: =SUM(B68:AC68) -> 0
A69: ='Section-Category'!A58 -> Toys/Games | AF69: =SUM(B69:AC69) -> 0
A70: ='Section-Category'!A59 -> Other | AF70: =SUM(B70:AC70) -> 0
A71: ='Section-Category'!A60 -> Total CHILDREN | B71: =SUM(B63:B70) -> 0 | C71: =SUM(C63:C70) -> 0 | D71: =SUM(D63:D70) -> 0 | E71: =SUM(E63:E70) -> 0 | F71: =SUM(F63:F70) -> 0 | G71: =SUM(G63:G70) -> 0 | H71: =SUM(H63:H70) -> 0 | I71: =SUM(I63:I70) -> 0 | ... AC71: =SUM(AC63:AC70) -> 0 | AF71: =SUM(AF63:AF70) -> 0
A73: ='Section-Category'!A63 -> TRANSPORTATION | AF73: Total
A74: ='Section-Category'!A64 -> Vehicle Payments | AF74: =SUM(B74:AC74) -> 0
A75: ='Section-Category'!A65 -> Fuel | AF75: =SUM(B75:AC75) -> 0
A76: ='Section-Category'!A66 -> Bus/Taxi/Train Fare | AF76: =SUM(B76:AC76) -> 0
A77: ='Section-Category'!A67 -> Repairs | AF77: =SUM(B77:AC77) -> 0
A78: ='Section-Category'!A68 -> Registration/License | AF78: =SUM(B78:AC78) -> 0
A79: ='Section-Category'!A69 -> Other | AF79: =SUM(B79:AC79) -> 0
A80: ='Section-Category'!A70 -> Total TRANSPORTATION | B80: =SUM(B74:B79) -> 0 | C80: =SUM(C74:C79) -> 0 | D80: =SUM(D74:D79) -> 0 | E80: =SUM(E74:E79) -> 0 | F80: =SUM(F74:F79) -> 0 | G80: =SUM(G74:G79) -> 0 | H80: =SUM(H74:H79) -> 0 | I80: =SUM(I74:I79) -> 0 | ... AC80: =SUM(AC74:AC79) -> 0 | AF80: =SUM(AF74:AF79) -> 0
A82: ='Section-Category'!A73 -> HEALTH | AF82: Total
A83: ='Section-Category'!A74 -> Doctor/Dentist | AF83: =SUM(B83:AC83) -> 0
A84: ='Section-Category'!A75 -> Medicine/Drugs | AF84: =SUM(B84:AC84) -> 0
A85: ='Section-Category'!A76 -> Lab Test | AF85: =SUM(B85:AC85) -> 0
A86: ='Section-Category'!A77 -> Consultation | AF86: =SUM(B86:AC86) -> 0
A87: ='Section-Category'!A78 -> Other | AF87: =SUM(B87:AC87) -> 0
A88: ='Section-Category'!A79 -> Total HEALTH | B88: =SUM(B83:B87) -> 0 | C88: =SUM(C83:C87) -> 0 | D88: =SUM(D83:D87) -> 0 | E88: =SUM(E83:E87) -> 0 | F88: =SUM(F83:F87) -> 0 | G88: =SUM(G83:G87) -> 0 | H88: =SUM(H83:H87) -> 0 | I88: =SUM(I83:I87) -> 0 | ... AC88: =SUM(AC83:AC87) -> 0 | AF88: =SUM(AF83:AF87) -> 0
A90: ='Section-Category'!A94 -> EDUCATION | AF90: Total
A91: ='Section-Category'!A95 -> Tuition | AF91: =SUM(B91:AC91) -> 0
A92: ='Section-Category'!A96 -> Books | AF92: =SUM(B92:AC92) -> 0
A93: ='Section-Category'!A97 -> Music Lessons | AF93: =SUM(B93:AC93) -> 0
A94: ='Section-Category'!A98 -> Other | AF94: =SUM(B94:AC94) -> 0
A95: ='Section-Category'!A99 -> Total EDUCATION | B95: =SUM(B91:B94) -> 0 | C95: =SUM(C91:C94) -> 0 | D95: =SUM(D91:D94) -> 0 | E95: =SUM(E91:E94) -> 0 | F95: =SUM(F91:F94) -> 0 | G95: =SUM(G91:G94) -> 0 | H95: =SUM(H91:H94) -> 0 | I95: =SUM(I91:I94) -> 0 | ... AC95: =SUM(AC91:AC94) -> 0 | AF95: =SUM(AF91:AF94) -> 0
A97: ='Section-Category'!A102 -> CHARITY/GIFTS | AF97: Total
A98: ='Section-Category'!A103 -> Gifts Given | AF98: =SUM(B98:AC98) -> 0
A99: ='Section-Category'!A104 -> Couple Charity | AF99: =SUM(B99:AC99) -> 0
A100: ='Section-Category'!A105 -> Mother Charity | AF100: =SUM(B100:AC100) -> 0
A101: ='Section-Category'!A106 -> Other | AF101: =SUM(B101:AC101) -> 0
A102: ='Section-Category'!A107 -> Total CHARITY/GIFTS | B102: =SUM(B98:B101) -> 0 | C102: =SUM(C98:C101) -> 0 | D102: =SUM(D98:D101) -> 0 | E102: =SUM(E98:E101) -> 0 | F102: =SUM(F98:F101) -> 0 | G102: =SUM(G98:G101) -> 0 | H102: =SUM(H98:H101) -> 0 | I102: =SUM(I98:I101) -> 0 | ... AC102: =SUM(AC98:AC101) -> 0 | AF102: =SUM(AF98:AF101) -> 0
A104: ='Section-Category'!A110 -> OBLIGATIONS | AF104: Total
A105: ='Section-Category'!A111 -> Credit Card Debt | AF105: =SUM(B105:AC105) -> 0
A106: ='Section-Category'!A112 -> Punjab ST on CC Fee @16 | AF106: =SUM(B106:AC106) -> 0
A107: ='Section-Category'!A113 -> Advance Tax 5% | AF107: =SUM(B107:AC107) -> 0
A108: ='Section-Category'!A114 -> Other | AF108: =SUM(B108:AC108) -> 0
A109: ='Section-Category'!A115 -> Total OBLIGATIONS | B109: =SUM(B105:B108) -> 0 | C109: =SUM(C105:C108) -> 0 | D109: =SUM(D105:D108) -> 0 | E109: =SUM(E105:E108) -> 0 | F109: =SUM(F105:F108) -> 0 | G109: =SUM(G105:G108) -> 0 | H109: =SUM(H105:H108) -> 0 | I109: =SUM(I105:I108) -> 0 | ... AC109: =SUM(AC105:AC108) -> 0 | AF109: =SUM(AF105:AF108) -> 0
A111: ='Section-Category'!A118 -> 0
A112: ='Section-Category'!A119 -> <Name-Of-Entry>
...

Sheet Mar
A1: =MID(CELL("filename",A1),FIND("]",CELL("filename",A1))+1,255) -> Mar | B1: =Budget!D1 -> 2026
A2: Summary/Date | B2: ='Section-Category'!D8 -> 46082 | C2: ='Section-Category'!E8 -> 46083 | D2: ='Section-Category'!F8 -> 46084 | E2: ='Section-Category'!G8 -> 46085 | F2: ='Section-Category'!H8 -> 46086 | G2: ='Section-Category'!I8 -> 46087 | H2: ='Section-Category'!J8 -> 46088 | I2: ='Section-Category'!K8 -> 46089 | ... AF2: ='Section-Category'!AH8 -> 46112 | AG2: Total Sum
A4: INCOME | AG4: Total
A5: Wages & Tips | AG5: =SUM(B5:AF5) -> 0
A6: Interest Income | AG6: =SUM(B6:AF6) -> 0
A7: Dividends | AG7: =SUM(B7:AF7) -> 0
A8: Gifts Received | AG8: =SUM(B8:AF8) -> 0
A9: Refunds/Reimbursements | AG9: =SUM(B9:AF9) -> 0
A10: Other | AG10: =SUM(B10:AF10) -> 0
A11: Transfer From Savings | AG11: =SUM(B11:AF11) -> 0
A12: ='Section-Category'!A9 -> Total INCOME | B12: =SUM(B5:B11) -> 0 | C12: =SUM(C5:C11) -> 0 | D12: =SUM(D5:D11) -> 0 | E12: =SUM(E5:E11) -> 0 | F12: =SUM(F5:F11) -> 0 | G12: =SUM(G5:G11) -> 0 | H12: =SUM(H5:H11) -> 0 | I12: =SUM(I5:I11) -> 0 | ... AD12: =SUM(AD5:AD11) -> 0 | AF12: =SUM(AF5:AF11) -> 0 | AG12: =SUM(AG5:AG11) -> 0
A14: ='Section-Category'!A82 -> Petty Cash Used | AG14: Total
A15: ='Section-Category'!A83 -> Pocket Money Wife | AG15: =SUM(B15:AF15) -> 0
A16: ='Section-Category'!A84 -> Car Repair / Workshop | AG16: =SUM(B16:AF16) -> 0
A17: ='Section-Category'!A85 -> Food | AG17: =SUM(B17:AF17) -> 0
A18: ='Section-Category'!A86 -> Donation | AG18: =SUM(B18:AF18) -> 0
A19: Eidi | AG19: =SUM(B19:AF19) -> 0
A20: ='Section-Category'!A88 -> Donation | AG20: =SUM(B20:AF20) -> 0
A21: ='Section-Category'!A89 -> Pocket Money Husband | AG21: =SUM(B21:AF21) -> 0
A22: ='Section-Category'!A90 -> Other | AG22: =SUM(B22:AF22) -> 0
A23: ='Section-Category'!A91 -> Total Petty Cash Used | B23: =SUM(B15:B22) -> 0 | C23: =SUM(C15:C22) -> 0 | D23: =SUM(D15:D22) -> 0 | E23: =SUM(E15:E22) -> 0 | F23: =SUM(F15:F22) -> 0 | G23: =SUM(G15:G22) -> 0 | H23: =SUM(H15:H22) -> 0 | I23: =SUM(I15:I22) -> 0 | ... AD23: =SUM(AD15:AD22) -> 0 | AF23: =SUM(AF15:AF22) -> 0 | AG23: =SUM(AG15:AG22) -> 0
A25: ='Section-Category'!A11 -> SAVINGS EXPENSE | AG25: Total
A26: ='Section-Category'!A12 -> Emergency Fund | AG26: =SUM(B26:AF26) -> 0
A27: ='Section-Category'!A13 -> Investments | AG27: =SUM(B27:AF27) -> 0
A28: ='Section-Category'!A14 -> Pocket Money Wife | AG28: =SUM(B28:AF28) -> 0
A29: ='Section-Category'!A15 -> <Name-Of-Entry> | AG29: =SUM(B29:AF29) -> 0
A30: ='Section-Category'!A16 -> <Name-Of-Entry> | AG30: =SUM(B30:AF30) -> 0
A31: ='Section-Category'!A17 -> Total SAVINGS EXPENSE | B31: =SUM(B26:B30) -> 0 | C31: =SUM(C26:C30) -> 0 | D31: =SUM(D26:D30) -> 0 | E31: =SUM(E26:E30) -> 0 | F31: =SUM(F26:F30) -> 0 | G31: =SUM(G26:G30) -> 0 | H31: =SUM(H26:H30) -> 0 | I31: =SUM(I26:I30) -> 0 | ... AD31: =SUM(AD26:AD30) -> 0 | AF31: =SUM(AF26:AF30) -> 0 | AG31: =SUM(AG26:AG30) -> 0
A33: ='Section-Category'!A20 -> HOME EXPENSES | AG33: Total
A34: ='Section-Category'!A21 -> Mortgage/Rent | AG34: =SUM(B34:AF34) -> 0
A35: ='Section-Category'!A22 -> Electricity | AG35: =SUM(B35:AF35) -> 0
A36: ='Section-Category'!A23 -> Gas/Oil | AG36: =SUM(B36:AF36) -> 0
A37: ='Section-Category'!A24 -> Water/Sewer/Trash | AG37: =SUM(B37:AF37) -> 0
A38: ='Section-Category'!A25 -> Phone | AG38: =SUM(B38:AF38) -> 0
A39: ='Section-Category'!A26 -> Cable/Satellite | AG39: =SUM(B39:AF39) -> 0
A40: ='Section-Category'!A27 -> Internet | AG40: =SUM(B40:AF40) -> 0
A41: ='Section-Category'!A28 -> Furnishings/Appliances | AG41: =SUM(B41:AF41) -> 0
A42: ='Section-Category'!A29 -> Lawn/Garden | AG42: =SUM(B42:AF42) -> 0
A43: ='Section-Category'!A30 -> Home Supplies | AG43: =SUM(B43:AF43) -> 0
A44: ='Section-Category'!A31 -> Maintenance | AG44: =SUM(B44:AF44) -> 0
A45: ='Section-Category'!A32 -> Improvements | AG45: =SUM(B45:AF45) -> 0
A46: ='Section-Category'!A33 -> Other | AG46: =SUM(B46:AF46) -> 0
A47: ='Section-Category'!A34 -> Total HOME EXPENSES | B47: =SUM(B34:B46) -> 0 | C47: =SUM(C34:C46) -> 0 | D47: =SUM(D34:D46) -> 0 | E47: =SUM(E34:E46) -> 0 | F47: =SUM(F34:F46) -> 0 | G47: =SUM(G34:G46) -> 0 | H47: =SUM(H34:H46) -> 0 | I47: =SUM(I34:I46) -> 0 | ... AD47: =SUM(AD34:AD46) -> 0 | AF47: =SUM(AF34:AF46) -> 0 | AG47: =SUM(AG34:AG46) -> 0
A49: ='Section-Category'!A37 -> DAILY LIVING | AG49: Total
A50: ='Section-Category'!A38 -> Groceries | AG50: =SUM(B50:AF50) -> 0
A51: ='Section-Category'!A39 -> Personal Supplies | AG51: =SUM(B51:AF51) -> 0
A52: ='Section-Category'!A40 -> Clothing | AG52: =SUM(B52:AF52) -> 0
A53: ='Section-Category'!A41 -> Cleaning Services | AG53: =SUM(B53:AF53) -> 0
A54: ='Section-Category'!A42 -> Dining/Eating Out | AG54: =SUM(B54:AF54) -> 0
A55: ='Section-Category'!A43 -> Dry Cleaning | AG55: =SUM(B55:AF55) -> 0
A56: ='Section-Category'!A44 -> Salon/Barber | AG56: =SUM(B56:AF56) -> 0
A57: ='Section-Category'!A45 -> FoodPanda | AG57: =SUM(B57:AF57) -> 0
A58: ='Section-Category'!A46 -> JazzCash/EasyPaisa | AG58: =SUM(B58:AF58) -> 0
A59: ='Section-Category'!A47 -> Other | AG59: =SUM(B59:AF59) -> 0
A60: ='Section-Category'!A48 -> Total DAILY LIVING | B60: =SUM(B50:B59) -> 0 | C60: =SUM(C50:C59) -> 0 | D60: =SUM(D50:D59) -> 0 | E60: =SUM(E50:E59) -> 0 | F60: =SUM(F50:F59) -> 0 | G60: =SUM(G50:G59) -> 0 | H60: =SUM(H50:H59) -> 0 | I60: =SUM(I50:I59) -> 0 | ... AD60: =SUM(AD50:AD59) -> 0 | AF60: =SUM(AF50:AF59) -> 0 | AG60: =SUM(AG50:AG59) -> 0
A62: ='Section-Category'!A51 -> CHILDREN | AG62: Total
A63: ='Section-Category'!A52 -> Medical | AG63: =SUM(B63:AF63) -> 0
A64: ='Section-Category'!A53 -> Clothing | AG64: =SUM(B64:AF64) -> 0
A65: ='Section-Category'!A54 -> School Tuition | AG65: =SUM(B65:AF65) -> 0
A66: ='Section-Category'!A55 -> School Lunch | AG66: =SUM(B66:AF66) -> 0
A67: ='Section-Category'!A56 -> School Supplies | AG67: =SUM(B67:AF67) -> 0
A68: ='Section-Category'!A57 -> Babysitting | AG68: =SUM(B68:AF68) -> 0
A69: ='Section-Category'!A58 -> Toys/Games | AG69: =SUM(B69:AF69) -> 0
A70: ='Section-Category'!A59 -> Other | AG70: =SUM(B70:AF70) -> 0
A71: ='Section-Category'!A60 -> Total CHILDREN | B71: =SUM(B63:B70) -> 0 | C71: =SUM(C63:C70) -> 0 | D71: =SUM(D63:D70) -> 0 | E71: =SUM(E63:E70) -> 0 | F71: =SUM(F63:F70) -> 0 | G71: =SUM(G63:G70) -> 0 | H71: =SUM(H63:H70) -> 0 | I71: =SUM(I63:I70) -> 0 | ... AD71: =SUM(AD63:AD70) -> 0 | AF71: =SUM(AF63:AF70) -> 0 | AG71: =SUM(AG63:AG70) -> 0
A73: ='Section-Category'!A63 -> TRANSPORTATION | AG73: Total
A74: ='Section-Category'!A64 -> Vehicle Payments | AG74: =SUM(B74:AF74) -> 0
A75: ='Section-Category'!A65 -> Fuel | AG75: =SUM(B75:AF75) -> 0
A76: ='Section-Category'!A66 -> Bus/Taxi/Train Fare | AG76: =SUM(B76:AF76) -> 0
A77: ='Section-Category'!A67 -> Repairs | AG77: =SUM(B77:AF77) -> 0
A78: ='Section-Category'!A68 -> Registration/License | AG78: =SUM(B78:AF78) -> 0
A79: ='Section-Category'!A69 -> Other | AG79: =SUM(B79:AF79) -> 0
A80: ='Section-Category'!A70 -> Total TRANSPORTATION | B80: =SUM(B74:B79) -> 0 | C80: =SUM(C74:C79) -> 0 | D80: =SUM(D74:D79) -> 0 | E80: =SUM(E74:E79) -> 0 | F80: =SUM(F74:F79) -> 0 | G80: =SUM(G74:G79) -> 0 | H80: =SUM(H74:H79) -> 0 | I80: =SUM(I74:I79) -> 0 | ... AD80: =SUM(AD74:AD79) -> 0 | AF80: =SUM(AF74:AF79) -> 0 | AG80: =SUM(AG74:AG79) -> 0
A82: ='Section-Category'!A73 -> HEALTH | AG82: Total
A83: ='Section-Category'!A74 -> Doctor/Dentist | AG83: =SUM(B83:AF83) -> 0
A84: ='Section-Category'!A75 -> Medicine/Drugs | AG84: =SUM(B84:AF84) -> 0
A85: ='Section-Category'!A76 -> Lab Test | AG85: =SUM(B85:AF85) -> 0
A86: ='Section-Category'!A77 -> Consultation | AG86: =SUM(B86:AF86) -> 0
A87: ='Section-Category'!A78 -> Other | AG87: =SUM(B87:AF87) -> 0
A88: ='Section-Category'!A79 -> Total HEALTH | B88: =SUM(B83:B87) -> 0 | C88: =SUM(C83:C87) -> 0 | D88: =SUM(D83:D87) -> 0 | E88: =SUM(E83:E87) -> 0 | F88: =SUM(F83:F87) -> 0 | G88: =SUM(G83:G87) -> 0 | H88: =SUM(H83:H87) -> 0 | I88: =SUM(I83:I87) -> 0 | ... AD88: =SUM(AD83:AD87) -> 0 | AF88: =SUM(AF83:AF87) -> 0 | AG88: =SUM(AG83:AG87) -> 0
A90: ='Section-Category'!A94 -> EDUCATION | AG90: Total
A91: ='Section-Category'!A95 -> Tuition | AG91: =SUM(B91:AF91) -> 0
A92: ='Section-Category'!A96 -> Books | AG92: =SUM(B92:AF92) -> 0
A93: ='Section-Category'!A97 -> Music Lessons | AG93: =SUM(B93:AF93) -> 0
A94: ='Section-Category'!A98 -> Other | AG94: =SUM(B94:AF94) -> 0
A95: ='Section-Category'!A99 -> Total EDUCATION | B95: =SUM(B91:B94) -> 0 | C95: =SUM(C91:C94) -> 0 | D95: =SUM(D91:D94) -> 0 | E95: =SUM(E91:E94) -> 0 | F95: =SUM(F91:F94) -> 0 | G95: =SUM(G91:G94) -> 0 | H95: =SUM(H91:H94) -> 0 | I95: =SUM(I91:I94) -> 0 | ... AD95: =SUM(AD91:AD94) -> 0 | AF95: =SUM(AF91:AF94) -> 0 | AG95: =SUM(AG91:AG94) -> 0
A97: ='Section-Category'!A102 -> CHARITY/GIFTS | AG97: Total
A98: ='Section-Category'!A103 -> Gifts Given | AG98: =SUM(B98:AF98) -> 0
A99: ='Section-Category'!A104 -> Couple Charity | AG99: =SUM(B99:AF99) -> 0
A100: ='Section-Category'!A105 -> Mother Charity | AG100: =SUM(B100:AF100) -> 0
A101: ='Section-Category'!A106 -> Other | AG101: =SUM(B101:AF101) -> 0
A102: ='Section-Category'!A107 -> Total CHARITY/GIFTS | B102: =SUM(B98:B101) -> 0 | C102: =SUM(C98:C101) -> 0 | D102: =SUM(D98:D101) -> 0 | E102: =SUM(E98:E101) -> 0 | F102: =SUM(F98:F101) -> 0 | G102: =SUM(G98:G101) -> 0 | H102: =SUM(H98:H101) -> 0 | I102: =SUM(I98:I101) -> 0 | ... AD102: =SUM(AD98:AD101) -> 0 | AF102: =SUM(AF98:AF101) -> 0 | AG102: =SUM(AG98:AG101) -> 0
A104: ='Section-Category'!A110 -> OBLIGATIONS | AG104: Total
A105: ='Section-Category'!A111 -> Credit Card Debt | AG105: =SUM(B105:AF105) -> 0
A106: ='Section-Category'!A112 -> Punjab ST on CC Fee @16 | AG106: =SUM(B106:AF106) -> 0
A107: ='Section-Category'!A113 -> Advance Tax 5% | AG107: =SUM(B107:AF107) -> 0
A108: ='Section-Category'!A114 -> Other | AG108: =SUM(B108:AF108) -> 0
A109: ='Section-Category'!A115 -> Total OBLIGATIONS | B109: =SUM(B105:B108) -> 0 | C109: =SUM(C105:C108) -> 0 | D109: =SUM(D105:D108) -> 0 | E109: =SUM(E105:E108) -> 0 | F109: =SUM(F105:F108) -> 0 | G109: =SUM(G105:G108) -> 0 | H109: =SUM(H105:H108) -> 0 | I109: =SUM(I105:I108) -> 0 | ... AD109: =SUM(AD105:AD108) -> 0 | AF109: =SUM(AF105:AF108) -> 0 | AG109: =SUM(AG105:AG108) -> 0
A111: ='Section-Category'!A118 -> 0
A112: ='Section-Category'!A119 -> <Name-Of-Entry>
...

Sheet Apr
A1: =MID(CELL("filename",A1),FIND("]",CELL("filename",A1))+1,255) -> Apr | B1: =Budget!D1 -> 2026
A2: Summary/Date | B2: ='Section-Category'!D9 -> 46113 | C2: ='Section-Category'!E9 -> 46114 | D2: ='Section-Category'!F9 -> 46115 | E2: ='Section-Category'!G9 -> 46116 | F2: ='Section-Category'!H9 -> 46117 | G2: ='Section-Category'!I9 -> 46118 | H2: ='Section-Category'!J9 -> 46119 | I2: ='Section-Category'!K9 -> 46120 | ... AE2: ='Section-Category'!AG9 -> 46142 | AF2: Total Sum
A4: INCOME | AF4: Total
A5: Wages & Tips | AF5: =SUM(B5:AE5) -> 0
A6: Interest Income | AF6: =SUM(B6:AE6) -> 0
A7: Dividends | AF7: =SUM(B7:AE7) -> 0
A8: Gifts Received | AF8: =SUM(B8:AE8) -> 0
A9: Refunds/Reimbursements | AF9: =SUM(B9:AE9) -> 0
A10: Other | AF10: =SUM(B10:AE10) -> 0
A11: Transfer From Savings | AF11: =SUM(B11:AE11) -> 0
A12: ='Section-Category'!A9 -> Total INCOME | B12: =SUM(B5:B11) -> 0 | C12: =SUM(C5:C11) -> 0 | D12: =SUM(D5:D11) -> 0 | E12: =SUM(E5:E11) -> 0 | F12: =SUM(F5:F11) -> 0 | G12: =SUM(G5:G11) -> 0 | H12: =SUM(H5:H11) -> 0 | I12: =SUM(I5:I11) -> 0 | ... AF12: =SUM(AF5:AF11) -> 0
A14: ='Section-Category'!A82 -> Petty Cash Used | AF14: Total
A15: ='Section-Category'!A83 -> Pocket Money Wife | AF15: =SUM(B15:AE15) -> 0
A16: ='Section-Category'!A84 -> Car Repair / Workshop | AF16: =SUM(B16:AE16) -> 0
A17: ='Section-Category'!A85 -> Food | AF17: =SUM(B17:AE17) -> 0
A18: ='Section-Category'!A86 -> Donation | AF18: =SUM(B18:AE18) -> 0
A19: Eidi | AF19: =SUM(B19:AE19) -> 0
A20: ='Section-Category'!A88 -> Donation | AF20: =SUM(B20:AE20) -> 0
A21: ='Section-Category'!A89 -> Pocket Money Husband | AF21: =SUM(B21:AE21) -> 0
A22: ='Section-Category'!A90 -> Other | AF22: =SUM(B22:AE22) -> 0
A23: ='Section-Category'!A91 -> Total Petty Cash Used | B23: =SUM(B15:B22) -> 0 | C23: =SUM(C15:C22) -> 0 | D23: =SUM(D15:D22) -> 0 | E23: =SUM(E15:E22) -> 0 | F23: =SUM(F15:F22) -> 0 | G23: =SUM(G15:G22) -> 0 | H23: =SUM(H15:H22) -> 0 | I23: =SUM(I15:I22) -> 0 | ... AF23: =SUM(AF15:AF22) -> 0
A25: ='Section-Category'!A11 -> SAVINGS EXPENSE | AF25: Total
A26: ='Section-Category'!A12 -> Emergency Fund | AF26: =SUM(B26:AE26) -> 0
A27: ='Section-Category'!A13 -> Investments | AF27: =SUM(B27:AE27) -> 0
A28: ='Section-Category'!A14 -> Pocket Money Wife | AF28: =SUM(B28:AE28) -> 0
A29: ='Section-Category'!A15 -> <Name-Of-Entry> | AF29: =SUM(B29:AE29) -> 0
A30: ='Section-Category'!A16 -> <Name-Of-Entry> | AF30: =SUM(B30:AE30) -> 0
A31: ='Section-Category'!A17 -> Total SAVINGS EXPENSE | B31: =SUM(B26:B30) -> 0 | C31: =SUM(C26:C30) -> 0 | D31: =SUM(D26:D30) -> 0 | E31: =SUM(E26:E30) -> 0 | F31: =SUM(F26:F30) -> 0 | G31: =SUM(G26:G30) -> 0 | H31: =SUM(H26:H30) -> 0 | I31: =SUM(I26:I30) -> 0 | ... AF31: =SUM(AF26:AF30) -> 0
A33: ='Section-Category'!A20 -> HOME EXPENSES | AF33: Total
A34: ='Section-Category'!A21 -> Mortgage/Rent | AF34: =SUM(B34:AE34) -> 0
A35: ='Section-Category'!A22 -> Electricity | AF35: =SUM(B35:AE35) -> 0
A36: ='Section-Category'!A23 -> Gas/Oil | AF36: =SUM(B36:AE36) -> 0
A37: ='Section-Category'!A24 -> Water/Sewer/Trash | AF37: =SUM(B37:AE37) -> 0
A38: ='Section-Category'!A25 -> Phone | AF38: =SUM(B38:AE38) -> 0
A39: ='Section-Category'!A26 -> Cable/Satellite | AF39: =SUM(B39:AE39) -> 0
A40: ='Section-Category'!A27 -> Internet | AF40: =SUM(B40:AE40) -> 0
A41: ='Section-Category'!A28 -> Furnishings/Appliances | AF41: =SUM(B41:AE41) -> 0
A42: ='Section-Category'!A29 -> Lawn/Garden | AF42: =SUM(B42:AE42) -> 0
A43: ='Section-Category'!A30 -> Home Supplies | AF43: =SUM(B43:AE43) -> 0
A44: ='Section-Category'!A31 -> Maintenance | AF44: =SUM(B44:AE44) -> 0
A45: ='Section-Category'!A32 -> Improvements | AF45: =SUM(B45:AE45) -> 0
A46: ='Section-Category'!A33 -> Other | AF46: =SUM(B46:AE46) -> 0
A47: ='Section-Category'!A34 -> Total HOME EXPENSES | B47: =SUM(B34:B46) -> 0 | C47: =SUM(C34:C46) -> 0 | D47: =SUM(D34:D46) -> 0 | E47: =SUM(E34:E46) -> 0 | F47: =SUM(F34:F46) -> 0 | G47: =SUM(G34:G46) -> 0 | H47: =SUM(H34:H46) -> 0 | I47: =SUM(I34:I46) -> 0 | ... AF47: =SUM(AF34:AF46) -> 0
A49: ='Section-Category'!A37 -> DAILY LIVING | AF49: Total
A50: ='Section-Category'!A38 -> Groceries | AF50: =SUM(B50:AE50) -> 0
A51: ='Section-Category'!A39 -> Personal Supplies | AF51: =SUM(B51:AE51) -> 0
A52: ='Section-Category'!A40 -> Clothing | AF52: =SUM(B52:AE52) -> 0
A53: ='Section-Category'!A41 -> Cleaning Services | AF53: =SUM(B53:AE53) -> 0
A54: ='Section-Category'!A42 -> Dining/Eating Out | AF54: =SUM(B54:AE54) -> 0
A55: ='Section-Category'!A43 -> Dry Cleaning | AF55: =SUM(B55:AE55) -> 0
A56: ='Section-Category'!A44 -> Salon/Barber | AF56: =SUM(B56:AE56) -> 0
A57: ='Section-Category'!A45 -> FoodPanda | AF57: =SUM(B57:AE57) -> 0
A58: ='Section-Category'!A46 -> JazzCash/EasyPaisa | AF58: =SUM(B58:AE58) -> 0
A59: ='Section-Category'!A47 -> Other | AF59: =SUM(B59:AE59) -> 0
A60: ='Section-Category'!A48 -> Total DAILY LIVING | B60: =SUM(B50:B59) -> 0 | C60: =SUM(C50:C59) -> 0 | D60: =SUM(D50:D59) -> 0 | E60: =SUM(E50:E59) -> 0 | F60: =SUM(F50:F59) -> 0 | G60: =SUM(G50:G59) -> 0 | H60: =SUM(H50:H59) -> 0 | I60: =SUM(I50:I59) -> 0 | ... AF60: =SUM(AF50:AF59) -> 0
A62: ='Section-Category'!A51 -> CHILDREN | AF62: Total
A63: ='Section-Category'!A52 -> Medical | AF63: =SUM(B63:AE63) -> 0
A64: ='Section-Category'!A53 -> Clothing | AF64: =SUM(B64:AE64) -> 0
A65: ='Section-Category'!A54 -> School Tuition | AF65: =SUM(B65:AE65) -> 0
A66: ='Section-Category'!A55 -> School Lunch | AF66: =SUM(B66:AE66) -> 0
A67: ='Section-Category'!A56 -> School Supplies | AF67: =SUM(B67:AE67) -> 0
A68: ='Section-Category'!A57 -> Babysitting | AF68: =SUM(B68:AE68) -> 0
A69: ='Section-Category'!A58 -> Toys/Games | AF69: =SUM(B69:AE69) -> 0
A70: ='Section-Category'!A59 -> Other | AF70: =SUM(B70:AE70) -> 0
A71: ='Section-Category'!A60 -> Total CHILDREN | B71: =SUM(B63:B70) -> 0 | C71: =SUM(C63:C70) -> 0 | D71: =SUM(D63:D70) -> 0 | E71: =SUM(E63:E70) -> 0 | F71: =SUM(F63:F70) -> 0 | G71: =SUM(G63:G70) -> 0 | H71: =SUM(H63:H70) -> 0 | I71: =SUM(I63:I70) -> 0 | ... AF71: =SUM(AF63:AF70) -> 0
A73: ='Section-Category'!A63 -> TRANSPORTATION | AF73: Total
A74: ='Section-Category'!A64 -> Vehicle Payments | AF74: =SUM(B74:AE74) -> 0
A75: ='Section-Category'!A65 -> Fuel | AF75: =SUM(B75:AE75) -> 0
A76: ='Section-Category'!A66 -> Bus/Taxi/Train Fare | AF76: =SUM(B76:AE76) -> 0
A77: ='Section-Category'!A67 -> Repairs | AF77: =SUM(B77:AE77) -> 0
A78: ='Section-Category'!A68 -> Registration/License | AF78: =SUM(B78:AE78) -> 0
A79: ='Section-Category'!A69 -> Other | AF79: =SUM(B79:AE79) -> 0
A80: ='Section-Category'!A70 -> Total TRANSPORTATION | B80: =SUM(B74:B79) -> 0 | C80: =SUM(C74:C79) -> 0 | D80: =SUM(D74:D79) -> 0 | E80: =SUM(E74:E79) -> 0 | F80: =SUM(F74:F79) -> 0 | G80: =SUM(G74:G79) -> 0 | H80: =SUM(H74:H79) -> 0 | I80: =SUM(I74:I79) -> 0 | ... AF80: =SUM(AF74:AF79) -> 0
A82: ='Section-Category'!A73 -> HEALTH | AF82: Total
A83: ='Section-Category'!A74 -> Doctor/Dentist | AF83: =SUM(B83:AE83) -> 0
A84: ='Section-Category'!A75 -> Medicine/Drugs | AF84: =SUM(B84:AE84) -> 0
A85: ='Section-Category'!A76 -> Lab Test | AF85: =SUM(B85:AE85) -> 0
A86: ='Section-Category'!A77 -> Consultation | AF86: =SUM(B86:AE86) -> 0
A87: ='Section-Category'!A78 -> Other | AF87: =SUM(B87:AE87) -> 0
A88: ='Section-Category'!A79 -> Total HEALTH | B88: =SUM(B83:B87) -> 0 | C88: =SUM(C83:C87) -> 0 | D88: =SUM(D83:D87) -> 0 | E88: =SUM(E83:E87) -> 0 | F88: =SUM(F83:F87) -> 0 | G88: =SUM(G83:G87) -> 0 | H88: =SUM(H83:H87) -> 0 | I88: =SUM(I83:I87) -> 0 | ... AF88: =SUM(AF83:AF87) -> 0
A90: ='Section-Category'!A94 -> EDUCATION | AF90: Total
A91: ='Section-Category'!A95 -> Tuition | AF91: =SUM(B91:AE91) -> 0
A92: ='Section-Category'!A96 -> Books | AF92: =SUM(B92:AE92) -> 0
A93: ='Section-Category'!A97 -> Music Lessons | AF93: =SUM(B93:AE93) -> 0
A94: ='Section-Category'!A98 -> Other | AF94: =SUM(B94:AE94) -> 0
A95: ='Section-Category'!A99 -> Total EDUCATION | B95: =SUM(B91:B94) -> 0 | C95: =SUM(C91:C94) -> 0 | D95: =SUM(D91:D94) -> 0 | E95: =SUM(E91:E94) -> 0 | F95: =SUM(F91:F94) -> 0 | G95: =SUM(G91:G94) -> 0 | H95: =SUM(H91:H94) -> 0 | I95: =SUM(I91:I94) -> 0 | ... AF95: =SUM(AF91:AF94) -> 0
A97: ='Section-Category'!A102 -> CHARITY/GIFTS | AF97: Total
A98: ='Section-Category'!A103 -> Gifts Given | AF98: =SUM(B98:AE98) -> 0
A99: ='Section-Category'!A104 -> Couple Charity | AF99: =SUM(B99:AE99) -> 0
A100: ='Section-Category'!A105 -> Mother Charity | AF100: =SUM(B100:AE100) -> 0
A101: ='Section-Category'!A106 -> Other | AF101: =SUM(B101:AE101) -> 0
A102: ='Section-Category'!A107 -> Total CHARITY/GIFTS | B102: =SUM(B98:B101) -> 0 | C102: =SUM(C98:C101) -> 0 | D102: =SUM(D98:D101) -> 0 | E102: =SUM(E98:E101) -> 0 | F102: =SUM(F98:F101) -> 0 | G102: =SUM(G98:G101) -> 0 | H102: =SUM(H98:H101) -> 0 | I102: =SUM(I98:I101) -> 0 | ... AF102: =SUM(AF98:AF101) -> 0
A104: ='Section-Category'!A110 -> OBLIGATIONS | AF104: Total
A105: ='Section-Category'!A111 -> Credit Card Debt | AF105: =SUM(B105:AE105) -> 0
A106: ='Section-Category'!A112 -> Punjab ST on CC Fee @16 | AF106: =SUM(B106:AE106) -> 0
A107: ='Section-Category'!A113 -> Advance Tax 5% | AF107: =SUM(B107:AE107) -> 0
A108: ='Section-Category'!A114 -> Other | AF108: =SUM(B108:AE108) -> 0
A109: ='Section-Category'!A115 -> Total OBLIGATIONS | B109: =SUM(B105:B108) -> 0 | C109: =SUM(C105:C108) -> 0 | D109: =SUM(D105:D108) -> 0 | E109: =SUM(E105:E108) -> 0 | F109: =SUM(F105:F108) -> 0 | G109: =SUM(G105:G108) -> 0 | H109: =SUM(H105:H108) -> 0 | I109: =SUM(I105:I108) -> 0 | ... AF109: =SUM(AF105:AF108) -> 0
A111: ='Section-Category'!A118 -> 0
A112: ='Section-Category'!A119 -> <Name-Of-Entry>
...

Sheet May
A1: =MID(CELL("filename",A1),FIND("]",CELL("filename",A1))+1,255) -> May | B1: =Budget!D1 -> 2026
A2: Summary | B2: ='Section-Category'!D10 -> 46143 | C2: ='Section-Category'!E10 -> 46144 | D2: ='Section-Category'!F10 -> 46145 | E2: ='Section-Category'!G10 -> 46146 | F2: ='Section-Category'!H10 -> 46147 | G2: ='Section-Category'!I10 -> 46148 | H2: ='Section-Category'!J10 -> 46149 | I2: ='Section-Category'!K10 -> 46150 | ... AG2: ='Section-Category'!AI10 -> 0 | AH2: Total Sum
A4: INCOME | AH4: Total
A5: Wages & Tips | AH5: =SUM(B5:AG5) -> 0
A6: Interest Income | AH6: =SUM(B6:AG6) -> 0
A7: Dividends | AH7: =SUM(B7:AG7) -> 0
A8: Gifts Received | AH8: =SUM(B8:AG8) -> 0
A9: Refunds/Reimbursements | AH9: =SUM(B9:AG9) -> 0
A10: Other | AH10: =SUM(B10:AG10) -> 0
A11: Transfer From Savings | AH11: =SUM(B11:AG11) -> 0
A12: ='Section-Category'!A9 -> Total INCOME | B12: =SUM(B5:B11) -> 0 | C12: =SUM(C5:C11) -> 0 | D12: =SUM(D5:D11) -> 0 | E12: =SUM(E5:E11) -> 0 | F12: =SUM(F5:F11) -> 0 | G12: =SUM(G5:G11) -> 0 | H12: =SUM(H5:H11) -> 0 | I12: =SUM(I5:I11) -> 0 | ... AE12: =SUM(AE5:AE11) -> 0 | AG12: =SUM(AG5:AG11) -> 0 | AH12: =SUM(AH5:AH11) -> 0
A14: ='Section-Category'!A82 -> Petty Cash Used | AH14: Total
A15: ='Section-Category'!A83 -> Pocket Money Wife | AH15: =SUM(B15:AG15) -> 0
A16: ='Section-Category'!A84 -> Car Repair / Workshop | AH16: =SUM(B16:AG16) -> 0
A17: ='Section-Category'!A85 -> Food | AH17: =SUM(B17:AG17) -> 0
A18: ='Section-Category'!A86 -> Donation | AH18: =SUM(B18:AG18) -> 0
A19: Eidi | AH19: =SUM(B19:AG19) -> 0
A20: ='Section-Category'!A88 -> Donation | AH20: =SUM(B20:AG20) -> 0
A21: ='Section-Category'!A89 -> Pocket Money Husband | AH21: =SUM(B21:AG21) -> 0
A22: ='Section-Category'!A90 -> Other | AH22: =SUM(B22:AG22) -> 0
A23: ='Section-Category'!A91 -> Total Petty Cash Used | B23: =SUM(B15:B22) -> 0 | C23: =SUM(C15:C22) -> 0 | D23: =SUM(D15:D22) -> 0 | E23: =SUM(E15:E22) -> 0 | F23: =SUM(F15:F22) -> 0 | G23: =SUM(G15:G22) -> 0 | H23: =SUM(H15:H22) -> 0 | I23: =SUM(I15:I22) -> 0 | ... AE23: =SUM(AE15:AE22) -> 0 | AG23: =SUM(AG15:AG22) -> 0 | AH23: =SUM(AH15:AH22) -> 0
A25: ='Section-Category'!A11 -> SAVINGS EXPENSE | AH25: Total
A26: ='Section-Category'!A12 -> Emergency Fund | AH26: =SUM(B26:AG26) -> 0
A27: ='Section-Category'!A13 -> Investments | AH27: =SUM(B27:AG27) -> 0
A28: ='Section-Category'!A14 -> Pocket Money Wife | AH28: =SUM(B28:AG28) -> 0
A29: ='Section-Category'!A15 -> <Name-Of-Entry> | AH29: =SUM(B29:AG29) -> 0
A30: ='Section-Category'!A16 -> <Name-Of-Entry> | AH30: =SUM(B30:AG30) -> 0
A31: ='Section-Category'!A17 -> Total SAVINGS EXPENSE | B31: =SUM(B26:B30) -> 0 | C31: =SUM(C26:C30) -> 0 | D31: =SUM(D26:D30) -> 0 | E31: =SUM(E26:E30) -> 0 | F31: =SUM(F26:F30) -> 0 | G31: =SUM(G26:G30) -> 0 | H31: =SUM(H26:H30) -> 0 | I31: =SUM(I26:I30) -> 0 | ... AE31: =SUM(AE26:AE30) -> 0 | AG31: =SUM(AG26:AG30) -> 0 | AH31: =SUM(AH26:AH30) -> 0
A33: ='Section-Category'!A20 -> HOME EXPENSES | AH33: Total
A34: ='Section-Category'!A21 -> Mortgage/Rent | AH34: =SUM(B34:AG34) -> 0
A35: ='Section-Category'!A22 -> Electricity | AH35: =SUM(B35:AG35) -> 0
A36: ='Section-Category'!A23 -> Gas/Oil | AH36: =SUM(B36:AG36) -> 0
A37: ='Section-Category'!A24 -> Water/Sewer/Trash | AH37: =SUM(B37:AG37) -> 0
A38: ='Section-Category'!A25 -> Phone | AH38: =SUM(B38:AG38) -> 0
A39: ='Section-Category'!A26 -> Cable/Satellite | AH39: =SUM(B39:AG39) -> 0
A40: ='Section-Category'!A27 -> Internet | AH40: =SUM(B40:AG40) -> 0
A41: ='Section-Category'!A28 -> Furnishings/Appliances | AH41: =SUM(B41:AG41) -> 0
A42: ='Section-Category'!A29 -> Lawn/Garden | AH42: =SUM(B42:AG42) -> 0
A43: ='Section-Category'!A30 -> Home Supplies | AH43: =SUM(B43:AG43) -> 0
A44: ='Section-Category'!A31 -> Maintenance | AH44: =SUM(B44:AG44) -> 0
A45: ='Section-Category'!A32 -> Improvements | AH45: =SUM(B45:AG45) -> 0
A46: ='Section-Category'!A33 -> Other | AH46: =SUM(B46:AG46) -> 0
A47: ='Section-Category'!A34 -> Total HOME EXPENSES | B47: =SUM(B34:B46) -> 0 | C47: =SUM(C34:C46) -> 0 | D47: =SUM(D34:D46) -> 0 | E47: =SUM(E34:E46) -> 0 | F47: =SUM(F34:F46) -> 0 | G47: =SUM(G34:G46) -> 0 | H47: =SUM(H34:H46) -> 0 | I47: =SUM(I34:I46) -> 0 | ... AE47: =SUM(AE34:AE46) -> 0 | AG47: =SUM(AG34:AG46) -> 0 | AH47: =SUM(AH34:AH46) -> 0
A49: ='Section-Category'!A37 -> DAILY LIVING | AH49: Total
A50: ='Section-Category'!A38 -> Groceries | AH50: =SUM(B50:AG50) -> 0
A51: ='Section-Category'!A39 -> Personal Supplies | AH51: =SUM(B51:AG51) -> 0
A52: ='Section-Category'!A40 -> Clothing | AH52: =SUM(B52:AG52) -> 0
A53: ='Section-Category'!A41 -> Cleaning Services | AH53: =SUM(B53:AG53) -> 0
A54: ='Section-Category'!A42 -> Dining/Eating Out | AH54: =SUM(B54:AG54) -> 0
A55: ='Section-Category'!A43 -> Dry Cleaning | AH55: =SUM(B55:AG55) -> 0
A56: ='Section-Category'!A44 -> Salon/Barber | AH56: =SUM(B56:AG56) -> 0
A57: ='Section-Category'!A45 -> FoodPanda | AH57: =SUM(B57:AG57) -> 0
A58: ='Section-Category'!A46 -> JazzCash/EasyPaisa | AH58: =SUM(B58:AG58) -> 0
A59: ='Section-Category'!A47 -> Other | AH59: =SUM(B59:AG59) -> 0
A60: ='Section-Category'!A48 -> Total DAILY LIVING | B60: =SUM(B50:B59) -> 0 | C60: =SUM(C50:C59) -> 0 | D60: =SUM(D50:D59) -> 0 | E60: =SUM(E50:E59) -> 0 | F60: =SUM(F50:F59) -> 0 | G60: =SUM(G50:G59) -> 0 | H60: =SUM(H50:H59) -> 0 | I60: =SUM(I50:I59) -> 0 | ... AE60: =SUM(AE50:AE59) -> 0 | AG60: =SUM(AG50:AG59) -> 0 | AH60: =SUM(AH50:AH59) -> 0
A62: ='Section-Category'!A51 -> CHILDREN | AH62: Total
A63: ='Section-Category'!A52 -> Medical | AH63: =SUM(B63:AG63) -> 0
A64: ='Section-Category'!A53 -> Clothing | AH64: =SUM(B64:AG64) -> 0
A65: ='Section-Category'!A54 -> School Tuition | AH65: =SUM(B65:AG65) -> 0
A66: ='Section-Category'!A55 -> School Lunch | AH66: =SUM(B66:AG66) -> 0
A67: ='Section-Category'!A56 -> School Supplies | AH67: =SUM(B67:AG67) -> 0
A68: ='Section-Category'!A57 -> Babysitting | AH68: =SUM(B68:AG68) -> 0
A69: ='Section-Category'!A58 -> Toys/Games | AH69: =SUM(B69:AG69) -> 0
A70: ='Section-Category'!A59 -> Other | AH70: =SUM(B70:AG70) -> 0
A71: ='Section-Category'!A60 -> Total CHILDREN | B71: =SUM(B63:B70) -> 0 | C71: =SUM(C63:C70) -> 0 | D71: =SUM(D63:D70) -> 0 | E71: =SUM(E63:E70) -> 0 | F71: =SUM(F63:F70) -> 0 | G71: =SUM(G63:G70) -> 0 | H71: =SUM(H63:H70) -> 0 | I71: =SUM(I63:I70) -> 0 | ... AE71: =SUM(AE63:AE70) -> 0 | AG71: =SUM(AG63:AG70) -> 0 | AH71: =SUM(AH63:AH70) -> 0
A73: ='Section-Category'!A63 -> TRANSPORTATION | AH73: Total
A74: ='Section-Category'!A64 -> Vehicle Payments | AH74: =SUM(B74:AG74) -> 0
A75: ='Section-Category'!A65 -> Fuel | AH75: =SUM(B75:AG75) -> 0
A76: ='Section-Category'!A66 -> Bus/Taxi/Train Fare | AH76: =SUM(B76:AG76) -> 0
A77: ='Section-Category'!A67 -> Repairs | AH77: =SUM(B77:AG77) -> 0
A78: ='Section-Category'!A68 -> Registration/License | AH78: =SUM(B78:AG78) -> 0
A79: ='Section-Category'!A69 -> Other | AH79: =SUM(B79:AG79) -> 0
A80: ='Section-Category'!A70 -> Total TRANSPORTATION | B80: =SUM(B74:B79) -> 0 | C80: =SUM(C74:C79) -> 0 | D80: =SUM(D74:D79) -> 0 | E80: =SUM(E74:E79) -> 0 | F80: =SUM(F74:F79) -> 0 | G80: =SUM(G74:G79) -> 0 | H80: =SUM(H74:H79) -> 0 | I80: =SUM(I74:I79) -> 0 | ... AE80: =SUM(AE74:AE79) -> 0 | AG80: =SUM(AG74:AG79) -> 0 | AH80: =SUM(AH74:AH79) -> 0
A82: ='Section-Category'!A73 -> HEALTH | AH82: Total
A83: ='Section-Category'!A74 -> Doctor/Dentist | AH83: =SUM(B83:AG83) -> 0
A84: ='Section-Category'!A75 -> Medicine/Drugs | AH84: =SUM(B84:AG84) -> 0
A85: ='Section-Category'!A76 -> Lab Test | AH85: =SUM(B85:AG85) -> 0
A86: ='Section-Category'!A77 -> Consultation | AH86: =SUM(B86:AG86) -> 0
A87: ='Section-Category'!A78 -> Other | AH87: =SUM(B87:AG87) -> 0
A88: ='Section-Category'!A79 -> Total HEALTH | B88: =SUM(B83:B87) -> 0 | C88: =SUM(C83:C87) -> 0 | D88: =SUM(D83:D87) -> 0 | E88: =SUM(E83:E87) -> 0 | F88: =SUM(F83:F87) -> 0 | G88: =SUM(G83:G87) -> 0 | H88: =SUM(H83:H87) -> 0 | I88: =SUM(I83:I87) -> 0 | ... AE88: =SUM(AE83:AE87) -> 0 | AG88: =SUM(AG83:AG87) -> 0 | AH88: =SUM(AH83:AH87) -> 0
A90: ='Section-Category'!A94 -> EDUCATION | AH90: Total
A91: ='Section-Category'!A95 -> Tuition | AH91: =SUM(B91:AG91) -> 0
A92: ='Section-Category'!A96 -> Books | AH92: =SUM(B92:AG92) -> 0
A93: ='Section-Category'!A97 -> Music Lessons | AH93: =SUM(B93:AG93) -> 0
A94: ='Section-Category'!A98 -> Other | AH94: =SUM(B94:AG94) -> 0
A95: ='Section-Category'!A99 -> Total EDUCATION | B95: =SUM(B91:B94) -> 0 | C95: =SUM(C91:C94) -> 0 | D95: =SUM(D91:D94) -> 0 | E95: =SUM(E91:E94) -> 0 | F95: =SUM(F91:F94) -> 0 | G95: =SUM(G91:G94) -> 0 | H95: =SUM(H91:H94) -> 0 | I95: =SUM(I91:I94) -> 0 | ... AE95: =SUM(AE91:AE94) -> 0 | AG95: =SUM(AG91:AG94) -> 0 | AH95: =SUM(AH91:AH94) -> 0
A97: ='Section-Category'!A102 -> CHARITY/GIFTS | AH97: Total
A98: ='Section-Category'!A103 -> Gifts Given | AH98: =SUM(B98:AG98) -> 0
A99: ='Section-Category'!A104 -> Couple Charity | AH99: =SUM(B99:AG99) -> 0
A100: ='Section-Category'!A105 -> Mother Charity | AH100: =SUM(B100:AG100) -> 0
A101: ='Section-Category'!A106 -> Other | AH101: =SUM(B101:AG101) -> 0
A102: ='Section-Category'!A107 -> Total CHARITY/GIFTS | B102: =SUM(B98:B101) -> 0 | C102: =SUM(C98:C101) -> 0 | D102: =SUM(D98:D101) -> 0 | E102: =SUM(E98:E101) -> 0 | F102: =SUM(F98:F101) -> 0 | G102: =SUM(G98:G101) -> 0 | H102: =SUM(H98:H101) -> 0 | I102: =SUM(I98:I101) -> 0 | ... AE102: =SUM(AE98:AE101) -> 0 | AG102: =SUM(AG98:AG101) -> 0 | AH102: =SUM(AH98:AH101) -> 0
A104: ='Section-Category'!A110 -> OBLIGATIONS | AH104: Total
A105: ='Section-Category'!A111 -> Credit Card Debt | AH105: =SUM(B105:AG105) -> 0
A106: ='Section-Category'!A112 -> Punjab ST on CC Fee @16 | AH106: =SUM(B106:AG106) -> 0
A107: ='Section-Category'!A113 -> Advance Tax 5% | AH107: =SUM(B107:AG107) -> 0
A108: ='Section-Category'!A114 -> Other | AH108: =SUM(B108:AG108) -> 0
A109: ='Section-Category'!A115 -> Total OBLIGATIONS | B109: =SUM(B105:B108) -> 0 | C109: =SUM(C105:C108) -> 0 | D109: =SUM(D105:D108) -> 0 | E109: =SUM(E105:E108) -> 0 | F109: =SUM(F105:F108) -> 0 | G109: =SUM(G105:G108) -> 0 | H109: =SUM(H105:H108) -> 0 | I109: =SUM(I105:I108) -> 0 | ... AE109: =SUM(AE105:AE108) -> 0 | AG109: =SUM(AG105:AG108) -> 0 | AH109: =SUM(AH105:AH108) -> 0
A111: ='Section-Category'!A118 -> 0
A112: ='Section-Category'!A119 -> <Name-Of-Entry>
...

Sheet Jun
A1: =MID(CELL("filename",A1),FIND("]",CELL("filename",A1))+1,255) -> Jun | B1: =Budget!D1 -> 2026
A2: Summary/Date | B2: ='Section-Category'!D11 -> 46174 | C2: ='Section-Category'!E11 -> 46175 | D2: ='Section-Category'!F11 -> 46176 | E2: ='Section-Category'!G11 -> 46177 | F2: ='Section-Category'!H11 -> 46178 | G2: ='Section-Category'!I11 -> 46179 | H2: ='Section-Category'!J11 -> 46180 | I2: ='Section-Category'!K11 -> 46181 | ... AE2: ='Section-Category'!AG11 -> 46203 | AF2: Total Sum
A4: INCOME | AF4: Total
A5: Wages & Tips | AF5: =SUM(B5:AE5) -> 0
A6: Interest Income | AF6: =SUM(B6:AE6) -> 0
A7: Dividends | AF7: =SUM(B7:AE7) -> 0
A8: Gifts Received | AF8: =SUM(B8:AE8) -> 0
A9: Refunds/Reimbursements | AF9: =SUM(B9:AE9) -> 0
A10: Other | AF10: =SUM(B10:AE10) -> 0
A11: Transfer From Savings | AF11: =SUM(B11:AE11) -> 0
A12: ='Section-Category'!A9 -> Total INCOME | B12: =SUM(B5:B11) -> 0 | C12: =SUM(C5:C11) -> 0 | D12: =SUM(D5:D11) -> 0 | E12: =SUM(E5:E11) -> 0 | F12: =SUM(F5:F11) -> 0 | G12: =SUM(G5:G11) -> 0 | H12: =SUM(H5:H11) -> 0 | I12: =SUM(I5:I11) -> 0 | ... AF12: =SUM(AF5:AF11) -> 0
A14: ='Section-Category'!A82 -> Petty Cash Used | AF14: Total
A15: ='Section-Category'!A83 -> Pocket Money Wife | AF15: =SUM(B15:AE15) -> 0
A16: ='Section-Category'!A84 -> Car Repair / Workshop | AF16: =SUM(B16:AE16) -> 0
A17: ='Section-Category'!A85 -> Food | AF17: =SUM(B17:AE17) -> 0
A18: ='Section-Category'!A86 -> Donation | AF18: =SUM(B18:AE18) -> 0
A19: Eidi | AF19: =SUM(B19:AE19) -> 0
A20: ='Section-Category'!A88 -> Donation | AF20: =SUM(B20:AE20) -> 0
A21: ='Section-Category'!A89 -> Pocket Money Husband | AF21: =SUM(B21:AE21) -> 0
A22: ='Section-Category'!A90 -> Other | AF22: =SUM(B22:AE22) -> 0
A23: ='Section-Category'!A91 -> Total Petty Cash Used | B23: =SUM(B15:B22) -> 0 | C23: =SUM(C15:C22) -> 0 | D23: =SUM(D15:D22) -> 0 | E23: =SUM(E15:E22) -> 0 | F23: =SUM(F15:F22) -> 0 | G23: =SUM(G15:G22) -> 0 | H23: =SUM(H15:H22) -> 0 | I23: =SUM(I15:I22) -> 0 | ... AF23: =SUM(AF15:AF22) -> 0
A25: ='Section-Category'!A11 -> SAVINGS EXPENSE | AF25: Total
A26: ='Section-Category'!A12 -> Emergency Fund | AF26: =SUM(B26:AE26) -> 0
A27: ='Section-Category'!A13 -> Investments | AF27: =SUM(B27:AE27) -> 0
A28: ='Section-Category'!A14 -> Pocket Money Wife | AF28: =SUM(B28:AE28) -> 0
A29: ='Section-Category'!A15 -> <Name-Of-Entry> | AF29: =SUM(B29:AE29) -> 0
A30: ='Section-Category'!A16 -> <Name-Of-Entry> | AF30: =SUM(B30:AE30) -> 0
A31: ='Section-Category'!A17 -> Total SAVINGS EXPENSE | B31: =SUM(B26:B30) -> 0 | C31: =SUM(C26:C30) -> 0 | D31: =SUM(D26:D30) -> 0 | E31: =SUM(E26:E30) -> 0 | F31: =SUM(F26:F30) -> 0 | G31: =SUM(G26:G30) -> 0 | H31: =SUM(H26:H30) -> 0 | I31: =SUM(I26:I30) -> 0 | ... AF31: =SUM(AF26:AF30) -> 0
A33: ='Section-Category'!A20 -> HOME EXPENSES | AF33: Total
A34: ='Section-Category'!A21 -> Mortgage/Rent | AF34: =SUM(B34:AE34) -> 0
A35: ='Section-Category'!A22 -> Electricity | AF35: =SUM(B35:AE35) -> 0
A36: ='Section-Category'!A23 -> Gas/Oil | AF36: =SUM(B36:AE36) -> 0
A37: ='Section-Category'!A24 -> Water/Sewer/Trash | AF37: =SUM(B37:AE37) -> 0
A38: ='Section-Category'!A25 -> Phone | AF38: =SUM(B38:AE38) -> 0
A39: ='Section-Category'!A26 -> Cable/Satellite | AF39: =SUM(B39:AE39) -> 0
A40: ='Section-Category'!A27 -> Internet | AF40: =SUM(B40:AE40) -> 0
A41: ='Section-Category'!A28 -> Furnishings/Appliances | AF41: =SUM(B41:AE41) -> 0
A42: ='Section-Category'!A29 -> Lawn/Garden | AF42: =SUM(B42:AE42) -> 0
A43: ='Section-Category'!A30 -> Home Supplies | AF43: =SUM(B43:AE43) -> 0
A44: ='Section-Category'!A31 -> Maintenance | AF44: =SUM(B44:AE44) -> 0
A45: ='Section-Category'!A32 -> Improvements | AF45: =SUM(B45:AE45) -> 0
A46: ='Section-Category'!A33 -> Other | AF46: =SUM(B46:AE46) -> 0
A47: ='Section-Category'!A34 -> Total HOME EXPENSES | B47: =SUM(B34:B46) -> 0 | C47: =SUM(C34:C46) -> 0 | D47: =SUM(D34:D46) -> 0 | E47: =SUM(E34:E46) -> 0 | F47: =SUM(F34:F46) -> 0 | G47: =SUM(G34:G46) -> 0 | H47: =SUM(H34:H46) -> 0 | I47: =SUM(I34:I46) -> 0 | ... AF47: =SUM(AF34:AF46) -> 0
A49: ='Section-Category'!A37 -> DAILY LIVING | AF49: Total
A50: ='Section-Category'!A38 -> Groceries | AF50: =SUM(B50:AE50) -> 0
A51: ='Section-Category'!A39 -> Personal Supplies | AF51: =SUM(B51:AE51) -> 0
A52: ='Section-Category'!A40 -> Clothing | AF52: =SUM(B52:AE52) -> 0
A53: ='Section-Category'!A41 -> Cleaning Services | AF53: =SUM(B53:AE53) -> 0
A54: ='Section-Category'!A42 -> Dining/Eating Out | AF54: =SUM(B54:AE54) -> 0
A55: ='Section-Category'!A43 -> Dry Cleaning | AF55: =SUM(B55:AE55) -> 0
A56: ='Section-Category'!A44 -> Salon/Barber | AF56: =SUM(B56:AE56) -> 0
A57: ='Section-Category'!A45 -> FoodPanda | AF57: =SUM(B57:AE57) -> 0
A58: ='Section-Category'!A46 -> JazzCash/EasyPaisa | AF58: =SUM(B58:AE58) -> 0
A59: ='Section-Category'!A47 -> Other | AF59: =SUM(B59:AE59) -> 0
A60: ='Section-Category'!A48 -> Total DAILY LIVING | B60: =SUM(B50:B59) -> 0 | C60: =SUM(C50:C59) -> 0 | D60: =SUM(D50:D59) -> 0 | E60: =SUM(E50:E59) -> 0 | F60: =SUM(F50:F59) -> 0 | G60: =SUM(G50:G59) -> 0 | H60: =SUM(H50:H59) -> 0 | I60: =SUM(I50:I59) -> 0 | ... AF60: =SUM(AF50:AF59) -> 0
A62: ='Section-Category'!A51 -> CHILDREN | AF62: Total
A63: ='Section-Category'!A52 -> Medical | AF63: =SUM(B63:AE63) -> 0
A64: ='Section-Category'!A53 -> Clothing | AF64: =SUM(B64:AE64) -> 0
A65: ='Section-Category'!A54 -> School Tuition | AF65: =SUM(B65:AE65) -> 0
A66: ='Section-Category'!A55 -> School Lunch | AF66: =SUM(B66:AE66) -> 0
A67: ='Section-Category'!A56 -> School Supplies | AF67: =SUM(B67:AE67) -> 0
A68: ='Section-Category'!A57 -> Babysitting | AF68: =SUM(B68:AE68) -> 0
A69: ='Section-Category'!A58 -> Toys/Games | AF69: =SUM(B69:AE69) -> 0
A70: ='Section-Category'!A59 -> Other | AF70: =SUM(B70:AE70) -> 0
A71: ='Section-Category'!A60 -> Total CHILDREN | B71: =SUM(B63:B70) -> 0 | C71: =SUM(C63:C70) -> 0 | D71: =SUM(D63:D70) -> 0 | E71: =SUM(E63:E70) -> 0 | F71: =SUM(F63:F70) -> 0 | G71: =SUM(G63:G70) -> 0 | H71: =SUM(H63:H70) -> 0 | I71: =SUM(I63:I70) -> 0 | ... AF71: =SUM(AF63:AF70) -> 0
A73: ='Section-Category'!A63 -> TRANSPORTATION | AF73: Total
A74: ='Section-Category'!A64 -> Vehicle Payments | AF74: =SUM(B74:AE74) -> 0
A75: ='Section-Category'!A65 -> Fuel | AF75: =SUM(B75:AE75) -> 0
A76: ='Section-Category'!A66 -> Bus/Taxi/Train Fare | AF76: =SUM(B76:AE76) -> 0
A77: ='Section-Category'!A67 -> Repairs | AF77: =SUM(B77:AE77) -> 0
A78: ='Section-Category'!A68 -> Registration/License | AF78: =SUM(B78:AE78) -> 0
A79: ='Section-Category'!A69 -> Other | AF79: =SUM(B79:AE79) -> 0
A80: ='Section-Category'!A70 -> Total TRANSPORTATION | B80: =SUM(B74:B79) -> 0 | C80: =SUM(C74:C79) -> 0 | D80: =SUM(D74:D79) -> 0 | E80: =SUM(E74:E79) -> 0 | F80: =SUM(F74:F79) -> 0 | G80: =SUM(G74:G79) -> 0 | H80: =SUM(H74:H79) -> 0 | I80: =SUM(I74:I79) -> 0 | ... AF80: =SUM(AF74:AF79) -> 0
A82: ='Section-Category'!A73 -> HEALTH | AF82: Total
A83: ='Section-Category'!A74 -> Doctor/Dentist | AF83: =SUM(B83:AE83) -> 0
A84: ='Section-Category'!A75 -> Medicine/Drugs | AF84: =SUM(B84:AE84) -> 0
A85: ='Section-Category'!A76 -> Lab Test | AF85: =SUM(B85:AE85) -> 0
A86: ='Section-Category'!A77 -> Consultation | AF86: =SUM(B86:AE86) -> 0
A87: ='Section-Category'!A78 -> Other | AF87: =SUM(B87:AE87) -> 0
A88: ='Section-Category'!A79 -> Total HEALTH | B88: =SUM(B83:B87) -> 0 | C88: =SUM(C83:C87) -> 0 | D88: =SUM(D83:D87) -> 0 | E88: =SUM(E83:E87) -> 0 | F88: =SUM(F83:F87) -> 0 | G88: =SUM(G83:G87) -> 0 | H88: =SUM(H83:H87) -> 0 | I88: =SUM(I83:I87) -> 0 | ... AF88: =SUM(AF83:AF87) -> 0
A90: ='Section-Category'!A94 -> EDUCATION | AF90: Total
A91: ='Section-Category'!A95 -> Tuition | AF91: =SUM(B91:AE91) -> 0
A92: ='Section-Category'!A96 -> Books | AF92: =SUM(B92:AE92) -> 0
A93: ='Section-Category'!A97 -> Music Lessons | AF93: =SUM(B93:AE93) -> 0
A94: ='Section-Category'!A98 -> Other | AF94: =SUM(B94:AE94) -> 0
A95: ='Section-Category'!A99 -> Total EDUCATION | B95: =SUM(B91:B94) -> 0 | C95: =SUM(C91:C94) -> 0 | D95: =SUM(D91:D94) -> 0 | E95: =SUM(E91:E94) -> 0 | F95: =SUM(F91:F94) -> 0 | G95: =SUM(G91:G94) -> 0 | H95: =SUM(H91:H94) -> 0 | I95: =SUM(I91:I94) -> 0 | ... AF95: =SUM(AF91:AF94) -> 0
A97: ='Section-Category'!A102 -> CHARITY/GIFTS | AF97: Total
A98: ='Section-Category'!A103 -> Gifts Given | AF98: =SUM(B98:AE98) -> 0
A99: ='Section-Category'!A104 -> Couple Charity | AF99: =SUM(B99:AE99) -> 0
A100: ='Section-Category'!A105 -> Mother Charity | AF100: =SUM(B100:AE100) -> 0
A101: ='Section-Category'!A106 -> Other | AF101: =SUM(B101:AE101) -> 0
A102: ='Section-Category'!A107 -> Total CHARITY/GIFTS | B102: =SUM(B98:B101) -> 0 | C102: =SUM(C98:C101) -> 0 | D102: =SUM(D98:D101) -> 0 | E102: =SUM(E98:E101) -> 0 | F102: =SUM(F98:F101) -> 0 | G102: =SUM(G98:G101) -> 0 | H102: =SUM(H98:H101) -> 0 | I102: =SUM(I98:I101) -> 0 | ... AF102: =SUM(AF98:AF101) -> 0
A104: ='Section-Category'!A110 -> OBLIGATIONS | AF104: Total
A105: ='Section-Category'!A111 -> Credit Card Debt | AF105: =SUM(B105:AE105) -> 0
A106: ='Section-Category'!A112 -> Punjab ST on CC Fee @16 | AF106: =SUM(B106:AE106) -> 0
A107: ='Section-Category'!A113 -> Advance Tax 5% | AF107: =SUM(B107:AE107) -> 0
A108: ='Section-Category'!A114 -> Other | AF108: =SUM(B108:AE108) -> 0
A109: ='Section-Category'!A115 -> Total OBLIGATIONS | B109: =SUM(B105:B108) -> 0 | C109: =SUM(C105:C108) -> 0 | D109: =SUM(D105:D108) -> 0 | E109: =SUM(E105:E108) -> 0 | F109: =SUM(F105:F108) -> 0 | G109: =SUM(G105:G108) -> 0 | H109: =SUM(H105:H108) -> 0 | I109: =SUM(I105:I108) -> 0 | ... AF109: =SUM(AF105:AF108) -> 0
A111: ='Section-Category'!A118 -> 0
A112: ='Section-Category'!A119 -> <Name-Of-Entry>
...

Sheet Jul
A1: =MID(CELL("filename",A1),FIND("]",CELL("filename",A1))+1,255) -> Jul | B1: =Budget!D1 -> 2026
A2: Summary/Date | B2: ='Section-Category'!D12 -> 46204 | C2: ='Section-Category'!E12 -> 46205 | D2: ='Section-Category'!F12 -> 46206 | E2: ='Section-Category'!G12 -> 46207 | F2: ='Section-Category'!H12 -> 46208 | G2: ='Section-Category'!I12 -> 46209 | H2: ='Section-Category'!J12 -> 46210 | I2: ='Section-Category'!K12 -> 46211 | ... AE2: ='Section-Category'!AG12 -> 46233 | AF2: Total Sum
A4: INCOME | AF4: Total
A5: Wages & Tips | AF5: =SUM(B5:AE5) -> 0
A6: Interest Income | AF6: =SUM(B6:AE6) -> 0
A7: Dividends | AF7: =SUM(B7:AE7) -> 0
A8: Gifts Received | AF8: =SUM(B8:AE8) -> 0
A9: Refunds/Reimbursements | AF9: =SUM(B9:AE9) -> 0
A10: Other | AF10: =SUM(B10:AE10) -> 0
A11: Transfer From Savings | AF11: =SUM(B11:AE11) -> 0
A12: ='Section-Category'!A9 -> Total INCOME | B12: =SUM(B5:B11) -> 0 | C12: =SUM(C5:C11) -> 0 | D12: =SUM(D5:D11) -> 0 | E12: =SUM(E5:E11) -> 0 | F12: =SUM(F5:F11) -> 0 | G12: =SUM(G5:G11) -> 0 | H12: =SUM(H5:H11) -> 0 | I12: =SUM(I5:I11) -> 0 | ... AF12: =SUM(AF5:AF11) -> 0
A14: ='Section-Category'!A82 -> Petty Cash Used | AF14: Total
A15: ='Section-Category'!A83 -> Pocket Money Wife | AF15: =SUM(B15:AE15) -> 0
A16: ='Section-Category'!A84 -> Car Repair / Workshop | AF16: =SUM(B16:AE16) -> 0
A17: ='Section-Category'!A85 -> Food | AF17: =SUM(B17:AE17) -> 0
A18: ='Section-Category'!A86 -> Donation | AF18: =SUM(B18:AE18) -> 0
A19: Eidi | AF19: =SUM(B19:AE19) -> 0
A20: ='Section-Category'!A88 -> Donation | AF20: =SUM(B20:AE20) -> 0
A21: ='Section-Category'!A89 -> Pocket Money Husband | AF21: =SUM(B21:AE21) -> 0
A22: ='Section-Category'!A90 -> Other | AF22: =SUM(B22:AE22) -> 0
A23: ='Section-Category'!A91 -> Total Petty Cash Used | B23: =SUM(B15:B22) -> 0 | C23: =SUM(C15:C22) -> 0 | D23: =SUM(D15:D22) -> 0 | E23: =SUM(E15:E22) -> 0 | F23: =SUM(F15:F22) -> 0 | G23: =SUM(G15:G22) -> 0 | H23: =SUM(H15:H22) -> 0 | I23: =SUM(I15:I22) -> 0 | ... AF23: =SUM(AF15:AF22) -> 0
A25: ='Section-Category'!A11 -> SAVINGS EXPENSE | AF25: Total
A26: ='Section-Category'!A12 -> Emergency Fund | AF26: =SUM(B26:AE26) -> 0
A27: ='Section-Category'!A13 -> Investments | AF27: =SUM(B27:AE27) -> 0
A28: ='Section-Category'!A14 -> Pocket Money Wife | AF28: =SUM(B28:AE28) -> 0
A29: ='Section-Category'!A15 -> <Name-Of-Entry> | AF29: =SUM(B29:AE29) -> 0
A30: ='Section-Category'!A16 -> <Name-Of-Entry> | AF30: =SUM(B30:AE30) -> 0
A31: ='Section-Category'!A17 -> Total SAVINGS EXPENSE | B31: =SUM(B26:B30) -> 0 | C31: =SUM(C26:C30) -> 0 | D31: =SUM(D26:D30) -> 0 | E31: =SUM(E26:E30) -> 0 | F31: =SUM(F26:F30) -> 0 | G31: =SUM(G26:G30) -> 0 | H31: =SUM(H26:H30) -> 0 | I31: =SUM(I26:I30) -> 0 | ... AF31: =SUM(AF26:AF30) -> 0
A33: ='Section-Category'!A20 -> HOME EXPENSES | AF33: Total
A34: ='Section-Category'!A21 -> Mortgage/Rent | AF34: =SUM(B34:AE34) -> 0
A35: ='Section-Category'!A22 -> Electricity | AF35: =SUM(B35:AE35) -> 0
A36: ='Section-Category'!A23 -> Gas/Oil | AF36: =SUM(B36:AE36) -> 0
A37: ='Section-Category'!A24 -> Water/Sewer/Trash | AF37: =SUM(B37:AE37) -> 0
A38: ='Section-Category'!A25 -> Phone | AF38: =SUM(B38:AE38) -> 0
A39: ='Section-Category'!A26 -> Cable/Satellite | AF39: =SUM(B39:AE39) -> 0
A40: ='Section-Category'!A27 -> Internet | AF40: =SUM(B40:AE40) -> 0
A41: ='Section-Category'!A28 -> Furnishings/Appliances | AF41: =SUM(B41:AE41) -> 0
A42: ='Section-Category'!A29 -> Lawn/Garden | AF42: =SUM(B42:AE42) -> 0
A43: ='Section-Category'!A30 -> Home Supplies | AF43: =SUM(B43:AE43) -> 0
A44: ='Section-Category'!A31 -> Maintenance | AF44: =SUM(B44:AE44) -> 0
A45: ='Section-Category'!A32 -> Improvements | AF45: =SUM(B45:AE45) -> 0
A46: ='Section-Category'!A33 -> Other | AF46: =SUM(B46:AE46) -> 0
A47: ='Section-Category'!A34 -> Total HOME EXPENSES | B47: =SUM(B34:B46) -> 0 | C47: =SUM(C34:C46) -> 0 | D47: =SUM(D34:D46) -> 0 | E47: =SUM(E34:E46) -> 0 | F47: =SUM(F34:F46) -> 0 | G47: =SUM(G34:G46) -> 0 | H47: =SUM(H34:H46) -> 0 | I47: =SUM(I34:I46) -> 0 | ... AF47: =SUM(AF34:AF46) -> 0
A49: ='Section-Category'!A37 -> DAILY LIVING | AF49: Total
A50: ='Section-Category'!A38 -> Groceries | AF50: =SUM(B50:AE50) -> 0
A51: ='Section-Category'!A39 -> Personal Supplies | AF51: =SUM(B51:AE51) -> 0
A52: ='Section-Category'!A40 -> Clothing | AF52: =SUM(B52:AE52) -> 0
A53: ='Section-Category'!A41 -> Cleaning Services | AF53: =SUM(B53:AE53) -> 0
A54: ='Section-Category'!A42 -> Dining/Eating Out | AF54: =SUM(B54:AE54) -> 0
A55: ='Section-Category'!A43 -> Dry Cleaning | AF55: =SUM(B55:AE55) -> 0
A56: ='Section-Category'!A44 -> Salon/Barber | AF56: =SUM(B56:AE56) -> 0
A57: ='Section-Category'!A45 -> FoodPanda | AF57: =SUM(B57:AE57) -> 0
A58: ='Section-Category'!A46 -> JazzCash/EasyPaisa | AF58: =SUM(B58:AE58) -> 0
A59: ='Section-Category'!A47 -> Other | AF59: =SUM(B59:AE59) -> 0
A60: ='Section-Category'!A48 -> Total DAILY LIVING | B60: =SUM(B50:B59) -> 0 | C60: =SUM(C50:C59) -> 0 | D60: =SUM(D50:D59) -> 0 | E60: =SUM(E50:E59) -> 0 | F60: =SUM(F50:F59) -> 0 | G60: =SUM(G50:G59) -> 0 | H60: =SUM(H50:H59) -> 0 | I60: =SUM(I50:I59) -> 0 | ... AF60: =SUM(AF50:AF59) -> 0
A62: ='Section-Category'!A51 -> CHILDREN | AF62: Total
A63: ='Section-Category'!A52 -> Medical | AF63: =SUM(B63:AE63) -> 0
A64: ='Section-Category'!A53 -> Clothing | AF64: =SUM(B64:AE64) -> 0
A65: ='Section-Category'!A54 -> School Tuition | AF65: =SUM(B65:AE65) -> 0
A66: ='Section-Category'!A55 -> School Lunch | AF66: =SUM(B66:AE66) -> 0
A67: ='Section-Category'!A56 -> School Supplies | AF67: =SUM(B67:AE67) -> 0
A68: ='Section-Category'!A57 -> Babysitting | AF68: =SUM(B68:AE68) -> 0
A69: ='Section-Category'!A58 -> Toys/Games | AF69: =SUM(B69:AE69) -> 0
A70: ='Section-Category'!A59 -> Other | AF70: =SUM(B70:AE70) -> 0
A71: ='Section-Category'!A60 -> Total CHILDREN | B71: =SUM(B63:B70) -> 0 | C71: =SUM(C63:C70) -> 0 | D71: =SUM(D63:D70) -> 0 | E71: =SUM(E63:E70) -> 0 | F71: =SUM(F63:F70) -> 0 | G71: =SUM(G63:G70) -> 0 | H71: =SUM(H63:H70) -> 0 | I71: =SUM(I63:I70) -> 0 | ... AF71: =SUM(AF63:AF70) -> 0
A73: ='Section-Category'!A63 -> TRANSPORTATION | AF73: Total
A74: ='Section-Category'!A64 -> Vehicle Payments | AF74: =SUM(B74:AE74) -> 0
A75: ='Section-Category'!A65 -> Fuel | AF75: =SUM(B75:AE75) -> 0
A76: ='Section-Category'!A66 -> Bus/Taxi/Train Fare | AF76: =SUM(B76:AE76) -> 0
A77: ='Section-Category'!A67 -> Repairs | AF77: =SUM(B77:AE77) -> 0
A78: ='Section-Category'!A68 -> Registration/License | AF78: =SUM(B78:AE78) -> 0
A79: ='Section-Category'!A69 -> Other | AF79: =SUM(B79:AE79) -> 0
A80: ='Section-Category'!A70 -> Total TRANSPORTATION | B80: =SUM(B74:B79) -> 0 | C80: =SUM(C74:C79) -> 0 | D80: =SUM(D74:D79) -> 0 | E80: =SUM(E74:E79) -> 0 | F80: =SUM(F74:F79) -> 0 | G80: =SUM(G74:G79) -> 0 | H80: =SUM(H74:H79) -> 0 | I80: =SUM(I74:I79) -> 0 | ... AF80: =SUM(AF74:AF79) -> 0
A82: ='Section-Category'!A73 -> HEALTH | AF82: Total
A83: ='Section-Category'!A74 -> Doctor/Dentist | AF83: =SUM(B83:AE83) -> 0
A84: ='Section-Category'!A75 -> Medicine/Drugs | AF84: =SUM(B84:AE84) -> 0
A85: ='Section-Category'!A76 -> Lab Test | AF85: =SUM(B85:AE85) -> 0
A86: ='Section-Category'!A77 -> Consultation | AF86: =SUM(B86:AE86) -> 0
A87: ='Section-Category'!A78 -> Other | AF87: =SUM(B87:AE87) -> 0
A88: ='Section-Category'!A79 -> Total HEALTH | B88: =SUM(B83:B87) -> 0 | C88: =SUM(C83:C87) -> 0 | D88: =SUM(D83:D87) -> 0 | E88: =SUM(E83:E87) -> 0 | F88: =SUM(F83:F87) -> 0 | G88: =SUM(G83:G87) -> 0 | H88: =SUM(H83:H87) -> 0 | I88: =SUM(I83:I87) -> 0 | ... AF88: =SUM(AF83:AF87) -> 0
A90: ='Section-Category'!A94 -> EDUCATION | AF90: Total
A91: ='Section-Category'!A95 -> Tuition | AF91: =SUM(B91:AE91) -> 0
A92: ='Section-Category'!A96 -> Books | AF92: =SUM(B92:AE92) -> 0
A93: ='Section-Category'!A97 -> Music Lessons | AF93: =SUM(B93:AE93) -> 0
A94: ='Section-Category'!A98 -> Other | AF94: =SUM(B94:AE94) -> 0
A95: ='Section-Category'!A99 -> Total EDUCATION | B95: =SUM(B91:B94) -> 0 | C95: =SUM(C91:C94) -> 0 | D95: =SUM(D91:D94) -> 0 | E95: =SUM(E91:E94) -> 0 | F95: =SUM(F91:F94) -> 0 | G95: =SUM(G91:G94) -> 0 | H95: =SUM(H91:H94) -> 0 | I95: =SUM(I91:I94) -> 0 | ... AF95: =SUM(AF91:AF94) -> 0
A97: ='Section-Category'!A102 -> CHARITY/GIFTS | AF97: Total
A98: ='Section-Category'!A103 -> Gifts Given | AF98: =SUM(B98:AE98) -> 0
A99: ='Section-Category'!A104 -> Couple Charity | AF99: =SUM(B99:AE99) -> 0
A100: ='Section-Category'!A105 -> Mother Charity | AF100: =SUM(B100:AE100) -> 0
A101: ='Section-Category'!A106 -> Other | AF101: =SUM(B101:AE101) -> 0
A102: ='Section-Category'!A107 -> Total CHARITY/GIFTS | B102: =SUM(B98:B101) -> 0 | C102: =SUM(C98:C101) -> 0 | D102: =SUM(D98:D101) -> 0 | E102: =SUM(E98:E101) -> 0 | F102: =SUM(F98:F101) -> 0 | G102: =SUM(G98:G101) -> 0 | H102: =SUM(H98:H101) -> 0 | I102: =SUM(I98:I101) -> 0 | ... AF102: =SUM(AF98:AF101) -> 0
A104: ='Section-Category'!A110 -> OBLIGATIONS | AF104: Total
A105: ='Section-Category'!A111 -> Credit Card Debt | AF105: =SUM(B105:AE105) -> 0
A106: ='Section-Category'!A112 -> Punjab ST on CC Fee @16 | AF106: =SUM(B106:AE106) -> 0
A107: ='Section-Category'!A113 -> Advance Tax 5% | AF107: =SUM(B107:AE107) -> 0
A108: ='Section-Category'!A114 -> Other | AF108: =SUM(B108:AE108) -> 0
A109: ='Section-Category'!A115 -> Total OBLIGATIONS | B109: =SUM(B105:B108) -> 0 | C109: =SUM(C105:C108) -> 0 | D109: =SUM(D105:D108) -> 0 | E109: =SUM(E105:E108) -> 0 | F109: =SUM(F105:F108) -> 0 | G109: =SUM(G105:G108) -> 0 | H109: =SUM(H105:H108) -> 0 | I109: =SUM(I105:I108) -> 0 | ... AF109: =SUM(AF105:AF108) -> 0
A111: ='Section-Category'!A118 -> 0
A112: ='Section-Category'!A119 -> <Name-Of-Entry>
...

Sheet Aug
A1: =MID(CELL("filename",A1),FIND("]",CELL("filename",A1))+1,255) -> Aug | B1: =Budget!D1 -> 2026
A2: Summary/Date | B2: ='Section-Category'!D13 -> 46235 | C2: ='Section-Category'!E12 -> 46205 | D2: ='Section-Category'!F12 -> 46206 | E2: ='Section-Category'!G12 -> 46207 | F2: ='Section-Category'!H12 -> 46208 | G2: ='Section-Category'!I12 -> 46209 | H2: ='Section-Category'!J12 -> 46210 | I2: ='Section-Category'!K12 -> 46211 | J2: ='Section-Category'!L12 -> 46212 | ... AE2: ='Section-Category'!AG12 -> 46233 | AF2: Total Sum
A4: INCOME | AF4: Total
A5: Wages & Tips | AF5: =SUM(B5:AE5) -> 0
A6: Interest Income | AF6: =SUM(B6:AE6) -> 0
A7: Dividends | AF7: =SUM(B7:AE7) -> 0
A8: Gifts Received | AF8: =SUM(B8:AE8) -> 0
A9: Refunds/Reimbursements | AF9: =SUM(B9:AE9) -> 0
A10: Other | AF10: =SUM(B10:AE10) -> 0
A11: Transfer From Savings | AF11: =SUM(B11:AE11) -> 0
A12: ='Section-Category'!A9 -> Total INCOME | B12: =SUM(B5:B11) -> 0 | C12: =SUM(C5:C11) -> 0 | D12: =SUM(D5:D11) -> 0 | E12: =SUM(E5:E11) -> 0 | F12: =SUM(F5:F11) -> 0 | G12: =SUM(G5:G11) -> 0 | H12: =SUM(H5:H11) -> 0 | I12: =SUM(I5:I11) -> 0 | ... AF12: =SUM(AF5:AF11) -> 0
A14: ='Section-Category'!A82 -> Petty Cash Used | AF14: Total
A15: ='Section-Category'!A83 -> Pocket Money Wife | AF15: =SUM(B15:AE15) -> 0
A16: ='Section-Category'!A84 -> Car Repair / Workshop | AF16: =SUM(B16:AE16) -> 0
A17: ='Section-Category'!A85 -> Food | AF17: =SUM(B17:AE17) -> 0
A18: ='Section-Category'!A86 -> Donation | AF18: =SUM(B18:AE18) -> 0
A19: Eidi | AF19: =SUM(B19:AE19) -> 0
A20: ='Section-Category'!A88 -> Donation | AF20: =SUM(B20:AE20) -> 0
A21: ='Section-Category'!A89 -> Pocket Money Husband | AF21: =SUM(B21:AE21) -> 0
A22: ='Section-Category'!A90 -> Other | AF22: =SUM(B22:AE22) -> 0
A23: ='Section-Category'!A91 -> Total Petty Cash Used | B23: =SUM(B15:B22) -> 0 | C23: =SUM(C15:C22) -> 0 | D23: =SUM(D15:D22) -> 0 | E23: =SUM(E15:E22) -> 0 | F23: =SUM(F15:F22) -> 0 | G23: =SUM(G15:G22) -> 0 | H23: =SUM(H15:H22) -> 0 | I23: =SUM(I15:I22) -> 0 | ... AF23: =SUM(AF15:AF22) -> 0
A25: ='Section-Category'!A11 -> SAVINGS EXPENSE | AF25: Total
A26: ='Section-Category'!A12 -> Emergency Fund | AF26: =SUM(B26:AE26) -> 0
A27: ='Section-Category'!A13 -> Investments | AF27: =SUM(B27:AE27) -> 0
A28: ='Section-Category'!A14 -> Pocket Money Wife | AF28: =SUM(B28:AE28) -> 0
A29: ='Section-Category'!A15 -> <Name-Of-Entry> | AF29: =SUM(B29:AE29) -> 0
A30: ='Section-Category'!A16 -> <Name-Of-Entry> | AF30: =SUM(B30:AE30) -> 0
A31: ='Section-Category'!A17 -> Total SAVINGS EXPENSE | B31: =SUM(B26:B30) -> 0 | C31: =SUM(C26:C30) -> 0 | D31: =SUM(D26:D30) -> 0 | E31: =SUM(E26:E30) -> 0 | F31: =SUM(F26:F30) -> 0 | G31: =SUM(G26:G30) -> 0 | H31: =SUM(H26:H30) -> 0 | I31: =SUM(I26:I30) -> 0 | ... AF31: =SUM(AF26:AF30) -> 0
A33: ='Section-Category'!A20 -> HOME EXPENSES | AF33: Total
A34: ='Section-Category'!A21 -> Mortgage/Rent | AF34: =SUM(B34:AE34) -> 0
A35: ='Section-Category'!A22 -> Electricity | AF35: =SUM(B35:AE35) -> 0
A36: ='Section-Category'!A23 -> Gas/Oil | AF36: =SUM(B36:AE36) -> 0
A37: ='Section-Category'!A24 -> Water/Sewer/Trash | AF37: =SUM(B37:AE37) -> 0
A38: ='Section-Category'!A25 -> Phone | AF38: =SUM(B38:AE38) -> 0
A39: ='Section-Category'!A26 -> Cable/Satellite | AF39: =SUM(B39:AE39) -> 0
A40: ='Section-Category'!A27 -> Internet | AF40: =SUM(B40:AE40) -> 0
A41: ='Section-Category'!A28 -> Furnishings/Appliances | AF41: =SUM(B41:AE41) -> 0
A42: ='Section-Category'!A29 -> Lawn/Garden | AF42: =SUM(B42:AE42) -> 0
A43: ='Section-Category'!A30 -> Home Supplies | AF43: =SUM(B43:AE43) -> 0
A44: ='Section-Category'!A31 -> Maintenance | AF44: =SUM(B44:AE44) -> 0
A45: ='Section-Category'!A32 -> Improvements | AF45: =SUM(B45:AE45) -> 0
A46: ='Section-Category'!A33 -> Other | AF46: =SUM(B46:AE46) -> 0
A47: ='Section-Category'!A34 -> Total HOME EXPENSES | B47: =SUM(B34:B46) -> 0 | C47: =SUM(C34:C46) -> 0 | D47: =SUM(D34:D46) -> 0 | E47: =SUM(E34:E46) -> 0 | F47: =SUM(F34:F46) -> 0 | G47: =SUM(G34:G46) -> 0 | H47: =SUM(H34:H46) -> 0 | I47: =SUM(I34:I46) -> 0 | ... AF47: =SUM(AF34:AF46) -> 0
A49: ='Section-Category'!A37 -> DAILY LIVING | AF49: Total
A50: ='Section-Category'!A38 -> Groceries | AF50: =SUM(B50:AE50) -> 0
A51: ='Section-Category'!A39 -> Personal Supplies | AF51: =SUM(B51:AE51) -> 0
A52: ='Section-Category'!A40 -> Clothing | AF52: =SUM(B52:AE52) -> 0
A53: ='Section-Category'!A41 -> Cleaning Services | AF53: =SUM(B53:AE53) -> 0
A54: ='Section-Category'!A42 -> Dining/Eating Out | AF54: =SUM(B54:AE54) -> 0
A55: ='Section-Category'!A43 -> Dry Cleaning | AF55: =SUM(B55:AE55) -> 0
A56: ='Section-Category'!A44 -> Salon/Barber | AF56: =SUM(B56:AE56) -> 0
A57: ='Section-Category'!A45 -> FoodPanda | AF57: =SUM(B57:AE57) -> 0
A58: ='Section-Category'!A46 -> JazzCash/EasyPaisa | AF58: =SUM(B58:AE58) -> 0
A59: ='Section-Category'!A47 -> Other | AF59: =SUM(B59:AE59) -> 0
A60: ='Section-Category'!A48 -> Total DAILY LIVING | B60: =SUM(B50:B59) -> 0 | C60: =SUM(C50:C59) -> 0 | D60: =SUM(D50:D59) -> 0 | E60: =SUM(E50:E59) -> 0 | F60: =SUM(F50:F59) -> 0 | G60: =SUM(G50:G59) -> 0 | H60: =SUM(H50:H59) -> 0 | I60: =SUM(I50:I59) -> 0 | ... AF60: =SUM(AF50:AF59) -> 0
A62: ='Section-Category'!A51 -> CHILDREN | AF62: Total
A63: ='Section-Category'!A52 -> Medical | AF63: =SUM(B63:AE63) -> 0
A64: ='Section-Category'!A53 -> Clothing | AF64: =SUM(B64:AE64) -> 0
A65: ='Section-Category'!A54 -> School Tuition | AF65: =SUM(B65:AE65) -> 0
A66: ='Section-Category'!A55 -> School Lunch | AF66: =SUM(B66:AE66) -> 0
A67: ='Section-Category'!A56 -> School Supplies | AF67: =SUM(B67:AE67) -> 0
A68: ='Section-Category'!A57 -> Babysitting | AF68: =SUM(B68:AE68) -> 0
